Workbook

Sheet Face Report

Sheet SOFP
A1: PT DUMMY - C DAN ENTITAS ANAK | N1: PT DUMMY - C AND SUBSIDIARIES
A2: LAPORAN POSISI KEUANGAN KONSOLIDASI | N2: CONSOLIDATED STATEMENTS OF FINANCIAL POSITION
A3: 31 DESEMBER 2024, 2023 DAN 2022 | N3: DECEMBER 31, 2024, 2023 AND 2022
A4: (Disajikan dalam Rupiah, kecuali dinyatakan lain) | N4: (Expressed in Rupiah, unless otherwise stated)
G7: Catatan/ | J7: 31 Desember 2024/ | L7: 31 Desember 2023/ | N7: 31 Desember 2022/
G8: Notes | J8: December 31, 2024 | L8: December 31, 2023 | N8: December 31, 2022
A10: ASET | P10: ASSETS
A11: ASET LANCAR | P11: CURRENT ASSETS
A12: Kas dan bank | J12: ='Consol SoFP 24'!AH15 -> 61178535792 | L12: ='Consol SoFP 23 & 22'!AE15 -> 75109486095 | N12: ='Consol SoFP 23 & 22'!BF15 -> 40661258337 | P12: Cash and banks
A13: Piutang usaha | J13: =SUM('Consol SoFP 24'!AH17:AH18,'Consol SoFP 24'!AH20) -> 244672056004 | L13: =SUM('Consol SoFP 23 & 22'!AE17:AE18,'Consol SoFP 23 & 22'!AE20) -> 323260364520 | N13: =SUM('Consol SoFP 23 & 22'!BF17:BF18) -> 227940501708 | P13: Trade receivables
A14: Piutang sewa | J14: ='Consol SoFP 24'!AH22 -> 5217740512 | L14: ='Consol SoFP 23 & 22'!AE22 -> 15830303102 | N14: ='Consol SoFP 23 & 22'!BF22 -> 14442442151 | P14: Lease Receivables
A15: Piutang lain-lain | J15: =SUM('Consol SoFP 24'!AH23,'Consol SoFP 24'!AH28:AH29,'Consol SoFP 24'!AH25) -> 62971200011 | L15: =SUM('Consol SoFP 23 & 22'!AE28:AE29) -> 38356602143 | N15: ='Consol SoFP 23 & 22'!BF28 -> 5434584686 | P15: Other receivables
A16: Piutang pihak berelasi | J16: =SUM('Consol SoFP 24'!AH26) -> 131678101647 | L16: ='Consol SoFP 23 & 22'!AE26 -> 20326406410 | N16: ='Consol SoFP 23 & 22'!BF26 -> 5180796035 | P16: Due from related parties
A17: Beban dibayar dimuka | J17: ='Consol SoFP 24'!AH31 -> 6267463919 | L17: ='Consol SoFP 23 & 22'!AE32 -> 11811728970 | N17: ='Consol SoFP 23 & 22'!BF32 -> 46432019959 | P17: Prepayments
A18: Pajak dibayar dimuka | J18: ='Consol SoFP 24'!AH32 -> 9836948341 | L18: ='Consol SoFP 23 & 22'!AE31 -> 2623976876 | N18: ='Consol SoFP 23 & 22'!BF31 -> 90969692 | P18: Prepaid taxes
A19: Restricted cash | J19: ='Consol SoFP 24'!AH34 -> 143195607918 | L19: ='Consol SoFP 23 & 22'!AE34 -> 159588593589 | N19: ='Consol SoFP 23 & 22'!BF34 -> 55354071673 | P19: Restricted cash
A20: Aset lancar lain-lain | J20: =SUM('Consol SoFP 24'!AH33,'Consol SoFP 24'!AH30,'Consol SoFP 24'!AH35) -> 2036699933 | L20: ='Consol SoFP 23 & 22'!AE35 -> 24013216750 | N20: ='Consol SoFP 23 & 22'!BF35 -> 12634397153 | P20: Other current assets
A22: Total Aset Lancar | J22: =SUM(J12:J20) -> 667054354077 | L22: =SUM(L12:L20) -> 670920678455 | N22: =SUM(N12:N20) -> 408171041394 | P22: Total current assets
A24: ASET TIDAK LANCAR | P24: NON-CURRENT ASSETS
A25: Piutang sewa - tidak lancar | J25: 0 | L25: ='Consol SoFP 23 & 22'!AE42 -> 2156177190 | N25: ='Consol SoFP 23 & 22'!BF42 -> 14398163289 | P25: Prepayments
A26: Aset tetap - bersih | J26: ='Consol SoFP 24'!AH43 -> 71907700936 | L26: ='Consol SoFP 23 & 22'!AE44 -> 21832710982 | N26: ='Consol SoFP 23 & 22'!BF44 -> 35664033274 | P26: Fixed assets - net
A27: Aset Hak Guna | J27: ='Consol SoFP 24'!AH45 -> 36242446809 | L27: ='Consol SoFP 23 & 22'!AE46 -> 11843914378 | N27: ='Consol SoFP 23 & 22'!BF46 -> 140145541230 | P27: Right of use assets
A28: Aset tak berwujud - bersih | J28: ='Consol SoFP 24'!AH44 -> 16469508674 | L28: ='Consol SoFP 23 & 22'!AE45 -> 24886088064 | N28: ='Consol SoFP 23 & 22'!BF45 -> 43488307487 | P28: Intangible assets - net
A29: Piutang Pemegang saham | J29: ='Consol SoFP 24'!AH46 -> 2314180101 | L29: ='Consol SoFP 23 & 22'!AE47 -> 2482200000 | N29: ='Consol SoFP 23 & 22'!BF47 -> 874125000 | P29: Shareholder Receivable
A30: Investasi | J30: 0 | L30: 0 | N30: 0 | P30: Investment
A31: Aset tidak lancar lainnya | J31: ='Consol SoFP 24'!AH49 -> 84860041916 | L31: ='Consol SoFP 23 & 22'!AE50 -> 12960995205 | N31: ='Consol SoFP 23 & 22'!BF50+'Consol SoFP 23 & 22'!BF48 -> 10947704500 | P31: Other non-current assets
A33: Total Aset Tidak Lancar | J33: =SUM(J25:J31) -> 211793878436 | L33: =SUM(L25:L31) -> 76162085819 | N33: =SUM(N25:N31) -> 245517874780 | P33: Total Non - Current Assets
A35: TOTAL ASET | J35: =+J22+J33 -> 878848232513 | L35: =+L22+L33 -> 747082764274 | N35: =+N22+N33 -> 653688916174 | P35: TOTAL ASSETS
A37: LIABILITAS DAN EKUITAS | P37: LIABILITES AND EQUITY
A39: LIABILITAS JANGKA PENDEK | P39: CURRENT LIABILITIES
A40: Utang usaha dan utang lain-lain | J40: =-SUM('Consol SoFP 24'!AH59:AH60,'Consol SoFP 24'!AH68:AH69) -> 100244378567 | L40: =-SUM('Consol SoFP 23 & 22'!AE60:AE61,'Consol SoFP 23 & 22'!AE70) -> 53941650149 | N40: =-'Consol SoFP 23 & 22'!BF60 -> 35633999745 | P40: Trade and other payables
A41: Utang sewa | J41: =-'Consol SoFP 24'!AH75 -> 44246726806 | L41: =-'Consol SoFP 23 & 22'!AE75 -> 57438550502 | N41: =-'Consol SoFP 23 & 22'!BF75 -> 52729712992 | P41: Lease Payables
A42: Utang bank jangka pendek | J42: =-SUM('Consol SoFP 24'!AH57) -> 109688388792 | L42: =-'Consol SoFP 23 & 22'!AE58 -> 141442017128 | N42: =-'Consol SoFP 23 & 22'!BF58 -> 43196374892 | P42: Short-term Bank Loan
A43: Utang Deposit | J43: =-'Consol SoFP 24'!AH64 -> 1597985933 | L43: =-'Consol SoFP 23 & 22'!AE65 -> 3998598175 | N43: =-'Consol SoFP 23 & 22'!BF65 -> 6108774604 | P43: Deposit payable
A44: Biaya yang masih harus dibayar | J44: =-SUM('Consol SoFP 24'!AH62:AH63) -> 28052747312 | L44: =-SUM('Consol SoFP 23 & 22'!AE63:AE64) -> 59423529841 | N44: =-SUM('Consol SoFP 23 & 22'!BF63:BF64) -> 83657606012 | P44: Accruals
A45: Utang Pembiayaan - jangka pendek | J45: =-'Consol SoFP 24'!AH71 -> 0 | L45: 0 | N45: 0 | P45: Consumer Financing Payables - Current Portion
A46: Pendapatan diterima dimuka | J46: =-'Consol SoFP 24'!AH74 -> 22024685439 | P46: Unearned Revenue
A47: Utang pihak berelasi | J47: =-'Consol SoFP 24'!AH66 -> 81841385213 | L47: =-'Consol SoFP 23 & 22'!AE67 -> 15917342497 | N47: =-'Consol SoFP 23 & 22'!BF67 -> 40302224 | P47: Due to related parties
A48: Utang pajak lainnya | J48: =-'Consol SoFP 24'!AH65 -> 351201384 | L48: =-'Consol SoFP 23 & 22'!AE66 -> 5484244074 | N48: =-'Consol SoFP 23 & 22'!BF66 -> 8775032472 | P48: Taxes payable - other taxes
A50: Total Liabilitas Jangka Pendek | J50: =SUM(J40:J48) -> 388047499446 | L50: =SUM(L40:L48) -> 337645932366 | N50: =SUM(N40:N48) -> 230141802941 | P50: Total Current Liabilities
A52: LIABILITAS JANGKA PANJANG | P52: NON-CURRENT LIABILITIES
A53: Utang sewa - tidak lancar | J53: =-'Consol SoFP 24'!AH81 -> 54385084988 | L53: =-'Consol SoFP 23 & 22'!AE81 -> 32226982313 | N53: =-'Consol SoFP 23 & 22'!BF81 -> 72365951559 | P53: Lease liabilities - non current
A54: Utang Pembiayaan | J54: =-'Consol SoFP 24'!AH82 -> 0 | L54: 0 | N54: 0 | P54: Consumer Financing
A55: Liabilitas imbalan kerja | J55: =-'Consol SoFP 24'!AH83 -> 4853302291 | L55: =-'Consol SoFP 23 & 22'!AE82 -> 4853302291 | N55: =-'Consol SoFP 23 & 22'!BF82 -> 4918246882 | P55: Employee benefits obligation
A56: Utang Pajak Tangguhan | J56: =-'Consol SoFP 24'!AH84 -> 11841969436 | L56: =-'Consol SoFP 23 & 22'!AE84 -> 11841969435 | N56: =-'Consol SoFP 23 & 22'!BF84 -> 3469782201 | P56: Deferred Tax Liabilities
A57: Utang tidak lancar lainya | J57: =-'Consol SoFP 24'!AH85 -> 4735334275 | L57: =-'Consol SoFP 23 & 22'!AE85 -> 4735334275 | N57: 0 | P57: Other non-current Liabilities
A59: Total Liabilitas Jangka Panjang | J59: =SUM(J53:J57) -> 75815690990 | L59: =SUM(L53:L57) -> 53657588314 | N59: =SUM(N53:N57) -> 80753980642 | P59: Total Non - Current Liabilities
A61: TOTAL LIABILITAS | J61: =+J50+J59 -> 463863190436 | L61: =+L50+L59 -> 391303520680 | N61: =+N50+N59 -> 310895783583 | P61: TOTAL LIABILITIES
A63: EKUITAS | P63: EQUITY
A64: Modal saham | J64: =-'Consol SoFP 24'!AH93 -> 486708075000 | L64: =-'Consol SoFP 23 & 22'!AE93 -> 486708075000 | N64: =-'Consol SoFP 23 & 22'!BF93 -> 142427250000 | P64: Share capital
A65: Akumulasi rugi | J65: =-SUM('Consol SoFP 24'!AH101:AH102) -> -902232119329 | L65: =-SUM('Consol SoFP 23 & 22'!AE101:AE102) -> -649879728743 | N65: =-SUM('Consol SoFP 23 & 22'!BF101:BF102) -> -323673912325 | P65: Accumulated gain/losses
A66: Penghasilan Komperhensif Lainya | J66: =-'Consol SoFP 24'!AH104 -> 1505283289 | L66: =-SUM('Consol SoFP 23 & 22'!AE104:AE105) -> 1505283288 | N66: =-SUM('Consol SoFP 23 & 22'!BF104:BF105) -> 890579715 | P66: Other Comperhensive Income
A67: Uang muka untuk modal saham | J67: =-'Consol SoFP 24'!AH94 -> 1608246198282 | L67: =-'Consol SoFP 23 & 22'!AE94 -> 1003275649843 | N67: =-'Consol SoFP 23 & 22'!BF94 -> 357853579198 | P67: Advance for share capital
A68: Cadangan kompensasi berbasis saham | J68: =-'Consol SoFP 24'!AH98 -> 42384330497 | L68: =-SUM('Consol SoFP 23 & 22'!AE97:AE98) -> 42384330497 | N68: =-SUM('Consol SoFP 23 & 22'!BF97:BF98) -> 28533901860 | P68: Share-based compensation reserve
A69: Selisih Nilai Transaksi entitas sepengendali | J69: =-'Consol SoFP 24'!AH96 -> -85320141313 | L69: 0 | N69: 0 | P69: Different value in transactions with entity under common control
A70: Proforma Modal | J70: 0 | L70: =-'Consol SoFP 23 & 22'!AE106 -> -55005764507 | N70: =-'Consol SoFP 23 & 22'!BF106 -> 2093719896 | P70: Capital proforma arising from restructuring under common control
A72: Total equity attributable to the Owners of the Company | J72: =SUM(J64:J70) -> 1151291626426 | L72: =SUM(L64:L70) -> 828987845378 | N72: =SUM(N64:N70) -> 208125118344 | P72: Total equity attributable to the Owners of the Company
A73: Kepentingan Non Pengendali | J73: =-'Consol SoFP 24'!AH110 -> -7.3630658e+11 | L73: =-'Consol SoFP 23 & 22'!AE110 -> -4.732086e+11 | N73: =-'Consol SoFP 23 & 22'!BF110 -> 134668014247 | P73: Non controlling Interest
A74: Total Ekuitas | J74: =SUM(J72:J73) -> 4.1498504e+11 | L74: =SUM(L72:L73) -> 3.5577924e+11 | N74: =SUM(N72:N73) -> 342793132591
A76: TOTAL LIABILITAS DAN EKUITAS | J76: =J61+J74 -> 8.7884823e+11 | L76: =L74+L61 -> 7.4708276e+11 | N76: =N74+N61 -> 653688916174 | P76: TOTAL LIABILITIES AND EQUITY
J78: =J35-J76 -> -0.46325684 | L78: =L35-L76 -> -0.31237793 | N78: =N35-N76 -> 0
A80: Catatan atas laporan keuangan merupakan bagian yang | N80: The accompanying notes to financial statements
A81: tidak terpisahkan dari laporan keuangan secara keseluruhan. | N81: are an integral part of these financial statements.

Sheet SOPL
A1: PT DUMMY - C DAN ENTITAS ANAK
A2: LAPORAN LABA RUGI DAN PENGHASILAN KONSOLIDASI | Q2: PT DUMMY - C AND ITS SUBSIDIARIES
A3: KOMPREHENSIF LAIN | Q3: CONSOLIDATED STATEMENTS OF PROFIT OR LOSS
A4: UNTUK TAHUN-TAHUN YANG BERAKHIR | Q4: AND OTHER COMPREHENSIVE INCOME
A5: 31 DESEMBER 2024, 2023 DAN 2022 | Q5: FOR THE YEARS ENDED DECEMBER 31, 2024, 2023 AND 2022
A6: (Disajikan dalam Rupiah, kecuali dinyatakan lain) | Q6: (Expressed in Rupiah, unless otherwise stated)
G9: Catatan/ | K9: Audited | N9: As restated | Q9: As restated
G10: Notes | K10: 2024 | N10: 2023 | Q10: 2022
A13: Pendapatan | K13: =-'Consol SoPL-OCI 24'!AG16 -> 7.8864517e+11 | N13: =-'Consol SoPL-OCI 23 & 22'!AC16 -> 913482303388 | Q13: =-'Consol SoPL-OCI 23 & 22'!BD16 -> 3.749433e+11 | S13: Revenue
A14: Beban Pokok Pendapatan | G14: 16 | K14: =-'Consol SoPL-OCI 24'!AG17 -> -6.9736014e+11 | N14: =-'Consol SoPL-OCI 23 & 22'!AC17 -> -966810700161 | Q14: =-'Consol SoPL-OCI 23 & 22'!BD17 -> -3.2414255e+11 | S14: Cost of Revenue
A16: LABA BRUTO | K16: =SUM(K13:K14) -> 9.128503e+10 | N16: =SUM(N13:N14) -> -53328396773 | Q16: =SUM(Q13:Q14) -> 5.0800755e+10 | S16: GROSS PROFIT
A18: BEBAN USAHA | S18: OPERATING EXPENSES
A20: Umum dan administrasi | K20: =-'Consol SoPL-OCI 24'!AG24 -> -5.6012593e+11 | N20: =-'Consol SoPL-OCI 23 & 22'!AC24 -> -799753482326 | Q20: =-'Consol SoPL-OCI 23 & 22'!BD24 -> -5.673036e+11 | S20: General and administration
A21: Penjualan dan Pemasaran | K21: =-'Consol SoPL-OCI 24'!AG23 -> -7.2626305e+09 | N21: =-'Consol SoPL-OCI 23 & 22'!AC23 -> -32112230024 | Q21: =-'Consol SoPL-OCI 23 & 22'!BD23 -> -2.3395208e+10 | S21: Sales and Marketing
A22: Rugi penurunan nilai aset tetap, aset takberwujud dan aset hak guna | S22: Impairment Loss on fixed assets, intangible assets and
A23: dan aset hak guna | K23: =-'Consol SoPL-OCI 24'!AG27 -> 0 | N23: =-'Consol SoPL-OCI 23 & 22'!AC27 -> -32453747018 | Q23: =-'Consol SoPL-OCI 23 & 22'!BD27 -> 1.3268913e+09 | S23: Right of used assets
A24: Depresiasi dan Amortisasi | K24: =-'Consol SoPL-OCI 24'!AG25 -> -2.4155198e+10 | N24: =-'Consol SoPL-OCI 23 & 22'!AC25 -> -30622890261 | Q24: =-'Consol SoPL-OCI 23 & 22'!BD25 -> -9.2150701e+09 | S24: Depreciation and Amortization
A25: Kerugian penurunan nilai aset keuangan | K25: =-'Consol SoPL-OCI 24'!AG26 -> -11266205309 | N25: =-'Consol SoPL-OCI 23 & 22'!AC26 -> -1899458800 | Q25: =-'Consol SoPL-OCI 23 & 22'!BD26 -> -4.08681e+10 | S25: Professional fees
A26: Lain-lain, bersih | K26: =-'Consol SoPL-OCI 24'!AG28-'Consol SoPL-OCI 24'!AG38 -> -4.2550162e+09 | N26: =-'Consol SoPL-OCI 23 & 22'!AC28-'Consol SoPL-OCI 23 & 22'!AC38 -> -24815839951 | Q26: =-'Consol SoPL-OCI 23 & 22'!BD28-'Consol SoPL-OCI 23 & 22'!BD38 -> 29660476 | S26: Others - net
A28: Total Beban Usaha | K28: =SUM(K20:K26) -> -6.0706498e+11 | N28: =SUM(N20:N26) -> -921657648380 | Q28: =SUM(Q20:Q26) -> -6.3942542e+11 | S28: Total Operating Expense
A30: RUGI USAHA | K30: =K16+K28 -> -5.1577995e+11 | N30: =N16+N28 -> -974986045153 | Q30: =Q16+Q28 -> -5.8862467e+11 | S30: OPERATING LOSS
A32: PENGHASILAN (BEBAN) LAIN-LAIN | S32: OTHER INCOME (EXPENSES)
A33: Penghasilan Bunga | K33: =-'Consol SoPL-OCI 24'!AG35 -> 8.0255535e+09 | N33: =-'Consol SoPL-OCI 23 & 22'!AC35 -> 8.605882e+09 | Q33: =-'Consol SoPL-OCI 23 & 22'!BD35 -> 5.6403384e+09 | S33: Interest Income
A34: Beban Bunga | K34: =-'Consol SoPL-OCI 24'!AG36 -> -1.2803155e+10 | N34: =-'Consol SoPL-OCI 23 & 22'!AC36 -> -3.1914224e+10 | Q34: =-'Consol SoPL-OCI 23 & 22'!BD36 -> -1.4054873e+10 | S34: Interest Expense
A35: Untung Selisih Kurs Neto | K35: =-'Consol SoPL-OCI 24'!AG37 -> -939065125 | N35: =-'Consol SoPL-OCI 23 & 22'!AC37 -> 1566688058 | Q35: =-'Consol SoPL-OCI 23 & 22'!BD37 -> 51355510 | S35: Gain On foreign exchange, net
A37: Total beban lain-lain, neto | K37: =SUM(K31:K35) -> -5.7166663e+09 | N37: =SUM(N31:N35) -> -2.1741654e+10 | Q37: =SUM(Q31:Q35) -> -8.3631792e+09 | S37: Total other expenses, net
A39: RUGI SEBELUM BEBAN PAJAK
A40: PENGHASILAN | K40: =K30+K37 -> -5.2149661e+11 | N40: =N30+N37 -> -9.967277e+11 | Q40: =Q30+Q37 -> -5.9698785e+11 | S40: LOSS BEFORE INCOME TAX EXPENSE
A42: BEBAN PAJAK PENGHASILAN | K42: 0 | N42: =-'Consol SoPL-OCI 23 & 22'!AC56 -> -8372187235 | Q42: =-'Consol SoPL-OCI 23 & 22'!BD56 -> -3.4697822e+09 | S42: INCOME TAX EXPENSE
A44: RUGI TAHUN BERJALAN SEBELUM | S44: LOSS FOR THE YEAR BEFORE
A45: EFEK PENYESUAIAN PROFORMA | K45: =K40+K42 -> -5.2149661e+11 | N45: =N40+N42 -> -1.0050999e+12 | Q45: =Q40+Q42 -> -6.0045763e+11 | S45: EFFECT OF PROFORMA ADJUSTMENT
A47: EFEK DARI PENYESUAIAN PROFORMA | S47: EFFECT OF PROFORMA ADJUSTMENT
A48: ATAS LABA TAHUN BERJALAN | K48: =-'Consol SoPL-OCI 24'!AG61 -> 6.0462397e+09 | N48: =-'Consol SoPL-OCI 23 & 22'!AC61 -> 5.8403962e+10 | Q48: =-'Consol SoPL-OCI 23 & 22'!BD61 -> 3.3149995e+10 | S48: ON NET INCOME FOR THE YEAR
A50: RUGI TAHUN BERJALAN | K50: =K48+K45 -> -5.1545037e+11 | N50: =N48+N45 -> -9.4669592e+11 | Q50: =Q48+Q45 -> -5.6730763e+11 | S50: LOSS FOR THE YEAR
A52: PENGHASILAN KOMPERHENSIF LAIN | S52: OTHER COMPERHENSIVE INCOME
A53: Item yang tidak akan direklasifikasi ke laba rugi: | S53: Items that will not be reclassified to profit or loss:
A54: - Pengukuran kembali liabilitas imbalan | S54: - Remerasurementof employee benefits
B55: kerja, setelah pajak | K55: 0 | N55: =-SUM('Consol SoPL-OCI 23 & 22'!AC66:AC67) -> 6.1470357e+08 | Q55: =-SUM('Consol SoPL-OCI 23 & 22'!BD66:BD67) -> 6.3235994e+08 | T55: obligation, net of tax
A57: JUMLAH PENGHASILAN (RUGI) KOMPREHENSIF | S57: TOTAL COMPREHENSIVE INCOME (LOSS)
B58: TAHUN BERJALAN | K58: =K50+K55 -> -5.1545037e+11 | N58: =N50+N55 -> -9.4608122e+11 | Q58: =Q50+Q55 -> -5.6667527e+11 | T58: FOR THE YEAR

Sheet SOCE
A2: PT Dummy C and its Subsidiaries
A3: Statement of Change in Equity
A4: For period end December 31, 2024 | V4: n
D7: Notes | F7: Share Capital | H7: Advance Capital | J7: Additional Paid in Capital | L7: Capital proforma arising from restructuring transactions of entities under common control | N7: Other Comperhensive Income | P7: Share-Based Compensation Reserve | R7: Retained Earnings | T7: Subtotal | V7: Non-controlling interest | X7: Total Equity | Z7: Control
B10: Balance as of December 31, 2022 Audited | F10: 142427250000 | H10: =-'Consol SoFP 23 & 22'!AJ94 -> 3.5785358e+11 | N10: =-'Consol SoFP 23 & 22'!AJ105-'Consol SoFP 23 & 22'!AJ104 -> 8.9057972e+08 | P10: =-SUM('Consol SoFP 23 & 22'!AJ97:AJ98) -> 2.8533902e+10 | R10: =-'Consol SoFP 23 & 22'!AJ102-'Consol SoFP 23 & 22'!AJ101 -> -3.2367391e+11 | T10: =SUM(F10,H10,J10,L10,N10,P10,R10) -> 2.060314e+11 | X10: =SUM(T10:V10) -> 2.060314e+11
B12: Restatement PSAK 22 in Subsidiaries | L12: 0 | T12: =SUM(F12,H12,J12,L12,N12,P12,R12) -> 0 | X12: =SUM(T12:V12) -> 0 | Z12: 0
B14: Restatement effect due to Proforma adjustment | L14: =-'Proforma Adjustment'!R15 -> 3.5078825e+10 | T14: =SUM(F14,H14,J14,L14,N14,P14,R14) -> 3.5078825e+10 | V14: =-SUM('NCI Detail & Movement'!P48,'NCI Detail & Movement'!P49,'NCI Detail & Movement'!P51,'NCI Detail & Movement'!P56) -> 5.192101e+11 | X14: =SUM(T14:V14) -> 5.5428892e+11 | Z14: 0
B16: Effect on proforma adjustment
B17: on current income for the year | L17: =-'Proforma Adjustment'!S15 -> -3.3149995e+10 | T17: =SUM(F17,H17,J17,L17,N17,P17,R17) -> -3.3149995e+10 | V17: =-'NCI Detail & Movement'!P50 -> -3.8937387e+11 | X17: =SUM(T17:V17) -> -4.2252387e+11 | Z17: 0
B19: Effect on proforma adjustment
B20: on Current year ESOP Reserve | L20: =-'Proforma Adjustment'!U15 -> 1.075576e+08 | T20: =SUM(F20,H20,J20,L20,N20,P20,R20) -> 1.075576e+08 | V20: =-'NCI Detail & Movement'!P52 -> 3.1517635e+09 | X20: =SUM(T20:V20) -> 3.2593211e+09 | Z20: 0
B22: Effect on proforma adjustment
B23: on Current Year OCI emben | L23: =-'Proforma Adjustment'!T15 -> 57332944 | T23: =SUM(F23,H23,J23,L23,N23,P23,R23) -> 57332944 | V23: =-'NCI Detail & Movement'!P54 -> 1.680029e+09 | X23: =SUM(T23:V23) -> 1.7373619e+09 | Z23: 0
B25: Balance as of December 31, 2022 as Restated | F25: =SUM(F10,F12,F14,F17,F20,F23) -> 142427250000 | H25: =SUM(H10,H12,H14,H17,H20,H23) -> 3.5785358e+11 | J25: =SUM(J10,J12,J14,J17,J20,J23) -> 0 | L25: =SUM(L10,L12,L14,L17,L20,L23) -> 2.0937199e+09 | N25: =SUM(N10,N12,N14,N17,N20,N23) -> 8.9057972e+08 | P25: =SUM(P10,P12,P14,P17,P20,P23) -> 2.8533902e+10 | R25: =SUM(R10,R12,R14,R17,R20,R23) -> -3.2367391e+11 | T25: =SUM(T10,T12,T14,T17,T20,T23) -> 2.0812512e+11 | V25: =SUM(V10,V12,V14,V17,V20,V23) -> 1.3466801e+11 | X25: =SUM(X10,X12,X14,X17,X20,X23) -> 3.4279313e+11
B27: Per SoFP | F27: ='Consol SoFP 23 & 22'!BF93 -> -142427250000 | H27: ='Consol SoFP 23 & 22'!BF94 -> -357853579198 | J27: ='Consol SoFP 23 & 22'!BF95 -> 0 | L27: ='Consol SoFP 23 & 22'!BF106 -> -2093719896 | N27: =SUM('Consol SoFP 23 & 22'!BF104:BF105) -> -890579715 | P27: =SUM('Consol SoFP 23 & 22'!BF97:BF98) -> -28533901860 | R27: =SUM('Consol SoFP 23 & 22'!BF101:BF102) -> 323673912325 | T27: ='Consol SoFP 23 & 22'!BF109 -> -208125118344 | V27: ='Consol SoFP 23 & 22'!BF110 -> -134668014247 | X27: ='Consol SoFP 23 & 22'!BF112 -> -342793132591
B28: Difference | F28: =ROUND(F25+F27,0) -> 0 | H28: =ROUND(H25+H27,0) -> 0 | J28: =ROUND(J25+J27,0) -> 0 | L28: =ROUND(L25+L27,0) -> 0 | N28: =ROUND(N25+N27,0) -> 0 | P28: =ROUND(P25+P27,0) -> 0 | R28: =ROUND(R25+R27,0) -> 0 | T28: =ROUND(T25+T27,0) -> 1 | V28: =ROUND(V25+V27,0) -> 0 | X28: =ROUND(X25+X27,0) -> 1
H29: =-H28 -> 0
B30: Advance for Share Capital | F30: 0 | H30: 9.897029e+11 | R30: 0 | T30: =SUM(F30,H30,J30,L30,N30,P30,R30) -> 9.897029e+11 | X30: =SUM(T30:V30) -> 9.897029e+11
B32: Issuance of share Capital | F32: 344280825000 | H32: =-F32 -> -344280825000 | T32: =SUM(F32,H32,J32,L32,N32,P32,R32) -> 0 | X32: =SUM(T32:V32) -> 0
B34: Net income for the year | R34: =-'Consol SoPL-OCI 23 & 22'!AC86 -> -3.2620582e+11 | T34: =SUM(F34,H34,J34,L34,N34,P34,R34) -> -3.2620582e+11 | X34: =SUM(T34:V34) -> -3.2620582e+11
B36: Remeasurement Empolyee Benefit | N36: =-'Consol SoFP 23 & 22'!AE105 -> 614703573 | R36: =-'Consol SoPL-OCI 23 & 22'!AC88 -> 0 | T36: =SUM(F36,H36,J36,L36,N36,P36,R36) -> 614703573 | X36: =SUM(T36:V36) -> 614703573
B38: Additional Share-based Reserved | P38: =-'Consol SoFP 23 & 22'!AE98 -> 13850428637 | R38: =-'Consol SoPL-OCI 23 & 22'!AC90 -> 0 | T38: =SUM(F38,H38,J38,L38,N38,P38,R38) -> 13850428637 | X38: =SUM(T38:V38) -> 13850428637
B40: Proforma Capital from issuance additional share
B41: in subsidiaries | L41: =-'Proforma Adjustment'!E78+'Proforma Adjustment'!D97 -> 1.0455437e+09 | R41: 0 | T41: =SUM(F41,H41,J41,L41,N41,P41,R41) -> 1.0455437e+09 | V41: =-'NCI Detail & Movement'!F200 -> 5.0259513e+09 | X41: =SUM(T41:V41) -> 6.071495e+09
B43: Effect on proforma adjustment
B44: on net income for the year | L44: =-'Capital Proforma Control'!P61 -> -5.8403962e+10 | T44: =SUM(F44,H44,J44,L44,N44,P44,R44) -> -5.8403962e+10 | V44: =-'Consol SoPL-OCI 23 & 22'!AC87 -> -6.2049011e+11 | X44: =SUM(T44:V44) -> -6.7889407e+11
B46: Effect on proforma adjustment
B47: on Current year ESOP Reserve | L47: =-'Proforma Adjustment'!E86 -> 231177233 | T47: =SUM(F47,H47,J47,L47,N47,P47,R47) -> 231177233 | V47: =-'NCI Detail & Movement'!L200 -> 6.7741935e+09 | X47: =SUM(T47:V47) -> 7.0053707e+09
B49: Effect on proforma adjustment
B50: on Current Year OCI emben | L50: =-'Proforma Adjustment'!E90 -> 27756416 | T50: =SUM(F50,H50,J50,L50,N50,P50,R50) -> 27756416 | V50: =-('Consol SoPL-OCI 23 & 22'!AB94-'Consol SoPL-OCI 23 & 22'!AB87) -> 8.133471e+08 | X50: =SUM(T50:V50) -> 8.4110352e+08
B52: Balance as of December 31, 2023 as restated | F52: =SUM(F25,F30,F32,F34,F36,F38,F41,F44,F47,F50) -> 486708075000 | H52: =SUM(H25,H30,H32,H34,H36,H38,H41,H44,H47,H50) -> 1.0032756e+12 | J52: =SUM(J25,J30,J32,J34,J36,J38,J41,J44,J47,J50) -> 0 | L52: =SUM(L25,L30,L32,L34,L36,L38,L41,L44,L47,L50) -> -5.5005765e+10 | N52: =SUM(N25,N30,N32,N34,N36,N38,N41,N44,N47,N50) -> 1.5052833e+09 | P52: =SUM(P25,P30,P32,P34,P36,P38,P41,P44,P47,P50) -> 4.238433e+10 | R52: =SUM(R25,R30,R32,R34,R36,R38,R41,R44,R47,R50) -> -6.4987973e+11 | T52: =SUM(T25,T30,T32,T34,T36,T38,T41,T44,T47,T50) -> 8.2898785e+11 | V52: =SUM(V25,V30,V32,V34,V36,V38,V41,V44,V47,V50) -> -4.732086e+11 | X52: =SUM(X25,X30,X32,X34,X36,X38,X41,X44,X47,X50) -> 3.5577924e+11
B54: Per SoFP | F54: ='Consol SoFP 23 & 22'!AE93 -> -486708075000 | H54: ='Consol SoFP 23 & 22'!AE94 -> -1003275649843 | J54: =SUM('Consol SoFP 23 & 22'!AE95) -> 0 | L54: ='Consol SoFP 23 & 22'!AE106 -> 55005764507 | N54: =SUM('Consol SoFP 23 & 22'!AE104:AE105) -> -1505283288 | P54: =SUM('Consol SoFP 23 & 22'!AE97:AE98) -> -42384330497 | R54: =SUM('Consol SoFP 23 & 22'!AE101:AE102) -> 649879728743 | T54: ='Consol SoFP 23 & 22'!AE109 -> -828987845378 | V54: ='Consol SoFP 23 & 22'!AE110 -> 4.732086e+11 | X54: ='Consol SoFP 23 & 22'!AE112 -> -3.5577924e+11
B55: Difference | F55: =ROUND(F52+F54,0) -> 0 | H55: =ROUND(H52+H54,0) -> 0 | J55: =ROUND(J52+J54,0) -> 0 | L55: =ROUND(L52+L54,0) -> 1 | N55: =N52+N54 -> 0.375 | P55: =ROUND(P52+P54,0) -> 0 | R55: =ROUND(R52+R54,0) -> 1 | T55: =ROUND(T52+T54,0) -> 3 | V55: =ROUND(V52+V54,0) -> -2 | X55: =ROUND(X52+X54,0) -> 1
B57: Advance for Share Capital | F57: 0 | R57: 0 | T57: =SUM(F57,H57,J57,L57,N57,P57,R57) -> 0 | X57: =SUM(T57:V57) -> 0
B59: Issuance of share Capital | H59: 604970548439 | T59: =SUM(F59,H59,J59,L59,N59,P59,R59) -> 604970548439 | X59: =SUM(T59:V59) -> 604970548439
B61: Reclassification Non-controlling Interest
B62: into Retained earning from indirect ownership in Subsidiaries | R62: 0 | T62: =SUM(F62,H62,J62,L62,N62,P62,R62) -> 0 | V62: 0 | X62: =SUM(T62:V62) -> 0
B64: Net income for the year | R64: =-'Consol SoPL-OCI 24'!AG87 -> -2.5235239e+11 | T64: =SUM(F64,H64,J64,L64,N64,P64,R64) -> -2.5235239e+11 | V64: =-'Consol SoPL-OCI 24'!AG88 -> -2.6309798e+11 | X64: =SUM(T64:V64) -> -5.1545037e+11
B66: Remeasurement Empolyee Benefit | N66: 0 | R66: 0 | T66: =SUM(F66,H66,J66,L66,N66,P66,R66) -> 0 | V66: 0 | X66: =SUM(T66:V66) -> 0
B68: Additional Share-based Reserved | P68: 0 | R68: 0 | T68: =SUM(F68,H68,J68,L68,N68,P68,R68) -> 0 | V68: 0 | X68: =SUM(T68:V68) -> 0
B70: Proforma Capital from issuance additional share
B71: in subsidiaries | R71: 0 | T71: =SUM(F71,H71,J71,L71,N71,P71,R71) -> 0 | V71: 0 | X71: =SUM(T71:V71) -> 0
B73: Effect on proforma adjustment
B74: on net income for the year | L74: ='Consol SoPL-OCI 24'!AA61 -> -6.0462397e+09 | T74: =SUM(F74,H74,J74,L74,N74,P74,R74) -> -6.0462397e+09 | X74: =SUM(T74:V74) -> -6.0462397e+09
B76: Business Combination entities
B77: under common control | J77: ='Capital Proforma Control'!T146 -> -8.5320141e+10 | L77: ='Capital Proforma Control'!N146 -> 6.1052004e+10 | T77: =SUM(F77,H77,J77,L77,N77,P77,R77) -> -2.4268137e+10 | X77: =SUM(T77:V77) -> -2.4268137e+10
B79: Effect on proforma adjustment
B80: on Current Year OCI emben | L80: =-'Proforma Adjustment'!E109 -> 0 | T80: =SUM(F80,H80,J80,L80,N80,P80,R80) -> 0 | X80: =SUM(T80:V80) -> 0
B82: Balance as of December 31, 2024 | F82: =SUM(F52,F57,F59,F64,F66,F68,F71,F74,F77,F80) -> 486708075000 | H82: =SUM(H52,H57,H59,H64,H66,H68,H71,H74,H77,H80) -> 1.6082462e+12 | J82: =SUM(J52,J57,J59,J64,J66,J68,J71,J74,J77,J80) -> -8.5320141e+10 | L82: =SUM(L52,L57,L59,L64,L66,L68,L71,L74,L77,L80) -> -0.17420197 | N82: =SUM(N52,N57,N59,N62,N64,N66,N68,N71,N74,N77,N80) -> 1.5052833e+09 | P82: =SUM(P52,P57,P59,P62,P64,P66,P68,P71,P74,P77,P80) -> 4.238433e+10 | R82: =SUM(R52,R57,R59,R62,R64,R66,R68,R71,R74,R77,R80) -> -9.0223212e+11 | T82: =SUM(T52,T57,T59,T62,T64,T66,T68,T71,T74,T77,T80) -> 1.1512916e+12 | V82: =SUM(V52,V57,V59,V62,V64,V66,V68,V71,V74,V77,V80) -> -7.3630658e+11 | X82: =SUM(X52,X57,X59,X64,X66,X68,X71,X74,X77,X80) -> 4.1498504e+11
B84: Per SoFP | F84: ='Consol SoFP 24'!AH93 -> -486708075000 | H84: ='Consol SoFP 24'!AH94 -> -1608246198282 | J84: ='Consol SoFP 24'!AH96 -> 85320141313 | N84: ='Consol SoFP 24'!AH104 -> -1505283289 | P84: ='Consol SoFP 24'!AH98 -> -42384330497 | R84: =SUM('Consol SoFP 24'!AH101:AH102) -> 902232119329 | T84: ='Consol SoFP 24'!AH109 -> -1151291626426 | V84: ='Consol SoFP 24'!AH110 -> 7.3630658e+11 | X84: ='Consol SoFP 24'!AH112 -> -4.1498504e+11
B85: Difference | F85: =ROUND(F82+F84,0) -> 0 | H85: =ROUND(H82+H84,0) -> 0 | J85: =ROUND(J82+J84,0) -> 0 | L85: =ROUND(L82+L84,0) -> 0 | N85: =N82+N84 -> -0.625 | P85: =ROUND(P82+P84,0) -> 0 | R85: =ROUND(R82+R84,0) -> -3 | T85: =ROUND(T82+T84,0) -> -3 | V85: =ROUND(V82+V84,0) -> 657 | X85: =ROUND(X82+X84,0) -> 655

Sheet CF 24
A1: PT Dummy - C and its subsidiaries | Z1: Restatement | AP1: Restatement | AY1: Restatement | AZ1: Restatement
A2: Consolidated Statement of Cash Flows
A3: December 31. 2024
E4: control | H4: =H97 -> 0 | I4: =I97 -> 0 | J4: =J97 -> 0 | K4: =K97 -> 0 | L4: =L97 -> 0 | M4: =M97 -> 0 | N4: =N97 -> 0 | O4: =O97 -> 0 | ... AF4: =AF97 -> 0 | AI4: =AI97 -> 0 | AJ4: =AJ97 -> 0 | AK4: =AK97 -> 0 | AL4: =AL97 -> 0 | AM4: =AM97 -> 0 | AN4: =AN97 -> 0 | AO4: =AO97 -> 0 | AP4: =AP97 -> 0 | AR4: =AR97 -> 0 | AS4: =AS97 -> 0 | AT4: =AT97 -> -0.27490234 | AU4: =AU97 -> 0 | AV4: =AV97 -> -1 | AW4: =AW97 -> -0.86421204 | AY4: =AY97 -> -3.8708801 | AZ4: =AZ97 -> 659.15817
F6: 0.42999268 | V6: Non-current asset
H7: Cash and cash equivalents | I7: Trade receivables, net | J7: Current portion of Lease receivables | K7: Loan Receivable Related Party, Net | L7: Other receivables net, | M7: Advance, prepaid expenses and other assets | N7: Restricted banks and time deposits (current and non-current) | O7: Prepaid tax | P7: Other Current Assets | Q7: Due from related parties, net (current and non-current) | R7: Lease receivables - non current | S7: Fixed assets, net | T7: Investment properties | U7: Right of use assets, net | V7: Intangible assets, net | W7: Shareholder Receivable | X7: Other non-current asset | Y7: Goodwill | Z7: Deferred tax assets, net | AA7: Deferred tax liabilities, net | AB7: Short-term bank loan | AC7: Trade payable | AD7: Other Payable | AE7: Deposit Payable | AF7: Loan Payable Related Party | AG7: Payable to Shareholder | AH7: Payable to Subsidiaries | AI7: Taxes payable | AJ7: Accrued expenses | AK7: Unearned Revenue | AL7: Borrowings | AM7: Liabilities related asset held for sale | AN7: Convertible bonds | AO7: Lease liabilities | AP7: Employee benefits liabilities | AQ7: Consumer Financing | AR7: Other Non current Liabilities | AS7: Share capital | AT7: Advance Capital | AU7: Share Based Compensation Reserve | AV7: Employee Benefit Liabilities | AW7: Capital proforma arising from restructuring transactions of entities under common control | AX7: SNTRESS | AY7: Retained earnings | AZ7: Non-controlling Interest | BA7: control
G8: 45657 | H8: ='Consol SoFP 24'!AH15 -> 61178535792 | I8: =SUM('Consol SoFP 24'!AH17:AH18,'Consol SoFP 24'!AH20) -> 244672056004 | J8: ='Consol SoFP 24'!AH22 -> 5217740512 | K8: =SUM('Consol SoFP 24'!AH25:AH26) -> 134787570854 | L8: =SUM('Consol SoFP 24'!AH28:AH29,'Consol SoFP 24'!AH23) -> 59861730804 | M8: =SUM('Consol SoFP 24'!AH32:AH33)+'Consol SoFP 24'!AH30 -> 10309535399 | N8: ='Consol SoFP 24'!AH34 -> 143195607918 | O8: ='Consol SoFP 24'!AH31 -> 6267463919 | P8: ='Consol SoFP 24'!AH35 -> 1564112875 | Q8: 0 | R8: ='Consol SoFP 24'!AH42 -> 0 | S8: ='Consol SoFP 24'!AH43 -> 71907700936 | U8: ='Consol SoFP 24'!AH45 -> 36242446809 | V8: ='Consol SoFP 24'!AH44 -> 16469508674 | W8: ='Consol SoFP 24'!AH46 -> 2314180101 | X8: ='Consol SoFP 24'!AH49 -> 84860041916 | AA8: ='Consol SoFP 24'!AH84 -> -11841969436 | AB8: ='Consol SoFP 24'!AH57 -> -109688388792 | AC8: =SUM('Consol SoFP 24'!AH59:AH60) -> -93585773120 | AD8: =SUM('Consol SoFP 24'!AH68:AH69) -> -6658605447 | AE8: ='Consol SoFP 24'!AH64 -> -1597985933 | AF8: ='Consol SoFP 24'!AH66 -> -81841385213 | AG8: ='Consol SoFP 24'!AH73 -> 0 | AH8: ='Consol SoFP 24'!AH72 -> 0 | AI8: ='Consol SoFP 24'!AH65 -> -351201384 | AJ8: =SUM('Consol SoFP 24'!AH62:AH63) -> -28052747312 | AK8: ='Consol SoFP 24'!AH74 -> -22024685439 | AL8: ='Consol SoFP 24'!AH71 -> 0 | AO8: ='Consol SoFP 24'!AH75+'Consol SoFP 24'!AH81 -> -98631811794 | AP8: ='Consol SoFP 24'!AH83 -> -4853302291 | AQ8: ='Consol SoFP 24'!AH82 -> 0 | AR8: ='Consol SoFP 24'!AH85 -> -4735334275 | AS8: ='Consol SoFP 24'!AH93 -> -486708075000 | AT8: ='Consol SoFP 24'!AH94 -> -1608246198282 | AU8: ='Consol SoFP 24'!AH98 -> -42384330497 | AV8: ='Consol SoFP 24'!AH104 -> -1505283289 | AX8: ='Consol SoFP 24'!AH96 -> 85320141313 | AY8: =SUM('Consol SoFP 24'!AH101:AH102) -> 902232119329 | AZ8: ='Consol SoFP 24'!AH110 -> 7.3630658e+11 | BA8: =SUM(H8:AZ8) -> -0.46325684
G9: 45291 | H9: ='Consol SoFP 23 & 22'!AE15 -> 75109486095 | I9: =SUM('Consol SoFP 23 & 22'!AE17:AE18,'Consol SoFP 23 & 22'!AE20) -> 323260364520 | J9: =SUM('Consol SoFP 23 & 22'!AE22) -> 15830303102 | K9: =SUM('Consol SoFP 23 & 22'!AE25:AE26) -> 20326406410 | L9: =SUM('Consol SoFP 23 & 22'!AE28:AE29) -> 38356602143 | M9: =SUM('Consol SoFP 23 & 22'!AE32) -> 11811728970 | N9: ='Consol SoFP 23 & 22'!AE34 -> 159588593589 | O9: ='Consol SoFP 23 & 22'!AE31 -> 2623976876 | P9: ='Consol SoFP 23 & 22'!AE35 -> 24013216750 | R9: ='Consol SoFP 23 & 22'!AE42 -> 2156177190 | S9: ='Consol SoFP 23 & 22'!AE44 -> 21832710982 | U9: ='Consol SoFP 23 & 22'!AE46 -> 11843914378 | V9: ='Consol SoFP 23 & 22'!AE45 -> 24886088064 | W9: ='Consol SoFP 23 & 22'!AE47 -> 2482200000 | X9: ='Consol SoFP 23 & 22'!AE50 -> 12960995205 | AA9: ='Consol SoFP 23 & 22'!AE84 -> -11841969435 | AB9: ='Consol SoFP 23 & 22'!AE58 -> -141442017128 | AC9: =SUM('Consol SoFP 23 & 22'!AE60:AE61) -> -48531295722 | AD9: ='Consol SoFP 23 & 22'!AE70 -> -5410354427 | AE9: ='Consol SoFP 23 & 22'!AE65 -> -3998598175 | AF9: ='Consol SoFP 23 & 22'!AE67 -> -15917342497 | AG9: ='Consol SoFP 23 & 22'!AE73 -> 0 | AH9: ='Consol SoFP 23 & 22'!AE72 -> 0 | AI9: ='Consol SoFP 23 & 22'!AE66 -> -5484244074 | AJ9: ='Consol SoFP 23 & 22'!AE63 -> -59423529841 | AK9: ='Consol SoFP 23 & 22'!AE74 -> 0 | AL9: ='Consol SoFP 23 & 22'!AE71 -> 0 | AO9: ='Consol SoFP 23 & 22'!AE81+'Consol SoFP 23 & 22'!AE75 -> -89665532815 | AP9: ='Consol SoFP 23 & 22'!AE82 -> -4853302291 | AQ9: ='Consol SoFP 23 & 22'!AE83 -> 0 | AR9: ='Consol SoFP 23 & 22'!AE85 -> -4735334275 | AS9: ='Consol SoFP 23 & 22'!AE93 -> -486708075000 | AT9: ='Consol SoFP 23 & 22'!AE94 -> -1003275649843 | AU9: =SUM('Consol SoFP 23 & 22'!AE97:AE98) -> -42384330497 | AV9: =SUM('Consol SoFP 23 & 22'!AE104:AE105) -> -1505283288 | AW9: ='Consol SoFP 23 & 22'!AE106 -> 55005764507 | AY9: =SUM('Consol SoFP 23 & 22'!AE101:AE102) -> 649879728743 | AZ9: ='Consol SoFP 23 & 22'!AE110 -> 4.732086e+11 | BA9: =SUM(H9:AZ9) -> -0.31237793
G10: Variance | H10: =H8-H9 -> -13930950303 | I10: =I8-I9 -> -78588308516 | J10: =J8-J9 -> -10612562590 | K10: =K8-K9 -> 114461164444 | L10: =L8-L9 -> 21505128661 | M10: =M8-M9 -> -1502193571 | N10: =N8-N9 -> -16392985671 | O10: =O8-O9 -> 3643487043 | ... AZ10: =AZ8-AZ9 -> 2.6309798e+11
A12: CASH FLOW FROM OPERATING ACTIVITIES
B13: Profit before income tax | F13: =ROUND(SUM(H13:AZ13),0) -> -521496612227 | AA13: 0 | AI13: 0 | AV13: 0 | AW13: =-'Supplementary CF 24'!M99 -> -6.0462397e+09 | AY13: =-'Consol SoPL-OCI 24'!AG87 -> -2.5235239e+11 | AZ13: =-'Consol SoPL-OCI 24'!AG88 -> -2.6309798e+11 | BA13: =F13-SUM(H13:AZ13) -> -0.0040893555 | BE13: Direct
BE14: Revenue
B15: Adjustment: | BE15: Add: Net change ar to cash
C16: Depreciation of fixed assets | F16: =ROUND(SUM(H16:AZ16),0) -> 18620446593 | S16: =-'Supplementary CF 24'!K24 -> 1.8620447e+10 | BA16: =F16-SUM(H16:AZ16) -> -0.27499771 | BE16: Add: Net movement of Unearned
C17: Provision for Impairment of Fixed Assets | F17: =ROUND(SUM(H17:AZ17),0) -> 0 | S17: =-'Supplementary CF 24'!O25 -> 0 | BA17: =F17-SUM(H17:AZ17) -> 0 | BE17: less: non-cash transaction related to AR
C18: Depreciation of right of use assets | F18: =ROUND(SUM(H18:AZ18),0) -> 9829951191 | U18: =-'Supplementary CF 24'!F43 -> 9829951191 | BA18: =F18-SUM(H18:AZ18) -> 0
C19: Provision for Impairment of Right of used assets | F19: =ROUND(SUM(H19:AZ19),0) -> 0 | U19: =-'Supplementary CF 24'!F44 -> 0 | BA19: =F19-SUM(H19:AZ19) -> 0
C20: Loss from early termination fo Lease | E20: l | F20: =ROUND(SUM(H20:AZ20),0) -> 0 | U20: =-'Supplementary CF 24'!F42 -> 0 | AO20: ='Supplementary CF 24'!F55 -> 0 | BA20: =F20-SUM(H20:AZ20) -> 0
C21: Amortization of intangible assets | F21: =ROUND(SUM(H21:AZ21),0) -> 8416579389 | V21: =-'Supplementary CF 24'!M66 -> 8.4165794e+09 | BA21: =F21-SUM(H21:AZ21) -> -0.0023345947
C22: Provision for Impairment of Intangible Assets | F22: =ROUND(SUM(H22:AZ22),0) -> 0 | V22: =-'Supplementary CF 24'!O67 -> 0 | BA22: =F22-SUM(H22:AZ22) -> 0
C23: Loss (Gain) on disposal of fixed assets | F23: =ROUND(SUM(H23:AZ23),0) -> 0 | S23: =-'Supplementary CF 24'!O23 -> 0 | BA23: =F23-SUM(H23:AZ23) -> 0
C24: Employee benefit expenses | F24: =ROUND(SUM(H24:AZ24),0) -> 0 | Z24: 0 | AP24: =-SUM('Supplementary CF 24'!O87:O88) -> 0 | AV24: 0 | BA24: =F24-SUM(H24:AZ24) -> 0
C25: Provision for impairment of trade receivables, net | F25: =ROUND(SUM(H25:AZ25),0) -> 0 | I25: =ROUND(SUM('Supplementary CF 24'!O10:O11),0) -> 0 | J25: 0 | Q25: 0 | BA25: =F25-SUM(H25:AZ25) -> 0
C26: Fair value of financial asset | F26: =ROUND(SUM(H26:AZ26),0) -> 0 | BA26: =F26-SUM(H26:AZ26) -> 0
C27: Share-based compensation reserve | F27: =ROUND(SUM(H27:AZ27),0) -> 0 | AU27: =-AU10 -> 0 | AV27: 0 | BA27: =F27-SUM(H27:AZ27) -> 0
C28: Interest income | F28: =ROUND(SUM(H28:AZ28),0) -> -8025553537 | Q28: 0 | AY28: ='Consol SoPL-OCI 24'!AG35 -> -8.0255535e+09 | BA28: =F28-SUM(H28:AZ28) -> 0.30000114
C29: Interest expense | F29: =ROUND(SUM(H29:AZ29),0) -> 12803154683 | AY29: ='Consol SoPL-OCI 24'!AG36 -> 1.2803155e+10 | BA29: =F29-SUM(H29:AZ29) -> 0.35000038
C30: Interest expense on lease | F30: =ROUND(SUM(H30:AZ30),0) -> 9784551649 | AO30: ='Supplementary CF 24'!M53 -> 9.7845516e+09 | BA30: =F30-SUM(H30:AZ30) -> 0.2365551
BA31: =F31-SUM(H31:AZ31) -> 0
F32: =SUM(F13:F31) -> -470067482259 | BA32: 0
B33: Changes in working capital: | BA33: =F33-SUM(H33:AZ33) -> 0
C34: Trade receivables, net | F34: =ROUND(SUM(H34:AZ34),0) -> 78588308516 | I34: =-I10-I25 -> 78588308516 | BA34: =F34-SUM(H34:AZ34) -> 0
C35: Other receivables, net | F35: =ROUND(SUM(H35:AZ35),0) -> -21337108766 | L35: =-L10-L59 -> -21505128661 | W35: =-W10 -> 168019899 | Z35: -4 | BA35: =F35-SUM(H35:AZ35) -> 0
C36: Other assets | F36: =ROUND(SUM(H36:AZ36),0) -> 23951297446 | M36: =-M10 -> 1502193571 | P36: =-P10 -> 22449103875 | BA36: =F36-SUM(H36:AZ36) -> 0
C37: Other non-current assets | F37: =ROUND(SUM(H37:AZ37),0) -> -71899046711 | X37: =-X10 -> -71899046711 | BA37: =F37-SUM(H37:AZ37) -> 0
C38: Trade and other payables | F38: =ROUND(SUM(H38:AZ38),0) -> 42709326002 | S38: =-'Supplementary CF 24'!O32 -> 0 | X38: 0 | AC38: =-AC10-AC57 -> 42709326002 | BA38: =F38-SUM(H38:AZ38) -> 0
C39: Deposit payable | F39: =ROUND(SUM(H39:AZ39),0) -> -2400612242 | AE39: =-AE10 -> -2400612242 | BA39: =F39-SUM(H39:AZ39) -> 0
C40: Unearned Revenue | F40: =ROUND(SUM(H40:AZ40),0) -> 22024685439 | AE40: =-AE11 -> 0 | AK40: =-AK10 -> 22024685439 | BA40: =F40-SUM(H40:AZ40) -> 0
C41: Accruals | F41: =ROUND(SUM(H41:AZ41),0) -> -31370782529 | AJ41: =-AJ10 -> -31370782529 | BA41: =F41-SUM(H41:AZ41) -> 0
C42: Taxes payable – other taxes | F42: =ROUND(SUM(H42:AZ42),0) -> -5133042690 | AI42: =-AI10-AI13 -> -5133042690 | BA42: =F42-SUM(H42:AZ42) -> 0
C43: Other non-current liabilities | F43: =ROUND(SUM(H43:AZ43),0) -> 1248251020 | AD43: =-AD10 -> 1248251020 | AR43: =-AR10 -> 0 | BA43: =F43-SUM(H43:AZ43) -> 0
BA44: =F44-SUM(H44:AZ44) -> 0
F45: =SUM(F32:F44) -> -433686206774
F46: 0
B47: Payment of employee benefits | F47: =ROUND(SUM(H47:AZ47),0) -> 0 | BA47: =F47-SUM(H47:AZ47) -> 0
B48: Receipt from Lease receivable | F48: =ROUND(SUM(H48:AZ48),0) -> 12768739780 | J48: =-J10 -> 10612562590 | O48: 0 | P48: 0 | R48: =-R10 -> 2156177190 | AI48: 0 | BA48: =F48-SUM(H48:AZ48) -> 0
B49: Payment of income tax | F49: =ROUND(SUM(H49:AZ49),0) -> -3643487043 | O49: =-O10 -> -3643487043 | AI49: 0 | BA49: =F49-SUM(H49:AZ49) -> 0
B50: Receipt of finance income | F50: =ROUND(SUM(H50:AZ50),0) -> 8025553537 | AY50: =-AY28 -> 8.0255535e+09 | BA50: =F50-SUM(H50:AZ50) -> -0.30000114
B51: Payment of interest | F51: =ROUND(SUM(H51:AZ51),0) -> -12803154683 | AY51: =-AY29 -> -1.2803155e+10 | BA51: =F51-SUM(H51:AZ51) -> -0.35000038
B53: Net cash provided by (used in) operating activities | F53: =SUM(F45:F52) -> -429338555183
A55: CASH FLOW FROM INVESTING ACTIVITIES
C57: Addition of fixed assets | F57: =ROUND(SUM(H57:AZ57),0) -> -25252112784 | S57: =-'Supplementary CF 24'!M34 -> -6.8695437e+10 | T57: =-T10 -> 0 | AC57: ='Supplementary CF 24'!M32 -> 2345151396 | AO57: ='Supplementary CF 24'!M33 -> 4.1098172e+10 | BA57: =F57-SUM(H57:AZ57) -> 0.22636414
C58: Addition of intangible assets | F58: =ROUND(SUM(H58:AZ58),0) -> 0 | BA58: =F58-SUM(H58:AZ58) -> 0
C59: Addition of ROU | F59: =ROUND(SUM(H59:AZ59),0) -> 0 | K59: =-SUM(L59:AY59) -> 0 | U59: =-'Supplementary CF 24'!F52 -> -3.4228484e+10 | AO59: ='Supplementary CF 24'!F52 -> 3.4228484e+10 | BA59: =F59-SUM(H59:AZ59) -> 0
C60: Acquisition of subsidiaries | F60: =ROUND(SUM(H60:AZ60),0) -> 0 | BA60: =F60-SUM(H60:AZ60) -> 0
C61: Addition investment in shares | F61: =ROUND(SUM(H61:AZ61),0) -> 0 | X61: 0 | BA61: =F61-SUM(H61:AZ61) -> 0
C62: Proceeds from sale of fixed assets | F62: =ROUND(SUM(H62:AZ62),0) -> 0 | S62: 0 | BA62: =F62-SUM(H62:AZ62) -> 0
C63: Receipt of other receivables | F63: =ROUND(SUM(H63:AZ63),0) -> 0 | BA63: =F63-SUM(H63:AZ63) -> 0
C64: Interest income | F64: =ROUND(SUM(H64:AZ64),0) -> 0 | BA64: =F64-SUM(H64:AZ64) -> 0
C65: Addition due from related parties | F65: =ROUND(SUM(H65:AZ65),0) -> 0 | BA65: =F65-SUM(H65:AZ65) -> 0
C66: Receipt due from related parties | F66: =ROUND(SUM(H66:AZ66),0) -> 0 | Q66: =-Q10-Q28-Q65-Q64-Q25 -> 0 | BA66: =F66-SUM(H66:AZ66) -> 0
C67: Addition to other assets | F67: =ROUND(SUM(H67:AZ67),0) -> 0 | BA67: =F67-SUM(H67:AZ67) -> 0
B69: Net cash provided by (used in) investing activities | F69: =SUM(F56:F68) -> -25252112784
A71: CASH FLOW FROM FINANCING ACTIVITIES
C73: Receipt of loan | F73: =ROUND(SUM(H73:AZ73),0) -> -31753628336 | AB73: =-AB10 -> -31753628336 | AL73: =-AL10 -> 0 | BA73: =F73-SUM(H73:AZ73) -> 0
C74: Repayment of loan | F74: =ROUND(SUM(H74:AZ74),0) -> 0 | BA74: =F74-SUM(H74:AZ74) -> 0
C75: Acquisition of Subsidiaries | F75: =ROUND(SUM(H75:AZ75),0) -> -24268137075 | AW75: ='SoCE Consol '!L77 -> 6.1052004e+10 | AX75: =-AX10 -> -85320141313 | BA75: =F75-SUM(H75:AZ75) -> 0.43013
C76: Payment due to related parties | F76: =ROUND(SUM(H76:AZ76),0) -> -48537121728 | K76: =-K10 -> -114461164444 | AF76: =-AF10 -> 65924042716 | BA76: =F76-SUM(H76:AZ76) -> 0
C77: Cash proceeds from issuance share in subsidiaries | F77: =ROUND(SUM(H77:AZ77),0) -> 0 | AV77: 0 | AZ77: 0 | BA77: =F77-SUM(H77:AZ77) -> 0
C78: Proceed from advance for share capital | F78: =ROUND(SUM(H78:AZ78),0) -> 604970548439 | AS78: =-AS10 -> 0 | AT78: =-'Supplementary CF 24'!E76-AS78 -> 6.0497055e+11 | BA78: =F78-SUM(H78:AZ78) -> 0.27490234
C79: Withdrawal (Placement) of restricted bank and time deposits, net | F79: =ROUND(SUM(H79:AZ79),0) -> 16392985671 | N79: =-N10 -> 16392985671 | BA79: =F79-SUM(H79:AZ79) -> 0
C80: Repayment of lease liabilities | F80: =ROUND(SUM(H80:AZ80),0) -> -76144928660 | AO80: ='Supplementary CF 24'!M54 -> -7.6144929e+10 | BA80: =F80-SUM(H80:AZ80) -> 0.006942749
C81: Dividend paid | F81: =ROUND(SUM(H81:AZ81),0) -> 0
B83: Net cash provided by (used in) financing activities | F83: =SUM(F73:F82) -> 440659718311
B86: NET INCREASE (DECREASE) IN CASH AND CASH EQUIVALENTS | F86: =F53+F69+F83 -> -13930949656
B88: NET INCREASE (DECREASE) IN CASH AND CASH EQUIVALENTS FROM DISCONTINUED OPERATIONS
B90: NET FOREIGN EXCHANGE DIFFERENCE | F90: 0
B92: CASH AND CASH EQUIVALENTS AT BEGINNING OF YEAR | F92: =H9 -> 75109486095
B94: CASH AND CASH EQUIVALENTS AT END OF YEAR | F94: =SUM(F86:F93) -> 61178536439
C96: Per FS | F96: =H8 -> 61178535792
C97: control | F97: =F94-F96 -> 647 | H97: =SUM(H11:H96) -> 0 | I97: =SUM(I10:I96) -> 0 | J97: =SUM(J10:J96) -> 0 | K97: =SUM(K10:K96) -> 0 | L97: =SUM(L10:L96) -> 0 | M97: =SUM(M10:M96) -> 0 | N97: =SUM(N10:N96) -> 0 | O97: =SUM(O10:O96) -> 0 | P97: =SUM(P10:P96) -> 0 | ... AF97: =SUM(AF10:AF96) -> 0 | AI97: =SUM(AI10:AI96) -> 0 | AJ97: =SUM(AJ10:AJ96) -> 0 | AK97: =SUM(AK10:AK96) -> 0 | AL97: =SUM(AL10:AL96) -> 0 | AM97: =SUM(AM10:AM96) -> 0 | AN97: =SUM(AN10:AN96) -> 0 | AO97: =SUM(AO10:AO96) -> 0 | AP97: =SUM(AP10:AP96) -> 0 | AR97: =SUM(AR10:AR96) -> 0 | AS97: =SUM(AS10:AS96) -> 0 | AT97: =SUM(AT10:AT96) -> -0.27490234 | AU97: =SUM(AU10:AU96) -> 0 | AV97: =SUM(AV10:AV96) -> -1 | AW97: =SUM(AW10:AW96) -> -0.86421204 | AX97: =SUM(AX10:AX96) -> 0 | AY97: =SUM(AY10:AY96) -> -3.8708801 | AZ97: =SUM(AZ10:AZ96) -> 659.15817

Sheet CF 23 as Restated
A1: PT Dummy - C and its Subsidiaries | Z1: Restatement | AM1: Restatement | AS1: Restatement | AT1: Restatement
A2: Consolidated Statement of Cash Flows
A3: December 31. 2023 - Restated CF
E4: control | J4: =J86 -> 0 | K4: =K86 -> 0 | L4: =L86 -> 0 | M4: =M86 -> 0 | N4: =N86 -> 0 | O4: =O86 -> 0 | P4: =P86 -> 0 | Q4: =Q86 -> 0 | ... BA4: =BA86 -> -2.2983217
H6: 0.42999268 | N6: Current Asset | V6: Non-current asset
J7: Cash and cash equivalents | K7: Trade receivables, net | L7: Current portion of Lease receivables | M7: Loan Receivable Related Party, Net | N7: Other receivables net, | O7: Advance, prepaid expenses and other assets | P7: Restricted banks and time deposits (current and non-current) | Q7: Prepaid tax | R7: Other Current Assets | S7: Due from related parties, net (current and non-current) | T7: Lease receivables - non current | U7: Fixed assets, net | V7: Investment properties | W7: Right of use assets, net | X7: Intangible assets, net | Y7: Shareholder Receivable | Z7: Other non-current asset | AA7: Goodwill | AB7: Deferred tax assets, net | AC7: Deferred tax liabilities, net | AD7: Short-term bank loan | AE7: Trade payable | AF7: Other Payable | AG7: Deposit Payable | AH7: Loan Payable Related Party | AI7: Payable to Shareholder | AJ7: Payable to Subsidiaries | AK7: Taxes payable | AL7: Accrued expenses | AM7: Unearned Revenue | AN7: Borrowings | AO7: Liabilities related asset held for sale | AP7: Convertible bonds | AQ7: Lease liabilities | AR7: Employee benefits liabilities | AS7: Consumer Financing | AT7: Other Non current Liabilities | AU7: Share capital | AV7: Advance Capital | AW7: Share Based Compensation Reserve | AX7: OCI - Employee benefit | AY7: Capital proforma arising from restructuring transactions of entities under common control | AZ7: Retained earnings | BA7: Non-controlling Interest | BB7: control
F8: 45291 | I8: 44926 | J8: ='CF 2024'!H9 -> 75109486095 | K8: ='CF 2024'!I9 -> 323260364520 | L8: ='CF 2024'!J9 -> 15830303102 | M8: ='CF 2024'!K9 -> 20326406410 | N8: ='CF 2024'!L9 -> 38356602143 | O8: ='CF 2024'!M9 -> 11811728970 | P8: ='CF 2024'!N9 -> 159588593589 | Q8: ='CF 2024'!O9 -> 2623976876 | ... AY8: ='CF 2024'!AW9 -> 55005764507 | AZ8: ='CF 2024'!AY9 -> 649879728743 | BA8: ='CF 2024'!AZ9 -> 4.732086e+11 | BB8: =SUM(J8:BA8) -> -0.31237793
F9: 44926 | I9: 44561 | J9: ='Consol SoFP 23 & 22'!BF15 -> 40661258337 | K9: =SUM('Consol SoFP 23 & 22'!BF17:BF18) -> 227940501708 | L9: ='Consol SoFP 23 & 22'!BF22 -> 14442442151 | M9: ='Consol SoFP 23 & 22'!BF26 -> 5180796035 | N9: ='Consol SoFP 23 & 22'!BF28 -> 5434584686 | O9: ='Consol SoFP 23 & 22'!BF32 -> 46432019959 | P9: ='Consol SoFP 23 & 22'!BF34 -> 55354071673 | Q9: ='Consol SoFP 23 & 22'!BF31 -> 90969692 | R9: ='Consol SoFP 23 & 22'!BF35 -> 12634397153 | T9: ='Consol SoFP 23 & 22'!BF42 -> 14398163289 | U9: ='Consol SoFP 23 & 22'!BF44 -> 35664033274 | W9: ='Consol SoFP 23 & 22'!BF46 -> 140145541230 | X9: ='Consol SoFP 23 & 22'!BF45 -> 43488307487 | Y9: ='Consol SoFP 23 & 22'!BF47 -> 874125000 | Z9: ='Consol SoFP 23 & 22'!BF50+'Consol SoFP 23 & 22'!BF48 -> 10947704500 | AC9: ='Consol SoFP 23 & 22'!BF84 -> -3469782201 | AD9: ='Consol SoFP 23 & 22'!BF58 -> -43196374892 | AE9: =SUM('Consol SoFP 23 & 22'!BF60:BF61) -> -35633999745 | AF9: =SUM('Consol SoFP 23 & 22'!BF69:BF70) -> 0 | AG9: ='Consol SoFP 23 & 22'!BF65 -> -6108774604 | AH9: ='Consol SoFP 23 & 22'!BF67 -> -40302224 | AK9: ='Consol SoFP 23 & 22'!BF66 -> -8775032472 | AL9: ='Consol SoFP 23 & 22'!BF63 -> -83657606012 | AQ9: ='Consol SoFP 23 & 22'!BF75+'Consol SoFP 23 & 22'!BF81 -> -125095664551 | AR9: ='Consol SoFP 23 & 22'!BF82 -> -4918246882 | AS9: 0 | AT9: ='Consol SoFP 23 & 22'!BF85 -> 0 | AU9: ='Consol SoFP 23 & 22'!BF93 -> -142427250000 | AV9: ='Consol SoFP 23 & 22'!BF94 -> -357853579198 | AW9: =SUM('Consol SoFP 23 & 22'!BF97:BF98) -> -28533901860 | AX9: =SUM('Consol SoFP 23 & 22'!BF104:BF105) -> -890579715 | AY9: ='Consol SoFP 23 & 22'!BF106 -> -2093719896 | AZ9: =SUM('Consol SoFP 23 & 22'!BF101:BF102) -> 323673912325 | BA9: ='Consol SoFP 23 & 22'!BF110 -> -134668014247 | BB9: =SUM(J9:BA9) -> 0
F10: Variance | I10: Variance | J10: =J8-J9 -> 34448227758 | K10: =K8-K9 -> 95319862812 | L10: =L8-L9 -> 1387860951 | M10: =M8-M9 -> 15145610375 | N10: =N8-N9 -> 32922017457 | O10: =O8-O9 -> -34620290989 | P10: =P8-P9 -> 104234521916 | Q10: =Q8-Q9 -> 2533007184 | ... BA10: =BA8-BA9 -> 6.0787662e+11
A12: CASH FLOW FROM OPERATING ACTIVITIES | F12: Before restatement | G12: Restatement | H12: After restatement
B13: Profit before income tax | F13: -3.0655578e+11 | G13: =H13-F13 -> -6.9017192e+11 | H13: =ROUND(SUM(J13:BA13),0) -> -996727698875 | AC13: ='Consol SoPL-OCI 23 & 22'!AC56 -> 8372187235 | AG13: 0 | AY13: ='Consol SoPL-OCI 23 & 22'!AC61 -> -5.8403962e+10 | AZ13: =-'Consol SoPL-OCI 23 & 22'!AC86 -> -3.2620582e+11 | BA13: =-'Consol SoPL-OCI 23 & 22'!AC87 -> -6.2049011e+11 | BB13: =H13-SUM(J13:BA13) -> 0.41638184
B15: Adjustment:
C16: Depreciation of fixed assets | F16: 1.2603248e+08 | G16: =H16-F16 -> 1.7543936e+10 | H16: =ROUND(SUM(J16:BA16),0) -> 17669968497 | U16: =-'Supplementary CF 23'!M24 -> 1.7669968e+10 | BB16: =H16-SUM(J16:BA16) -> 0.27225113
C17: Provision for Impairment of Fixed Assets | F17: 0 | G17: =H17-F17 -> 32453747018 | H17: =ROUND(SUM(J17:BA17),0) -> 32453747018 | U17: =-'Supplementary CF 23'!M25 -> 3.2453747e+10 | BB17: =H17-SUM(J17:BA17) -> 0.4851532
C18: Depreciation of right of use assets | F18: 0 | G18: =H18-F18 -> 83296105213 | H18: =ROUND(SUM(J18:BA18),0) -> 83296105213 | W18: =-'Supplementary CF 23'!F43 -> 8.3296105e+10 | BB18: =H18-SUM(J18:BA18) -> 0.40000916
C19: Provision for Impairment of Right of used assets | F19: 0 | G19: =H19-F19 -> 88325573940 | H19: =ROUND(SUM(J19:BA19),0) -> 88325573940 | W19: =-'Supplementary CF 23'!F44 -> 8.8325574e+10 | BB19: =H19-SUM(J19:BA19) -> -0.44999695
C20: Loss from early termination fo Lease | F20: 0 | G20: =H20-F20 -> -7662849305 | H20: =ROUND(SUM(J20:BA20),0) -> -7662849305 | W20: =-'Supplementary CF 23'!F42 -> 4.9691894e+10 | AQ20: ='Supplementary CF 23'!F55 -> -57354743376 | BB20: =H20-SUM(J20:BA20) -> -0.049995422
C21: Amortization of intangible assets | F21: 6.9373535e+09 | G21: =H21-F21 -> 3.9178496e+09 | H21: =ROUND(SUM(J21:BA21),0) -> 10855203098 | X21: =-'Supplementary CF 23'!M66 -> 1.0855203e+10 | BB21: =H21-SUM(J21:BA21) -> 0.27499962
C22: Provision for Impairment of Intangible Assets | F22: 7.7470163e+09 | G22: =H22-F22 -> -0.30000019 | H22: =ROUND(SUM(J22:BA22),0) -> 7747016325 | X22: =-'Supplementary CF 23'!M67 -> 7.7470163e+09 | BB22: =H22-SUM(J22:BA22) -> -0.30000019
C23: Loss (Gain) on disposal of fixed assets | F23: 0 | G23: =H23-F23 -> 133536375 | H23: =ROUND(SUM(J23:BA23),0) -> 133536375 | U23: =-'Supplementary CF 23'!M23 -> 133536375 | BB23: =H23-SUM(J23:BA23) -> 0
C24: Employee benefit expenses | F24: 5.019583e+08 | G24: =H24-F24 -> 8.889042e+08 | H24: =ROUND(SUM(J24:BA24),0) -> 1390862499 | AR24: =-AR10 -> -64944591 | AX24: =-'Supplementary CF 23'!E88 -> 6.1470357e+08 | AY24: =-'Supplementary CF 23'!K100 -> 27756416 | BA24: =-'NCI Detail & Movement'!J194 -> 8.133471e+08 | BB24: =H24-SUM(J24:BA24) -> -0.1500001
C25: Provision for impairment of trade receivables, net | F25: 2.5870488e+09 | G25: =H25-F25 -> -6.8759004e+08 | H25: =ROUND(SUM(J25:BA25),0) -> 1899458800 | K25: =SUM('Supplementary CF 23'!K10,'Supplementary CF 23'!K12) -> 1.8994588e+09 | L25: 0 | Q25: 0 | BB25: =H25-SUM(J25:BA25) -> -0.42500019
C26: Writing Off AR | F26: 0 | G26: =H26-F26 -> 5028226875 | H26: =ROUND(SUM(J26:BA26),0) -> 5028226875 | K26: =-'Supplementary CF 23'!K11 -> 5028226875 | L26: 0 | Q26: 0 | BB26: =H26-SUM(J26:BA26) -> 0
C27: Share-based compensation reserve | F27: 1.3850429e+10 | G27: =H27-F27 -> 7.0053707e+09 | H27: =ROUND(SUM(J27:BA27),0) -> 20855799337 | AR27: 0 | AT27: 0 | AW27: =-AW10 -> 13850428637 | AY27: =-'Supplementary CF 23'!K101 -> 2.3117723e+08 | BA27: =-'NCI Detail & Movement'!L194 -> 6.7741935e+09 | BB27: =H27-SUM(J27:BA27) -> -0.47499847
C28: Interest income | F28: -2.4693637e+10 | G28: =H28-F28 -> 1.6087755e+10 | H28: =SUM(J28:BA28) -> -8.605882e+09 | Q28: 0 | AZ28: ='Consol SoPL-OCI 23 & 22'!AC35 -> -8.605882e+09 | BB28: =H28-SUM(J28:BA28) -> 0
C29: Interest expense | F29: 3.8390263e+09 | G29: =H29-F29 -> 2.8075197e+10 | H29: =SUM(J29:BA29) -> 3.1914224e+10 | AZ29: ='Consol SoPL-OCI 23 & 22'!AC36 -> 3.1914224e+10 | BB29: =H29-SUM(J29:BA29) -> 0
C30: Interest expense on lease | F30: 0 | G30: =H30-F30 -> 13001777997 | H30: =ROUND(SUM(J30:BA30),0) -> 13001777997 | AQ30: ='Supplementary CF 23'!F53 -> 1.3001778e+10 | BB30: =H30-SUM(J30:BA30) -> 0.18213654
BB31: =H31-SUM(J31:BA31) -> 0
F32: =SUM(F13:F31) -> -2.9566055e+11 | G32: =SUM(G13:G31) -> -4.0276438e+11 | H32: =SUM(H13:H31) -> -6.9842493e+11 | BB32: 0
B33: Changes in working capital: | BB33: =H33-SUM(J33:BA33) -> 0
C34: Trade receivables, net | F34: =42097916433.825-3796710247.575 -> 3.8301206e+10 | G34: =H34-F34 -> -1.4054875e+11 | H34: =ROUND(SUM(J34:BA34),0) -> -102247548487 | K34: =-K10-K25-K26 -> -1.0224755e+11 | BB34: =H34-SUM(J34:BA34) -> 0.42500305
C35: Other receivables, net | F35: -1.8838057e+10 | G35: =H35-F35 -> -1.4083961e+10 | H35: =ROUND(SUM(J35:BA35),0) -> -32922017457 | N35: =-N10 -> -32922017457 | Z35: 0 | BB35: =H35-SUM(J35:BA35) -> 0
C36: Other assets | F36: -8.5554704e+08 | G36: =H36-F36 -> 3.5475838e+10 | H36: =ROUND(SUM(J36:BA36),0) -> 34620290989 | N36: 0 | O36: =-O10 -> 34620290989 | BB36: =H36-SUM(J36:BA36) -> 0
C37: Other non-current assets | F37: -2.0805585e+08 | G37: =H37-F37 -> -1.3184054e+10 | H37: =ROUND(SUM(J37:BA37),0) -> -13392110302 | R37: =-R10 -> -11378819597 | Z37: =-Z10 -> -2013290705 | BB37: =H37-SUM(J37:BA37) -> 0
C38: Trade and other payables | F38: 6.2904497e+09 | G38: =H38-F38 -> 5.839648e+09 | H38: =ROUND(SUM(J38:BA38),0) -> 12130097727 | AE38: =-AE10-AE56 -> 12130097727 | BB38: =H38-SUM(J38:BA38) -> 0
C39: Deposit payable | F39: -2.1101764e+09 | G39: =H39-F39 -> -0.1500001 | H39: =ROUND(SUM(J39:BA39),0) -> -2110176429 | AG39: =-AG10 -> -2110176429 | BB39: =H39-SUM(J39:BA39) -> 0
C40: Accruals | F40: 0 | G40: =H40-F40 -> -24234076171 | H40: =ROUND(SUM(J40:BA40),0) -> -24234076171 | AL40: =-AL10 -> -24234076171 | BB40: =H40-SUM(J40:BA40) -> 0
C41: Taxes payable – other taxes | F41: -1.8831866e+10 | G41: =H41-F41 -> 1.3008071e+10 | H41: =ROUND(SUM(J41:BA41),0) -> -5823795582 | Q41: =-Q10 -> -2533007184 | AK41: =-AK10 -> -3290788398 | BB41: =H41-SUM(J41:BA41) -> 0
C42: Other non-current liabilities | F42: -1.7758503e+09 | G42: =H42-F42 -> 6.5111845e+09 | H42: =ROUND(SUM(J42:BA42),0) -> 4735334275 | AN42: =-AN10 -> 0 | AT42: =-AT10 -> 4735334275 | BB42: =H42-SUM(J42:BA42) -> 0
BB43: =H43-SUM(J43:BA43) -> 0
F44: =SUM(F32:F43) -> -2.9368845e+11 | G44: =SUM(G32:G43) -> -5.3398048e+11 | H44: =SUM(H32:H43) -> -8.2766893e+11
H45: 0
B46: Payment of employee benefits | F46: 0 | G46: =H46-F46 -> 0 | H46: =ROUND(SUM(J46:BA46),0) -> 0 | BB46: =H46-SUM(J46:BA46) -> 0
B47: Receipt from Lease receivable | F47: 0 | G47: =H47-F47 -> 10854125148 | H47: =ROUND(SUM(J47:BA47),0) -> 10854125148 | L47: =-L10 -> -1387860951 | P47: 0 | T47: =-T10 -> 12241986099 | AG47: 0 | BB47: =H47-SUM(J47:BA47) -> 0
B48: Payment of income tax | F48: 0 | G48: =H48-F48 -> 0 | H48: =ROUND(SUM(J48:BA48),0) -> 0 | AG48: 0 | BB48: =H48-SUM(J48:BA48) -> 0
B49: Receipt of finance income | F49: 6.856053e+08 | G49: =H49-F49 -> 7.9202767e+09 | H49: =-H28 -> 8.605882e+09 | AZ49: =-AZ28 -> 8.605882e+09 | BB49: =H49-SUM(J49:BA49) -> 0
B50: Payment of interest | F50: -3.8390263e+09 | G50: =H50-F50 -> -2.8075197e+10 | H50: =-H29 -> -3.1914224e+10 | AZ50: =-AZ29 -> -3.1914224e+10 | BB50: =H50-SUM(J50:BA50) -> 0
B52: Net cash provided by (used in) operating activities | F52: =SUM(F44:F51) -> -2.9684187e+11 | G52: =SUM(G44:G51) -> -5.4328128e+11 | H52: =SUM(H44:H51) -> -840123148495
A54: CASH FLOW FROM INVESTING ACTIVITIES
C56: Addition of fixed assets | F56: -1.7756243e+08 | G56: =H56-F56 -> -3.5481169e+10 | H56: =ROUND(SUM(J56:BA56),0) -> -35658731345 | U56: =-'Supplementary CF 23'!M34 -> -3.642593e+10 | AE56: ='Supplementary CF 23'!K32 -> 767198250 | BB56: =H56-SUM(J56:BA56) -> -0.050003052
C57: Addition to other assets | F57: 0 | G57: =H57-F57 -> 0 | H57: =ROUND(SUM(J57:BA57),0) -> 0 | BB57: =H57-SUM(J57:BA57) -> 0
B59: Net cash provided by (used in) investing activities | F59: =SUM(F55:F58) -> -1.7756243e+08 | G59: =SUM(G55:G58) -> -3.5481169e+10 | H59: =SUM(H55:H58) -> -35658731345
A61: CASH FLOW FROM FINANCING ACTIVITIES
C63: Receipt of loan, net | F63: -11025000000 | G63: =H63-F63 -> 109270642236 | H63: =ROUND(SUM(J63:BA63),0) -> 98245642236 | AB63: =-AB10 -> 0 | AD63: =-AD10 -> 98245642236 | AI63: =-AI10 -> 0 | BB63: =H63-SUM(J63:BA63) -> 0
C64: Receipt due to related parties | F64: 1.587704e+10 | G64: =H64-F64 -> 1.25 | H64: =ROUND(SUM(J64:BA64),0) -> 15877040273 | AH64: =-AH10 -> 15877040273 | BB64: =H64-SUM(J64:BA64) -> 0
C65: Payment due to related parties | F65: -6.820359e+11 | G65: =H65-F65 -> 6.7069257e+11 | H65: =ROUND(SUM(J65:BA65),0) -> -11343330948 | M65: =-M10 -> -15145610375 | Y65: =-Y10 -> -1608075000 | AF65: =-AF10 -> 5410354427 | BB65: =H65-SUM(J65:BA65) -> 0
C66: Issuance share in Subsidiaries | F66: 0 | H66: =ROUND(SUM(J66:BA66),0) -> 6071495040 | AY66: =-'Supplementary CF 23'!K98 -> 1.0455437e+09 | BA66: =-'NCI Detail & Movement'!F200 -> 5.0259513e+09
C67: Proceed from advance for share capital | F67: 9.897029e+11 | G67: 0 | H67: =ROUND(SUM(J67:BA67),0) -> 989702895645 | AO67: =-AO10 -> 0 | AU67: =-AU10 -> 344280825000 | AV67: =-'Supplementary CF 23'!E76-AU67 -> 6.4542207e+11 | BB67: =H67-SUM(J67:BA67) -> -0.44995117
C68: Withdrawal (Placement) of restricted bank and time deposits, net | F68: 0 | G68: =H68-F68 -> -104234521916 | H68: =ROUND(SUM(J68:BA68),0) -> -104234521916 | P68: =-P10 -> -104234521916 | BB68: =H68-SUM(J68:BA68) -> 0
C69: Repayment of lease liabilities | F69: 0 | G69: =H69-F69 -> -84089112726 | H69: =ROUND(SUM(J69:BA69),0) -> -84089112726 | AQ69: ='Supplementary CF 23'!M54 -> -8.4089113e+10 | BB69: =H69-SUM(J69:BA69) -> 0.1499939
C70: Dividend paid | F70: 0 | G70: =H70-F70 -> 0 | H70: =ROUND(SUM(J70:BA70),0) -> 0
B72: Net cash provided by (used in) financing activities | F72: =SUM(F63:F71) -> 3.1251903e+11 | G72: =H72-F72 -> 5.9771107e+11 | H72: =SUM(H63:H71) -> 910230107604
B75: NET INCREASE (DECREASE) IN CASH AND CASH EQUIVALENTS | F75: =F52+F59+F72 -> 1.5499598e+10 | G75: =H75-F75 -> 1.8948629e+10 | H75: =H52+H59+H72 -> 34448227764
B77: NET INCREASE (DECREASE) IN CASH AND CASH EQUIVALENTS FROM DISCONTINUED OPERATIONS
B79: NET FOREIGN EXCHANGE DIFFERENCE | G79: =H79-F79 -> 0 | H79: 0
B81: CASH AND CASH EQUIVALENTS AT BEGINNING OF YEAR | F81: 2.5526565e+10 | G81: =H81-F81 -> 1.5134693e+10 | H81: =J9 -> 40661258337
B83: CASH AND CASH EQUIVALENTS AT END OF YEAR | F83: =SUM(F75:F82) -> 4.1026164e+10 | G83: =H83-F83 -> 3.4083322e+10 | H83: =SUM(H75:H82) -> 75109486101
C85: Per FS | F85: ='Consol SoFP 23 & 22'!H15 -> 41026163646 | G85: =H85-F85 -> 34083322449 | H85: =J8 -> 75109486095
C86: control | F86: =F83-F85 -> 0 | G86: =G83-G85 -> 5.9999542 | H86: =H83-H85 -> 6 | J86: =SUM(J11:J85) -> 0 | K86: =SUM(K10:K85) -> 0 | L86: =SUM(L10:L85) -> 0 | M86: =SUM(M10:M85) -> 0 | N86: =SUM(N10:N85) -> 0 | O86: =SUM(O10:O85) -> 0 | P86: =SUM(P10:P85) -> 0 | Q86: =SUM(Q10:Q85) -> 0 | R86: =SUM(R10:R85) -> 0 | ... BA86: =SUM(BA10:BA85) -> -2.2983217

Sheet WP Consol

Sheet Control
A2: Retained Earnings
D4: 0.51 | E4: 0.51 | F4: 0.51 | G4: 0.51 | H4: 0.51 | J4: 0.51
D5: =100%-D4 -> 0.49 | E5: =100%-E4 -> 0.49 | F5: =100%-F4 -> 0.49 | G5: =100%-G4 -> 0.49 | H5: =100%-H4 -> 0.49 | J5: =100%-J4 -> 0.49
C7: PT Dummy C | D7: PT Dummy A - Consol | E7: PT Dummy - D | F7: PT Dummy - E | G7: PT Dummy - F | H7: PT Dummy - G | J7: Elimination | L7: Elimination
A11: Beginning Balance RE - Jan 1 2022 | C11: ='Consol SoFP 23 & 22'!AJ101 -> 145740154214 | D11: ='Consol SoFP 23 & 22'!AT101 -> -20240927228 | E11: ='Consol SoFP 23 & 22'!AM101 -> 1.2996164e+11 | F11: ='Consol SoFP 23 & 22'!AP101 -> 0 | G11: ='Consol SoFP 23 & 22'!AQ101 -> -1.1332579e+10 | H11: ='Consol SoFP 23 & 22'!AY101 -> 0 | J11: =SUM('Consol SoFP 23 & 22'!BD101:BE101) -> -9.8388134e+10 | L11: =SUM(C11:H11,J11) -> 145740154214
A12: Current Profit | C12: ='Consol SoPL-OCI 23 & 22'!AH86 -> 1.7793376e+11 | D12: ='Consol SoPL-OCI 23 & 22'!AT86 -> 3.9420352e+10 | E12: ='Consol SoPL-OCI 23 & 22'!AK86 -> 3.8207448e+11 | F12: ='Consol SoPL-OCI 23 & 22'!AN86 -> 2.8261882e+08 | G12: ='Consol SoPL-OCI 23 & 22'!AQ86 -> 574553968 | H12: 0 | J12: =SUM('Consol SoFP 23 & 22'!BD102:BE102) -> -4.2235201e+11 | L12: =SUM(C12:H12,J12) -> 1.7793376e+11
A13: As of December 31, 2022 | C13: =SUM(C11:C12) -> 3.2367391e+11 | D13: =SUM(D11:D12) -> 1.9179424e+10 | E13: =SUM(E11:E12) -> 5.1203612e+11 | F13: =SUM(F11:F12) -> 2.8261882e+08 | G13: =SUM(G11:G12) -> -1.0758025e+10 | H13: =SUM(H11:H12) -> 0 | J13: =SUM(H13:I13) -> 0 | L13: =SUM(L11:L12) -> 3.2367391e+11
A14: Per BS | C14: =SUM('Consol SoFP 23 & 22'!AJ101:AJ102) -> 3.2367391e+11 | D14: =SUM('Consol SoFP 23 & 22'!AT101:AT102) -> 1.9179424e+10 | E14: =SUM('Consol SoFP 23 & 22'!AM101:AM102) -> 5.1203612e+11 | F14: =SUM('Consol SoFP 23 & 22'!AP101:AP102) -> 2.8261882e+08 | G14: =SUM('Consol SoFP 23 & 22'!AQ101:AQ102) -> -1.0758025e+10 | H14: ='Consol SoFP 23 & 22'!AY101 -> 0 | J14: =SUM(H14:I14) -> 0 | L14: =SUM('Consol SoFP 23 & 22'!BF101:BF102) -> 323673912325
A15: Diff | C15: =C13-C14 -> 0 | D15: =D13-D14 -> 0 | E15: =E13-E14 -> 0 | F15: =F13-F14 -> 0 | G15: =G13-G14 -> 0 | H15: =H13-H14 -> 0 | J15: =SUM(H15:I15) -> 0 | L15: =SUM(J15:K15) -> 0
A17: Beginning Balance RE - Jan 1 2023 | C17: =C13 -> 3.2367391e+11 | D17: =D13 -> 1.9179424e+10 | E17: =E13 -> 5.1203612e+11 | F17: =F13 -> 2.8261882e+08 | G17: =G13 -> -1.0758025e+10 | H17: =H13 -> 0 | J17: =SUM('Consol SoFP 23 & 22'!AC101:AD101) -> -5.2074014e+11 | L17: =SUM(C17:H17,J17) -> 3.2367391e+11
A18: Current Profit | C18: ='Consol SoPL-OCI 23 & 22'!G86 -> 3.0717049e+11 | D18: ='Consol SoPL-OCI 23 & 22'!S86 -> 7.9178339e+10 | E18: ='Consol SoPL-OCI 23 & 22'!J86 -> 6.0319819e+11 | F18: ='Consol SoPL-OCI 23 & 22'!M86 -> -2677772539 | G18: ='Consol SoPL-OCI 23 & 22'!P86 -> -1013465132 | H18: 0 | J18: =SUM('Consol SoFP 23 & 22'!AC102:AD102) -> -6.5964996e+11 | L18: =SUM(C18:H18,J18) -> 3.2620582e+11
A19: As of December 31, 2023 | C19: =SUM(C17:C18) -> 6.308444e+11 | D19: =SUM(D17:D18) -> 9.8357763e+10 | E19: =SUM(E17:E18) -> 1.1152343e+12 | F19: =SUM(F17:F18) -> -2.3951537e+09 | G19: =SUM(G17:G18) -> -1.1771491e+10 | H19: =SUM(H17:H18) -> 0 | J19: =SUM(J17:J18) -> -1.1803901e+12 | L19: =SUM(L17:L18) -> 6.4987973e+11
A20: Per BS | C20: =SUM('Consol SoFP 23 & 22'!H101:H102) -> 6.308444e+11 | D20: =SUM('Consol SoFP 23 & 22'!T101:T102) -> 9.8357763e+10 | E20: =SUM('Consol SoFP 23 & 22'!K101:K102) -> 1.1152343e+12 | F20: =SUM('Consol SoFP 23 & 22'!N101:N102) -> -2.3951537e+09 | G20: =SUM('Consol SoFP 23 & 22'!Q101:Q102) -> -1.1771491e+10 | H20: ='Consol SoFP 23 & 22'!AY107 -> 0 | L20: =SUM('Consol SoFP 23 & 22'!AE101:AE102) -> 649879728743
A21: Diff | C21: =C19-C20 -> 0 | D21: =D19-D20 -> -0.62319946 | E21: =E19-E20 -> 1.7248535 | F21: =F19-F20 -> 0 | G21: =G19-G20 -> 0.25 | H21: =H19-H20 -> 0 | L21: =L19-L20 -> 0.94311523
A23: Beginning Balance RE - Jan 1 2024 | C23: =C19 -> 6.308444e+11 | D23: =D19 -> 9.8357763e+10 | E23: =E19 -> 1.1152343e+12 | F23: =F19 -> -2.3951537e+09 | G23: =G19 -> -1.1771491e+10 | H23: =H19 -> 0 | J23: =SUM('Consol SoFP 23 & 22'!AC107:AD107) -> 0 | L23: =SUM(C23:H23,J23) -> 1.8302698e+12
A24: Current Profit | C24: ='Consol SoPL-OCI 24'!E63+'Consol SoPL-OCI 24'!F63 -> 232074381913 | D24: ='Consol SoPL-OCI 24'!W87 -> 9.1244059e+09 | E24: ='Consol SoPL-OCI 24'!M87 -> 2.4367652e+11 | F24: ='Consol SoPL-OCI 24'!P79 -> 10891649906 | G24: ='Consol SoPL-OCI 24'!T79 -> 36098801827 | H24: ='Consol SoFP 24'!Y102 -> -8.971568e+08
A25: Equity adjustment - Current Profit | C25: =SUM('Consol SoFP 24'!F102:G102) -> 1.9370965e+10 | D25: ='Consol SoPL-OCI 23 & 22'!S92 -> 0 | E25: ='Consol SoPL-OCI 23 & 22'!J92 -> 0 | F25: ='Consol SoPL-OCI 23 & 22'!M92 -> 0 | G25: ='Consol SoPL-OCI 23 & 22'!P92 -> 0 | H25: 0 | J25: =SUM('Consol SoFP 23 & 22'!AC108:AD108) -> 0 | L25: =SUM(C25:H25,J25) -> 1.9370965e+10
A26: As of December 31, 2024 | C26: =SUM(C23:C25) -> 8.8228974e+11 | D26: =SUM(D23:D25) -> 1.0748217e+11 | E26: =SUM(E23:E25) -> 1.3589108e+12 | F26: =SUM(F23:F25) -> 8.4964962e+09 | G26: =SUM(G23:G25) -> 2.4327311e+10 | H26: =SUM(H23:H25) -> -8.971568e+08 | J26: =SUM(J23:J25) -> 0 | L26: =SUM(L23:L25) -> 1.8496408e+12
A27: Per BS - Before re Reconciliation | C27: =SUM('Consol SoFP 24'!H101:H102) -> 8.8228974e+11 | D27: =SUM('Consol SoFP 24'!V101:V102) -> 1.0748217e+11 | E27: =SUM('Consol SoFP 24'!L101:L102) -> 1.3589108e+12 | F27: =SUM('Consol SoFP 24'!M101:M102) -> 8207054749 | G27: =SUM('Consol SoFP 24'!S101:S102) -> 2.4327311e+10 | H27: 0 | L27: =SUM('Consol SoFP 23 & 22'!AE107:AE108) -> 0
A28: Diff | C28: =C26-C27 -> 3.2749023 | D28: =D26-D27 -> -0.29432678 | E28: =E26-E27 -> 11.015625 | F28: =F26-F27 -> 2.8944144e+08 | G28: =G26-G27 -> -0.59949493 | H28: 0 | L28: =L26-L27 -> 1.8496408e+12
A30: RE Reconciliation:
A31: 1) PT Dummy - D
A32: Accrued Expense | F32: =-F28 -> -2.8944144e+08
A34: Beginning Balance RE - Jan 1 2024 | C34: =C23 -> 6.308444e+11 | D34: =D23 -> 9.8357763e+10 | E34: =E23 -> 1.1152343e+12 | F34: =F23 -> -2.3951537e+09 | G34: =G23 -> -1.1771491e+10 | H34: =H23 -> 0 | J34: =J23 -> 0 | L34: =L23 -> 1.8302698e+12
A35: Current Profit | C35: =C24 -> 232074381913 | D35: =D24 -> 9.1244059e+09 | E35: ='Consol SoPL-OCI 24'!M98 -> 2.4367652e+11 | F35: ='Consol SoPL-OCI 24'!P90 -> 10891649906 | G35: ='Consol SoPL-OCI 24'!T90 -> 36098801827 | H35: ='Consol SoFP 24'!Y102 -> -8.971568e+08
A36: Equity adjustment - Current Profit | C36: =C25 -> 1.9370965e+10 | D36: ='Consol SoPL-OCI 23 & 22'!S103 -> 0 | E36: ='Consol SoPL-OCI 23 & 22'!J103 -> 0 | F36: ='Consol SoPL-OCI 23 & 22'!M103 -> 0 | G36: ='Consol SoPL-OCI 23 & 22'!P103 -> 0 | H36: 0 | J36: =SUM('Consol SoFP 23 & 22'!AC119:AD119) -> 0 | L36: =SUM(C36:H36,J36) -> 1.9370965e+10
A37: As of December 31, 2024 | C37: =SUM(C34:C36) -> 8.8228974e+11 | D37: =SUM(D34:D36) -> 1.0748217e+11 | E37: =SUM(E34:E36) -> 1.3589108e+12 | F37: =SUM(F34:F36) -> 8.4964962e+09 | G37: =SUM(G34:G36) -> 2.4327311e+10 | H37: =SUM(H34:H36) -> -8.971568e+08 | J37: =SUM(J34:J36) -> 0 | L37: =SUM(L34:L36) -> 1.8496408e+12
A38: Per BS - Before After Reconciliation | C38: =SUM('Consol SoFP 24'!H101:H102) -> 8.8228974e+11 | D38: =SUM('Consol SoFP 24'!V101:V102) -> 1.0748217e+11 | E38: =SUM('Consol SoFP 24'!L101:L102) -> 1.3589108e+12 | F38: =SUM('Consol SoFP 24'!O101:O102) -> 8.4964962e+09 | G38: =SUM('Consol SoFP 24'!S101:S102) -> 2.4327311e+10 | H38: 0 | L38: =SUM('Consol SoFP 23 & 22'!AE118:AE119) -> 6.5241163e+11
A39: Diff | C39: =C37-C38 -> 3.2749023 | D39: =D37-D38 -> -0.29432678 | E39: =E37-E38 -> 11.015625 | F39: =F37-F38 -> 0 | G39: =G37-G38 -> -0.59949493 | H39: 0 | L39: =L37-L38 -> 1.1972292e+12
A41: Investment
C44: Investment | D44: Proforma | E44: Proforma Adjustment | F44: Proforma Adjustment | G44: Equity | H44: Total | J44: Elimination | L44: Elimination
C45: Per Book | D45: Adjustment PY | E45: Current Profit CY | F45: Investment value should be | G45: Adjustment | H45: Before Elimination | J45: PT Dummy C Consol | L45: PT Dummy C Consol
A48: PT Dummy A - Consol | C48: 240975000 | D48: =SUM('Proforma Adjustment'!N123:O123) -> -4.9921484e+10 | E48: ='Proforma Adjustment'!E136 -> 7.7806288e+09 | F48: ='Proforma Adjustment'!D139 -> 4.2140855e+10 | G48: =-'Consol SoPL-OCI 24'!G48 -> -1.2434076e+10 | H48: =SUM(C48:G48) -> -1.2193101e+10 | J48: =SUM('Elimination 2024'!H57,'Elimination 2024'!G62,'Elimination 2024'!H67) -> 1.2193101e+10 | L48: =SUM(H48,J48) -> 0.15010643
A49: PT Dummy - D | C49: =SUM('BS RP Disclosure 2024'!E253:F253) -> 21504957075 | D49: =SUM('Proforma Adjustment'!N120:O120) -> -1.4831474e+10 | E49: ='Proforma Adjustment'!E112 -> -2.910673e+09 | F49: ='Proforma Adjustment'!D115 -> 1.7742147e+10 | G49: =-'Consol SoPL-OCI 24'!G45 -> -5.1306523e+09 | H49: =SUM(C49:G49) -> 1.6374305e+10 | J49: =SUM('Elimination 2024'!H7,'Elimination 2024'!G10,'Elimination 2024'!H18,'Elimination 2024'!H23,'Elimination 2024'!G27) -> 6.2119903e+10 | L49: =SUM(H49,J49) -> 7.8494208e+10 | M49: =L49/2 -> 3.9247104e+10
A50: PT Dummy - E | C50: ='BS RP Disclosure 2024'!F254 -> 12049420 | D50: =SUM('Proforma Adjustment'!N121:O121) -> 1.2335771e+09 | E50: ='Proforma Adjustment'!E120 -> -1.5828349e+09 | F50: ='Proforma Adjustment'!D123 -> 3.4925771e+08 | G50: =-'Consol SoPL-OCI 24'!G46 -> -3.9719066e+09 | H50: =SUM(C50:G50) -> -3.9598572e+09 | J50: =SUM('Elimination 2024'!H31,'Elimination 2024'!G36,'Elimination 2024'!H41) -> 3.9598578e+09 | L50: =SUM(H50,J50) -> 670
A51: PT Dummy - F | C51: ='BS RP Disclosure 2024'!F255 -> 2510156250 | D51: =SUM('Proforma Adjustment'!N122:O122) -> 8.5136164e+09 | E51: ='Proforma Adjustment'!D127 -> -9.3333607e+09 | F51: ='Proforma Adjustment'!E132 -> 8.1974424e+08 | G51: =-'Consol SoPL-OCI 24'!G47 -> -9.0770283e+09 | H51: =SUM(C51:G51) -> -6.566872e+09 | J51: =SUM('Elimination 2024'!H44,'Elimination 2024'!G49,'Elimination 2024'!G53) -> 6.566872e+09 | L51: =SUM(H51,J51) -> -0.14200592
A52: PT Dummy - G
C53: =SUM(C48:C51) -> 24268137745 | D53: =SUM(D48:D51) -> -5.5005765e+10 | E53: =SUM(E48:E51) -> -6.0462397e+09 | F53: =SUM(F48:F51) -> 6.1052005e+10 | G53: =SUM(G48:G51) -> -3.0613663e+10 | H53: =SUM(H48:H51) -> -6.3455247e+09 | J53: =SUM(J48:J51) -> 8.4839734e+10 | L53: =SUM(L48:L51) -> 7.8494209e+10
C54: =SUM('BS RP Disclosure 2024'!E261:F261) -> 24268137745 | D54: =SUM('Consol SoFP 24'!Z40:AA40) -> -5.5005765e+10 | E54: =-'Consol SoPL-OCI 24'!AA50 -> -6.0462397e+09 | G54: =SUM('Consol SoFP 24'!F40) -> -30613662987 | H54: ='Consol SoFP 24'!AE40 -> -6.3258372e+09 | J54: ='Consol SoFP 24'!AG40 -> -1.1007427e+11 | L54: ='Consol SoFP 24'!AH40 -> 0
C55: =C53-C54 -> 0 | D55: =D53-D54 -> 0 | E55: =E53-E54 -> 0 | G55: =G53-G54 -> 0.084030151 | H55: =H53-H54 -> -19687500 | J55: =J53-J54 -> 1.94914e+11 | L55: =L53-L54 -> 7.8494209e+10
F56: =SUM(E53:F53) -> 5.5005765e+10
F57: ='Consol SoFP 24'!AB40 -> 5.5005765e+10
C58: =C56-C57 -> 0 | D58: =D56-D57 -> 0 | E58: =E56-E57 -> 0 | F58: =F56-F57 -> 0 | L58: =L56-L57 -> 0
G59: =G51+'Proforma Adjustment'!D127 -> -1.8410389e+10

Sheet Consol SoFP 24
C3: PT Dummy - C and its Subsidiaries
C4: Matter:
C5: Statement of Financial Position
L7: oke
H8: Dummy - C | L8: Dummy - D | O8: Dummy - E | S8: Dummy F | V8: Dummy - A | Y8: Dummy G
B9: Control to A=LE+E | D9: =D114+D53 -> 0 | E9: =E114+E53 -> 0 | H9: =H114+H53 -> 0 | I9: =I114+I53 -> 0 | J9: =J114+J53 -> 0 | L9: =L114+L53 -> 0 | M9: =M114+M53 -> 0 | O9: =O114+O53 -> 0 | P9: =P114+P53 -> 0 | Q9: =Q114+Q53 -> 0 | S9: =S114+S53 -> 0 | T9: =T114+T53 -> 0 | V9: =V114+V53 -> 0 | W9: =W114+W53 -> 0 | Y9: =Y114+Y53 -> 0 | Z9: =Z114+Z53 -> 0 | AA9: =AA114+AA53 -> 0 | AB9: =AB114+AB53 -> 0 | AC9: =SUM(AC12:AC114) -> 0 | AD9: =SUM(AD12:AD114) -> 0 | AE9: =AE114+AE53 -> 0 | AF9: =SUM(AF12:AF114) -> 3.6625151e+12 | AG9: =SUM(AG12:AG114) -> -3.6625151e+12 | AH9: =AH114+AH53 -> -0.18823242
B10: Description | D10: Per Book | E10: CLA | F10: Adjustment Equity Method | G10: Adjustment at consol | H10: Dummy - C | I10: Per Book | J10: CLA | K10: Adjustment at consol | L10: Dummy - D | M10: Dummy - E | N10: Adjustment at consol | O10: Dummy - E | P10: Per Book | Q10: CLA | R10: Adjustment at consol | S10: Dummy F | T10: Dummy - A | U10: Adjustment at consol | V10: Dummy - A | W10: Dummy G | X10: Adjustment at consol | Y10: Dummy G | Z10: Proforma Adjustment | AC10: Adjustment/ Reclassification | AE10: Combined | AF10: Elimination Entries | AH10: Consolidated
D11: 45657 | E11: 45657 | H11: 45657 | I11: 45657 | J11: 45657 | L11: 45657 | M11: 45657 | O11: 45657 | P11: 45657 | Q11: 45657 | S11: 45657 | T11: 45657 | V11: 45657 | W11: 45657 | Y11: 45657 | Z11: 44926 | AA11: 45291 | AB11: 45657 | AC11: Dr. | AD11: Cr. | AE11: 45657 | AF11: Dr. | AG11: Cr. | AH11: 45657
B13: ASSET
B14: CURRENT ASSET
B15: Cash and cash equivalents | D15: 62677974049 | E15: =-41826334020-24038265825+7250000000 -> -58614599845 | H15: =SUM(D15:E15) -> 4063374204 | I15: 37552005067 | J15: -11610679986 | L15: =SUM(I15:K15) -> 25941325081 | M15: 887896090 | O15: =SUM(M15:N15) -> 887896090 | P15: 3588753174 | Q15: 44193733 | S15: =SUM(P15:R15) -> 3632946907 | T15: 25054867533 | V15: =SUM(T15:U15) -> 25054867533 | W15: 1598125977 | Y15: =SUM(W15:X15) -> 1598125977 | AE15: =SUM(H15,L15,Z15,AA15,AC15:AD15,O15,S15,V15,Y15,AB15) -> 61178535792 | AH15: =ROUND(SUM(AE15:AG15),0) -> 61178535792
B16: Trade receivables | W16: 0
B17: Trade Receivables - Third Parties | D17: -7632229507 | E17: 7632229507 | H17: =SUM(D17:G17) -> 0 | I17: 13726195227 | J17: =26831819127-0.25 -> 2.6831819e+10 | L17: =SUM(I17:K17) -> 4.0558014e+10 | M17: 1464025584 | O17: =SUM(M17:N17) -> 1464025584 | P17: 3.7459812e+10 | Q17: -3.7459812e+10 | S17: =SUM(P17:R17) -> 0 | T17: =161473988972--0.67529296875 -> 1.6147399e+11 | V17: =SUM(T17:U17) -> 1.6147399e+11 | W17: 23251725 | Y17: =SUM(W17:X17) -> 23251725 | AE17: =SUM(H17,L17,Z17,AA17,AC17:AD17,O17,S17,V17,Y17,AB17) -> 2.0351928e+11 | AH17: =ROUND(SUM(AE17:AG17),0) -> 203519280635
B18: Trade Receivables - Related Parties | D18: -3721021958 | E18: 21936578161 | G18: ='Adjustment Consol'!J10+'Adjustment Consol'!J7+'Adjustment Consol'!I33+'Adjustment Consol'!I36+'Adjustment Consol'!I39+'Adjustment Consol'!J22+'Adjustment Consol'!I24 -> -4.5996643e+09 | H18: =SUM(D18:G18) -> 1.3615892e+10 | I18: 3698150207 | J18: 10840235364 | K18: ='Adjustment Consol'!I55 -> 2.204243e+09 | L18: =SUM(I18:K18) -> 1.6742629e+10 | M18: 0 | O18: =SUM(M18:N18) -> 0 | P18: 469001723 | Q18: 31647238381 | S18: =SUM(P18:R18) -> 32116240104 | T18: 18820641340 | V18: =SUM(T18:U18) -> 18820641340 | W18: 0 | Y18: =SUM(W18:X18) -> 0 | AE18: =SUM(H18,L18,Z18,AA18,AC18:AD18,O18,S18,V18,Y18,AB18) -> 8.1295402e+10 | AG18: =SUM('Elimination 2024'!H150,'Elimination 2024'!H153,'Elimination 2024'!H156,'Elimination 2024'!H159,'Elimination 2024'!H162,'Elimination 2024'!H165) -> -4.6323999e+10 | AH18: =ROUND(SUM(AE18:AG18),0) -> 34971402798
B19: Unbilled Receivable | W19: 0
B20: Unbilled - Third Parties | D20: 0 | E20: 0 | H20: =SUM(D20:G20) -> 0 | I20: 0 | J20: 0 | L20: =SUM(I20:K20) -> 0 | M20: 0 | O20: =SUM(M20:N20) -> 0 | P20: 13938025090 | Q20: -8.3884414e+09 | S20: =SUM(P20:R20) -> 5.5495836e+09 | T20: 0 | V20: =SUM(T20:U20) -> 0 | W20: 6.3178893e+08 | Y20: =SUM(W20:X20) -> 6.3178893e+08 | AE20: =SUM(H20,L20,Z20,AA20,AC20:AD20,O20,S20,V20,Y20,AB20) -> 6.1813726e+09 | AH20: =ROUND(SUM(AE20:AG20),0) -> 6181372571
B21: Unbilled - Related Parties | D21: 0 | E21: 0 | H21: =SUM(D21:G21) -> 0 | I21: 0 | J21: 0 | L21: =SUM(I21:K21) -> 0 | M21: 0 | O21: =SUM(M21:N21) -> 0 | P21: 0 | Q21: 0 | S21: =SUM(P21:R21) -> 0 | T21: 0 | V21: =SUM(T21:U21) -> 0 | W21: 0 | Y21: =SUM(W21:X21) -> 0 | AE21: =SUM(H21,L21,Z21,AA21,AC21:AD21,O21,S21,V21,Y21,AB21) -> 0 | AH21: =ROUND(SUM(AE21:AG21),0) -> 0
B22: Current portion of Lease receivables | D22: 0 | E22: 0 | H22: =SUM(D22:G22) -> 0 | I22: 17986480292 | J22: -12768739780 | L22: =SUM(I22:K22) -> 5217740512 | M22: 0 | O22: =SUM(M22:N22) -> 0 | P22: 0 | Q22: 0 | S22: =SUM(P22:R22) -> 0 | T22: 0 | V22: =SUM(T22:U22) -> 0 | W22: 0 | Y22: =SUM(W22:X22) -> 0 | AE22: =SUM(H22,L22,Z22,AA22,AC22:AD22,O22,S22,V22,Y22,AB22) -> 5217740512 | AH22: =ROUND(SUM(AE22:AG22),0) -> 5217740512
B23: Employee Receivables | D23: 236250000 | E23: 0 | H23: =SUM(D23:G23) -> 236250000 | I23: 507315342 | J23: 0 | L23: =SUM(I23:K23) -> 507315342 | M23: 0 | O23: =SUM(M23:N23) -> 0 | P23: 0 | Q23: 0 | S23: =SUM(P23:R23) -> 0 | T23: 0 | V23: =SUM(T23:U23) -> 0 | W23: 0 | Y23: =SUM(W23:X23) -> 0 | AE23: =SUM(H23,L23,Z23,AA23,AC23:AD23,O23,S23,V23,Y23,AB23) -> 743565342 | AH23: =ROUND(SUM(AE23:AG23),0) -> 743565342
B24: Loan Receivable | W24: 0
B25: Loan Receivable - Third Parties | D25: 2684635361 | E25: 0 | G25: ='Adjustment Consol'!I42 -> 4.2483385e+08 | H25: =SUM(D25:G25) -> 3.1094692e+09 | I25: 0 | J25: 0 | L25: =SUM(I25:K25) -> 0 | M25: 0 | O25: =SUM(M25:N25) -> 0 | P25: 0 | Q25: 0 | S25: =SUM(P25:R25) -> 0 | T25: 0 | V25: =SUM(T25:U25) -> 0 | W25: 0 | Y25: =SUM(W25:X25) -> 0 | AC25: 0 | AE25: =SUM(H25,L25,Z25,AA25,AC25:AD25,O25,S25,V25,Y25,AB25) -> 3.1094692e+09 | AH25: =ROUND(SUM(AE25:AG25),0) -> 3109469207
B26: Loan Receivable - Related Parties | D26: 362561297932 | E26: 874798300958 | G26: ='Adjustment Consol'!I9+'Adjustment Consol'!I15+'Adjustment Consol'!I18+'Adjustment Consol'!I6+'Adjustment Consol'!I12+'Adjustment Consol'!J43+'Adjustment Consol'!I21 -> 3.2757618e+10 | H26: =SUM(D26:G26) -> 1.2701172e+12 | I26: -32369740768 | J26: 74851107918 | K26: ='Adjustment Consol'!I45 -> 1.592556e+10 | L26: =SUM(I26:K26) -> 5.8406927e+10 | M26: 22197208320 | N26: ='Adjustment Consol'!I74 -> 5.7943386e+08 | O26: =SUM(M26:N26) -> 2.2776642e+10 | P26: 34960642633 | Q26: 62554427406 | S26: =SUM(P26:R26) -> 97515070039 | T26: -4711560001 | U26: ='Adjustment Consol'!I77+'Adjustment Consol'!I80 -> 1.6012185e+10 | V26: =SUM(T26:U26) -> 1.1300625e+10 | W26: 0 | Y26: =SUM(W26:X26) -> 0 | AE26: =SUM(H26,L26,Z26,AA26,AC26:AD26,O26,S26,V26,Y26,AB26) -> 1.4601165e+12 | AF26: ='Elimination 2024'!G82 -> 9.1240269e+09 | AG26: ='Elimination 2024'!H73+'Elimination 2024'!H76+'Elimination 2024'!H79+'Elimination 2024'!H84+'Elimination 2024'!H87+'Elimination 2024'!H90+'Elimination 2024'!H93+'Elimination 2024'!H96+'Elimination 2024'!H99+'Elimination 2024'!H102+'Elimination 2024'!H105+'Elimination 2024'!H108+'Elimination 2024'!H111+'Elimination 2024'!H114+'Elimination 2024'!H117+'Elimination 2024'!H120 -> -1.3375624e+12 | AH26: =ROUND(SUM(AE26:AG26),0) -> 131678101647
B27: Other Receivables | M27: 0 | P27: 0 | W27: 0
B28: Other Receivable - Third Parties | D28: 2273954718 | E28: =-1986498808--0.199996948242187 -> -1.9864988e+09 | H28: =SUM(D28:G28) -> 2.8745591e+08 | I28: 1260520835 | J28: 6523399681 | L28: =SUM(I28:K28) -> 7783920516 | M28: 0 | O28: =SUM(M28:N28) -> 0 | P28: 764617335 | Q28: -502454320 | S28: =SUM(P28:R28) -> 262163015 | T28: 0 | V28: =SUM(T28:U28) -> 0 | W28: 26511202 | Y28: =SUM(W28:X28) -> 26511202 | AE28: =SUM(H28,L28,Z28,AA28,AC28:AD28,O28,S28,V28,Y28,AB28) -> 8.3600506e+09 | AH28: =ROUND(SUM(AE28:AG28),0) -> 8360050643
B29: Other Receivable - Related Parties | D29: 37480750502 | E29: 21625811503 | F29: 0 | G29: ='Adjustment Consol'!J40 -> -8.8162005e+08 | H29: =SUM(D29:G29) -> 5.8224942e+10 | I29: =69939941939-17351817049.224 -> 5.2588125e+10 | J29: 31995748484 | K29: ='Adjustment Consol'!J49 -> -5.091988e+08 | L29: =SUM(I29:K29) -> 8.4074675e+10 | M29: 1804200965 | O29: =SUM(M29:N29) -> 1804200965 | P29: 0 | Q29: 0 | S29: =SUM(P29:R29) -> 0 | T29: 0 | V29: =SUM(T29:U29) -> 0 | W29: 0 | Y29: =SUM(W29:X29) -> 0 | AE29: =SUM(H29,L29,Z29,AA29,AC29:AD29,O29,S29,V29,Y29,AB29) -> 1.4410382e+11 | AG29: ='Elimination 2024'!H123+SUM('Elimination 2024'!H126:H129)+'Elimination 2024'!H144+'Elimination 2024'!H147+'Elimination 2024'!H135+'Elimination 2024'!H138+'Elimination 2024'!H141 -> -9.3345703e+10 | AH29: =ROUND(SUM(AE29:AG29),0) -> 50758114819
B30: Inventories | D30: 0 | E30: 0 | H30: =SUM(D30:G30) -> 0 | I30: -3230677550 | J30: 3230677550 | L30: =SUM(I30:K30) -> 0 | M30: 0 | O30: =SUM(M30:N30) -> 0 | P30: 0 | Q30: 0 | S30: =SUM(P30:R30) -> 0 | T30: 0 | V30: =SUM(T30:U30) -> 0 | W30: 2.6873752e+08 | Y30: =SUM(W30:X30) -> 2.6873752e+08 | AE30: =SUM(H30,L30,Z30,AA30,AC30:AD30,O30,S30,V30,Y30,AB30) -> 2.6873752e+08 | AH30: =ROUND(SUM(AE30:AG30),0) -> 268737517
B31: Prepaid Tax | D31: -1344536470 | E31: 2115386814 | H31: =SUM(D31:G31) -> 770850344 | I31: -5179648363 | J31: =-I31 -> 5179648363 | L31: =SUM(I31:K31) -> 0 | M31: 1628484531 | O31: =SUM(M31:N31) -> 1628484531 | P31: -18145906 | Q31: =-P31 -> 18145906 | S31: =SUM(P31:R31) -> 0 | T31: 3868129044 | V31: =SUM(T31:U31) -> 3868129044 | W31: 0 | Y31: =SUM(W31:X31) -> 0 | AE31: =SUM(H31,L31,Z31,AA31,AC31:AD31,O31,S31,V31,Y31,AB31) -> 6267463919 | AH31: =ROUND(SUM(AE31:AG31),0) -> 6267463919
B32: Prepayment and Advances | D32: 3.0642728e+09 | E32: -10465648 | H32: =SUM(D32:G32) -> 3.0538071e+09 | I32: 17363804453 | J32: -13667088966 | L32: =SUM(I32:K32) -> 3696715487 | M32: 808894385 | O32: =SUM(M32:N32) -> 808894385 | P32: 157000904 | Q32: -21407540 | S32: =SUM(P32:R32) -> 135593364 | T32: 2130408993 | V32: =SUM(T32:U32) -> 2130408993 | W32: 11529000 | Y32: =SUM(W32:X32) -> 11529000 | AE32: =SUM(H32,L32,Z32,AA32,AC32:AD32,O32,S32,V32,Y32,AB32) -> 9.8369483e+09 | AH32: =ROUND(SUM(AE32:AG32),0) -> 9836948341
B33: Deposits | D33: 2547137611 | E33: -2343288070 | H33: =SUM(D33:G33) -> 203849541 | I33: 0 | J33: 0 | L33: =SUM(I33:K33) -> 0 | M33: 0 | O33: =SUM(M33:N33) -> 0 | P33: 0 | Q33: 0 | S33: =SUM(P33:R33) -> 0 | T33: 0 | V33: =SUM(T33:U33) -> 0 | W33: 0 | Y33: =SUM(W33:X33) -> 0 | AE33: =SUM(H33,L33,Z33,AA33,AC33:AD33,O33,S33,V33,Y33,AB33) -> 203849541 | AH33: =ROUND(SUM(AE33:AG33),0) -> 203849541
B34: Restricted Cash and Time Deposits | D34: 0 | E34: 40000000000 | H34: =SUM(D34:E34) -> 40000000000 | I34: 64625421475 | J34: -1211853055 | L34: =SUM(I34:K34) -> 63413568420 | M34: 0 | O34: =SUM(M34:N34) -> 0 | P34: 39375000000 | Q34: 0 | S34: =SUM(P34:R34) -> 39375000000 | T34: 407039498 | V34: =SUM(T34:U34) -> 407039498 | W34: 0 | Y34: =SUM(W34:X34) -> 0 | AE34: =SUM(H34,L34,Z34,AA34,AC34:AD34,O34,S34,V34,Y34,AB34) -> 143195607918 | AH34: =ROUND(SUM(AE34:AG34),0) -> 143195607918
B35: Other Current Assets | D35: -1049795960 | E35: =1038692880-231525+11576250+-241645 -> 1049795960 | H35: =SUM(D35:G35) -> 0 | I35: =157174881--211837500.273376 -> 3.6901238e+08 | J35: 190396710 | K35: ='Adjustment Consol'!I48 -> 5.091988e+08 | L35: =SUM(I35:K35) -> 1.0686079e+09 | M35: 0 | O35: =SUM(M35:N35) -> 0 | P35: 425165488 | Q35: =-124535250-12048750.2750015 -> -1.36584e+08 | S35: =SUM(P35:R35) -> 2.8858149e+08 | T35: 293548500 | U35: ='Adjustment Consol'!J81 -> -86625000 | V35: =SUM(T35:U35) -> 206923500 | W35: 0 | Y35: =SUM(W35:X35) -> 0 | AE35: =SUM(H35,L35,Z35,AA35,AC35:AD35,O35,S35,V35,Y35,AB35) -> 1.5641129e+09 | AH35: =ROUND(SUM(AE35:AG35),0) -> 1564112875
B37: TOTAL CURRENT ASSETS | D37: =SUM(D14:D36) -> 4.5977869e+11 | E37: =SUM(E14:E36) -> 9.0620325e+11 | H37: =SUM(H14:H36) -> 1.3936831e+12 | I37: =SUM(I14:I36) -> 1.6889696e+11 | J37: =SUM(J14:J36) -> 1.2038467e+11 | L37: =SUM(L14:L36) -> 3.0741144e+11 | M37: =SUM(M14:M36) -> 28790709875 | O37: =SUM(O14:O36) -> 2.9370144e+10 | P37: =SUM(P14:P36) -> 1.3111987e+11 | Q37: =SUM(Q14:Q36) -> 4.7755306e+10 | S37: =SUM(S14:S36) -> 1.7887518e+11 | T37: =SUM(T14:T36) -> 2.0733706e+11 | V37: =SUM(V14:V36) -> 2.2326262e+11 | W37: =SUM(W14:W36) -> 2.5599443e+09 | Y37: =SUM(Y14:Y36) -> 2.5599443e+09 | AE37: =SUM(AE14:AE36) -> 2.1351624e+12 | AH37: =SUM(AH14:AH36) -> 667054354077
D38: ^ | E38: ^ | I38: ^ | J38: ^ | M38: ^ | P38: ^ | Q38: ^ | T38: ^ | W38: ^ | AE38: ^
B39: Investments
B40: Investment in Subsidiaries | D40: =79329820854+240975000 -> 79570795854 | E40: =-55291555029+231525-11576250--241645 -> -55302658109 | F40: =ROUND(SUM('Equity & Adjustment Consol'!C34:H34),0) -> -30613662987 | H40: =SUM(D40:G40) -> -6345525242 | I40: 19687500 | J40: 0 | L40: =SUM(I40:K40) -> 19687500 | M40: 0 | O40: =SUM(M40:N40) -> 0 | S40: =SUM(P40:R40) -> 0 | T40: 0 | V40: =SUM(T40:U40) -> 0 | W40: 0 | Y40: =SUM(W40:X40) -> 0 | Z40: ='Consol SoFP 23 & 22'!X40 -> 2.0937199e+09 | AA40: ='Consol SoFP 23 & 22'!Y40 -> -5.7099484e+10 | AB40: =-AB106 -> 5.5005765e+10 | AE40: =SUM(H40,L40,Z40,AA40,AC40:AD40,O40,S40,V40,Y40,AB40) -> -6.3258372e+09 | AF40: ='Elimination 2024'!G10+'Elimination 2024'!G36+'Elimination 2024'!G49+'Elimination 2024'!G62 -> 1.1640011e+11 | AG40: ='Elimination 2024'!H7+'Elimination 2024'!H18+'Elimination 2024'!H23+'Elimination 2024'!H28+'Elimination 2024'!H31+'Elimination 2024'!H41+'Elimination 2024'!H44+'Elimination 2024'!G53+'Elimination 2024'!H57+'Elimination 2024'!H67+'Elimination 2024'!H70 -> -1.1007427e+11 | AH40: =ROUND(SUM(AE40:AG40),0) -> 0
B41: Deemed Investment | D41: 976364006631 | E41: -976364006631 | F41: =SUM('Adjustment Consol'!G80,'Adjustment Consol'!G83,'Adjustment Consol'!G86) -> 0 | H41: =SUM(D41:G41) -> 0 | I41: 20779414154 | J41: -20779414154 | L41: =SUM(I41:K41) -> 0 | M41: 0 | O41: =SUM(M41:N41) -> 0 | P41: 50779755437 | Q41: =-50791804187--12048750.2750015 -> -5.0779755e+10 | S41: =SUM(P41:R41) -> 0.27500153 | T41: 0 | V41: =SUM(T41:U41) -> 0 | W41: 0 | Y41: =SUM(W41:X41) -> 0 | AE41: =SUM(H41,L41,Z41,AA41,AC41:AD41,O41,S41,V41,Y41,AB41) -> 0.27500153 | AH41: =SUM(AE41:AG41) -> 0.27500153
B42: Lease Receivables - Non Current | D42: 0 | E42: 0 | H42: =SUM(D42:G42) -> 0 | I42: 0 | J42: 0 | L42: =SUM(I42:K42) -> 0 | M42: 0 | O42: =SUM(M42:N42) -> 0 | P42: 0 | Q42: 0 | S42: =SUM(P42:R42) -> 0 | T42: 0 | V42: =SUM(T42:U42) -> 0 | W42: 0 | Y42: =SUM(W42:X42) -> 0 | AE42: =SUM(H42,L42,Z42,AA42,AC42:AD42,O42,S42,V42,Y42,AB42) -> 0 | AH42: =ROUND(SUM(AE42:AG42),0) -> 0 | AJ42: =-AJ41 -> 0
B43: Fixed Assets | D43: 34746004940 | E43: -34312390817 | H43: =SUM(D43:G43) -> 433614123 | I43: -2909334616 | J43: 30758023232 | L43: =SUM(I43:K43) -> 27848688616 | M43: 15897898189 | O43: =SUM(M43:N43) -> 15897898189 | P43: 58314473 | Q43: -6284250 | S43: =SUM(P43:R43) -> 52030223 | T43: =27415430721.8+257925937.5 -> 2.7673357e+10 | V43: =SUM(T43:U43) -> 2.7673357e+10 | W43: 2113125.5 | Y43: =SUM(W43:X43) -> 2113125.5 | AE43: =SUM(H43,L43,Z43,AA43,AC43:AD43,O43,S43,V43,Y43,AB43) -> 7.1907701e+10 | AH43: =ROUND(SUM(AE43:AG43),0) -> 71907700936
B44: Intangible Assets | D44: -21200641572 | E44: 29909546979 | H44: =SUM(D44:G44) -> 8708905407 | I44: 12097450124 | J44: -4336846857 | L44: =SUM(I44:K44) -> 7760603267 | M44: 0 | O44: =SUM(M44:N44) -> 0 | P44: 171950625 | Q44: -171950625 | S44: =SUM(P44:R44) -> 0 | T44: 0 | V44: =SUM(T44:U44) -> 0 | W44: 0 | Y44: =SUM(W44:X44) -> 0 | AE44: =SUM(H44,L44,Z44,AA44,AC44:AD44,O44,S44,V44,Y44,AB44) -> 16469508674 | AH44: =ROUND(SUM(AE44:AG44),0) -> 16469508674
B45: Right of Used of Asset | D45: 0 | E45: 0 | H45: =SUM(D45:G45) -> 0 | I45: 15146709252 | J45: 21095737557 | L45: =SUM(I45:K45) -> 36242446809 | M45: 0 | O45: =SUM(M45:N45) -> 0 | P45: 0 | Q45: 0 | S45: =SUM(P45:R45) -> 0 | T45: 0 | V45: =SUM(T45:U45) -> 0 | W45: 0 | Y45: =SUM(W45:X45) -> 0 | AE45: =SUM(H45,L45,Z45,AA45,AC45:AD45,O45,S45,V45,Y45,AB45) -> 36242446809 | AH45: =ROUND(SUM(AE45:AG45),0) -> 36242446809
B46: Shareholder Receivable | D46: 410071174 | E46: 0 | H46: =SUM(D46:G46) -> 410071174 | I46: 0 | J46: 0 | L46: =SUM(I46:K46) -> 0 | M46: 23625000 | O46: =SUM(M46:N46) -> 23625000 | P46: 1789200000 | Q46: -116131641 | S46: =SUM(P46:R46) -> 1673068359 | T46: 187728068 | V46: =SUM(T46:U46) -> 187728068 | W46: 19687500 | Y46: =SUM(W46:X46) -> 19687500 | AD46: 0 | AE46: =SUM(H46,L46,Z46,AA46,AC46:AD46,O46,S46,V46,Y46,AB46) -> 2314180101 | AH46: =ROUND(SUM(AE46:AG46),0) -> 2314180101
B47: Prepayments - non-current | D47: 0 | E47: 0 | H47: =SUM(D47:G47) -> 0 | I47: 0 | J47: 0 | L47: =SUM(I47:K47) -> 0 | M47: 0 | O47: =SUM(M47:N47) -> 0 | P47: 0 | Q47: 0 | S47: =SUM(P47:R47) -> 0 | T47: 0 | V47: =SUM(T47:U47) -> 0 | W47: 0 | Y47: =SUM(W47:X47) -> 0 | AD47: 0 | AE47: =SUM(H47,L47,Z47,AA47,AC47:AD47,O47,S47,V47,Y47,AB47) -> 0 | AH47: =ROUND(SUM(AE47:AG47),0) -> 0
B48: Deferred Tax Asset | D48: 0 | E48: 0 | H48: =SUM(D48:G48) -> 0 | I48: 0 | J48: 0 | L48: =SUM(I48:K48) -> 0 | M48: 0 | O48: =SUM(M48:N48) -> 0 | P48: 0 | Q48: 0 | S48: =SUM(P48:R48) -> 0 | T48: 0 | V48: =SUM(T48:U48) -> 0 | W48: 0 | Y48: =SUM(W48:X48) -> 0 | AE48: =SUM(H48,L48,Z48,AA48,AC48:AD48,O48,S48,V48,Y48,AB48) -> 0 | AH48: =ROUND(SUM(AE48:AG48),0) -> 0
B49: Other non-current asset | D49: -1118936546 | E49: 2377361546 | H49: =SUM(D49:G49) -> 1258425000 | I49: 81501258425 | J49: 2042524488 | L49: =SUM(I49:K49) -> 83543782913 | M49: 0 | O49: =SUM(M49:N49) -> 0 | P49: 0 | Q49: 57834000 | S49: =SUM(P49:R49) -> 57834000 | V49: =SUM(T49:U49) -> 0 | W49: 0 | Y49: =SUM(W49:X49) -> 0 | AE49: =SUM(H49,L49,Z49,AA49,AC49:AD49,O49,S49,V49,Y49,AB49)-552.08154296875 -> 8.4860041e+10 | AH49: =ROUND(SUM(AE49:AG49),0)+555 -> 84860041916
B51: TOTAL NON CURRENT ASSETS | D51: =SUM(D39:D50) -> 1068771300481 | E51: =SUM(E39:E50) -> -1033692147032 | H51: =SUM(H39:H50) -> 4465490462 | I51: =SUM(I39:I50) -> 126635184839 | J51: =SUM(J39:J50) -> 28780024266 | L51: =SUM(L39:L50) -> 155415209105 | M51: =SUM(M39:M50) -> 15921523189 | O51: =SUM(O39:O50) -> 15921523189 | P51: =SUM(P39:P50) -> 52799220535 | Q51: =SUM(Q39:Q50) -> -5.1016288e+10 | S51: =SUM(S39:S50) -> 1.7829326e+09 | T51: =SUM(T39:T50) -> 2.7861085e+10 | V51: =SUM(V39:V50) -> 2.7861085e+10 | W51: =SUM(W39:W50) -> 21800626 | Y51: =SUM(Y39:Y50) -> 21800626 | AE51: =SUM(AE39:AE50) -> 2.0546804e+11 | AH51: =SUM(AH39:AH50) -> 2.1179388e+11
D52: ^ | E52: ^ | I52: ^ | J52: ^ | M52: ^ | P52: ^ | Q52: ^ | T52: ^ | W52: ^ | AE52: ^ | AH52: ^
B53: TOTAL ASSETS | D53: =D37+D51 -> 1.52855e+12 | E53: =E37+E51 -> -1.274889e+11 | H53: =H37+H51 -> 1.3981486e+12 | I53: =I37+I51 -> 2.9553215e+11 | J53: =J37+J51 -> 1.491647e+11 | L53: =L37+L51 -> 4.6282665e+11 | M53: =M37+M51 -> 44712233064 | O53: =O37+O51 -> 4.5291667e+10 | P53: =P37+P51 -> 1.8391909e+11 | Q53: =Q37+Q51 -> -3.260982e+09 | S53: =S37+S51 -> 1.8065811e+11 | T53: =T37+T51 -> 2.3519815e+11 | V53: =V37+V51 -> 2.5112371e+11 | W53: =W37+W51 -> 2.581745e+09 | Y53: =Y37+Y51 -> 2.581745e+09 | AE53: =AE37+AE51 -> 2.3406305e+12 | AH53: =AH37+AH51 -> 8.7884823e+11
D54: ^ | E54: ^ | I54: ^ | J54: ^ | M54: ^ | P54: ^ | Q54: ^ | T54: ^ | W54: ^ | AE54: ^
B55: LIABILITIES
B56: CURRENT LIABILITIES
B57: Short-tern Bank Loans | D57: -46943428544 | E57: 0 | H57: =SUM(D57:G57) -> -46943428544 | I57: -15523844205 | J57: 15523844205 | L57: =SUM(I57:K57) -> 0 | M57: 0 | O57: =SUM(M57:N57) -> 0 | P57: -39247030249 | Q57: 0 | S57: =SUM(P57:R57) -> -39247030249 | T57: -23497929999 | V57: =SUM(T57:U57) -> -23497929999 | W57: 0 | X57: 0 | Y57: =SUM(W57:X57) -> 0 | AE57: =SUM(H57,L57,Z57,AA57,AC57:AD57,O57,S57,V57,Y57,AB57) -> -109688388792 | AH57: =ROUND(SUM(AE57:AG57),0) -> -109688388792
B58: Account Payable
B59: Account Payable - Third Parties | D59: -1.9509198e+10 | E59: -346379424 | H59: =SUM(D59:G59) -> -1.9855578e+10 | I59: 11359025634 | J59: -14159137597 | L59: =SUM(I59:K59) -> -2800111963 | M59: 0 | N59: ='Adjustment Consol'!J75 -> -5.7943386e+08 | O59: =SUM(M59:N59) -> -5.7943386e+08 | P59: =-1184567608-223349175 -> -1407916783 | Q59: =3006407222+158356800 -> 3164764022 | S59: =SUM(P59:R59) -> 1756847239 | T59: -68920311050 | V59: =SUM(T59:U59) -> -68920311050 | W59: -54870466 | X59: 0 | Y59: =SUM(W59:X59) -> -54870466 | AE59: =SUM(H59,L59,Z59,AA59,AC59:AD59,O59,S59,V59,Y59,AB59) -> -9.0453458e+10 | AH59: =ROUND(SUM(AE59:AG59),0) -> -90453457743
B60: Account Payable - Related Parties | D60: 0 | E60: -775151124 | G60: ='Adjustment Consol'!J25 -> -2.2896913e+09 | H60: =SUM(D60:G60) -> -3.0648424e+09 | I60: 562427707792 | J60: -562427707792 | L60: =SUM(I60:K60) -> 0 | M60: 0 | O60: =SUM(M60:N60) -> 0 | P60: -67473000 | Q60: 0 | S60: =SUM(P60:R60) -> -67473000 | T60: 0 | V60: =SUM(T60:U60) -> 0 | W60: 0 | X60: 0 | Y60: =SUM(W60:X60) -> 0 | AE60: =SUM(H60,L60,Z60,AA60,AC60:AD60,O60,S60,V60,Y60,AB60) -> -3.1323154e+09 | AH60: =ROUND(SUM(AE60:AG60),0) -> -3132315377
B61: Accrued Expenses
B62: Accrued Expenses - Third Parties | D62: -23570578229 | E62: 13365595881 | H62: =SUM(D62:G62) -> -10204982348 | I62: -36323317490 | J62: 13897531496 | L62: =SUM(I62:K62) -> -22425785994 | M62: -1538442357 | N62: =-N101 -> -2.8944144e+08 | O62: =SUM(M62:N62) -> -1.8278838e+09 | P62: -3708612087 | Q62: 363640024 | S62: =SUM(P62:R62) -> -3344972063 | T62: 12710962077 | V62: =SUM(T62:U62) -> 12710962077 | W62: -1.3034113e+09 | X62: 0 | Y62: =SUM(W62:X62) -> -1.3034113e+09 | AE62: =SUM(H62,L62,Z62,AA62,AC62:AD62,O62,S62,V62,Y62,AB62) -> -2.6396073e+10 | AH62: =ROUND(SUM(AE62:AG62),0) -> -26396073458
B63: Accrued Expenses - Related Parties | D63: -65017402 | E63: -24115768113 | G63: ='Adjustment Consol'!J34 -> -3.5315861e+09 | H63: =SUM(D63:G63) -> -2.7712372e+10 | I63: -21605108 | J63: 0 | K63: ='Adjustment Consol'!J53 -> -2.1421685e+09 | L63: =SUM(I63:K63) -> -2.1637736e+09 | M63: 0 | O63: =SUM(M63:N63) -> 0 | P63: -6871273 | Q63: -16978511147 | S63: =SUM(P63:R63) -> -16985382420 | T63: -9535163807 | V63: =SUM(T63:U63) -> -9535163807 | W63: 0 | X63: 0 | Y63: =SUM(W63:X63) -> 0 | AE63: =SUM(H63,L63,Z63,AA63,AC63:AD63,O63,S63,V63,Y63,AB63) -> -5.6396691e+10 | AF63: ='Elimination 2024'!G122+SUM('Elimination 2024'!G149,'Elimination 2024'!G152,'Elimination 2024'!G155,'Elimination 2024'!G158,'Elimination 2024'!G161) -> 5.4740018e+10 | AH63: =ROUND(SUM(AE63:AG63),0) -> -1656673854
B64: Deposit Payable | D64: 2790907089 | E64: -2817573912 | H64: =SUM(D64:G64) -> -26666823 | I64: -2190537514 | J64: 619218404 | L64: =SUM(I64:K64) -> -1571319110 | M64: 0 | O64: =SUM(M64:N64) -> 0 | P64: 0 | Q64: 0 | S64: =SUM(P64:R64) -> 0 | T64: 0 | V64: =SUM(T64:U64) -> 0 | W64: 0 | X64: 0 | Y64: =SUM(W64:X64) -> 0 | AE64: =SUM(H64,L64,Z64,AA64,AC64:AD64,O64,S64,V64,Y64,AB64) -> -1597985933 | AH64: =ROUND(SUM(AE64:AG64),0) -> -1597985933
B65: Tax Payables | D65: 754361138 | E65: -1449438162 | H65: =SUM(D65:G65) -> -695077024 | I65: 1641417929 | J65: -322309542 | L65: =SUM(I65:K65) -> 1319108387 | M65: -379032447 | O65: =SUM(M65:N65) -> -379032447 | P65: -377730535 | Q65: 242656293 | S65: =SUM(P65:R65) -> -135074242 | T65: -401782194 | V65: =SUM(T65:U65) -> -401782194 | W65: -59343864 | X65: 0 | Y65: =SUM(W65:X65) -> -59343864 | AE65: =SUM(H65,L65,Z65,AA65,AC65:AD65,O65,S65,V65,Y65,AB65) -> -3.5120138e+08 | AH65: =ROUND(SUM(AE65:AG65),0) -> -351201384
B66: Loan Payable Related Party | D66: -157149021046 | E66: 136665061717 | G66: ='Adjustment Consol'!J16+'Adjustment Consol'!J19+'Adjustment Consol'!J13 -> -1.0637191e+10 | H66: =SUM(D66:G66) -> -3.1121151e+10 | I66: -603276477415 | J66: -406567657574 | K66: ='Adjustment Consol'!J46 -> -1.592556e+10 | L66: =SUM(I66:K66) -> -1.0257697e+12 | M66: -37542606781 | O66: =SUM(M66:N66) -> -37542606781 | P66: -735738971 | Q66: -129243390324 | S66: =SUM(P66:R66) -> -129979129295 | T66: -169694347759 | U66: ='Adjustment Consol'!J78 -> -1.592556e+10 | V66: =SUM(T66:U66) -> -1.8561991e+11 | W66: -7875000 | X66: -239400000 | Y66: =SUM(W66:X66) -> -247275000 | AE66: =SUM(H66,L66,Z66,AA66,AC66:AD66,O66,S66,V66,Y66,AB66) -> -1.4102798e+12 | AF66: ='Elimination 2024'!G72+'Elimination 2024'!G75+'Elimination 2024'!G78+'Elimination 2024'!G81+'Elimination 2024'!G86++'Elimination 2024'!G89+'Elimination 2024'!G92+'Elimination 2024'!G95+'Elimination 2024'!G98+'Elimination 2024'!G101++'Elimination 2024'!G104+'Elimination 2024'!G107+'Elimination 2024'!G110+'Elimination 2024'!G113+'Elimination 2024'!G116+'Elimination 2024'!G119 -> 1.3375624e+12 | AG66: ='Elimination 2024'!H83 -> -9.1240269e+09 | AH66: =ROUND(SUM(AE66:AG66),0) -> -81841385213
B67: Other Payables
B68: Other Payable - Third Parties | D68: 0 | E68: 0 | G68: ='Adjustment Consol'!G76 -> 0 | H68: =SUM(D68:G68) -> 0 | I68: 0 | J68: 0 | L68: =SUM(I68:K68) -> 0 | M68: 0 | O68: =SUM(M68:N68) -> 0 | P68: 104465326 | Q68: -6716976821 | S68: =SUM(P68:R68) -> -6612511495 | T68: 0 | V68: =SUM(T68:U68) -> 0 | W68: 0 | X68: 0 | Y68: =SUM(W68:X68) -> 0 | AE68: =SUM(H68,L68,Z68,AA68,AC68:AD68,O68,S68,V68,Y68,AB68) -> -6612511495 | AH68: =ROUND(SUM(AE68:AG68),0) -> -6612511495
B69: Other Payable - Related Parties | D69: -1130613.8 | E69: -46093950 | H69: =SUM(D69:G69) -> -47224564 | I69: =-14285797676--17351817049.224 -> 3.0660194e+09 | J69: -3066019373 | K69: 0 | L69: =SUM(I69:K69) -> 0.22399902 | M69: 0 | O69: =SUM(M69:N69) -> 0 | P69: =-5344262167--223349175 -> -5120912992 | Q69: 0 | S69: =SUM(P69:R69) -> -5120912992 | T69: -30256823164 | U69: =-U102 -> -2.8711286e+10 | V69: =SUM(T69:U69) -> -5.8968109e+10 | W69: 0 | X69: 0 | Y69: =SUM(W69:X69) -> 0 | AE69: =SUM(H69,L69,Z69,AA69,AC69:AD69,O69,S69,V69,Y69,AB69) -> -6.4136246e+10 | AF69: ='Elimination 2024'!G146+'Elimination 2024'!G143+'Elimination 2024'!G164+'Elimination 2024'!G140 -> 6.4090152e+10 | AH69: =ROUND(SUM(AE69:AG69),0) -> -46093952
B70: Borrowings | D70: 0 | E70: 0 | H70: =SUM(D70:G70) -> 0 | I70: 0 | J70: 0 | L70: =SUM(I70:K70) -> 0 | M70: 0 | O70: =SUM(M70:N70) -> 0 | P70: 0 | Q70: 0 | S70: =SUM(P70:R70) -> 0 | T70: 0 | V70: =SUM(T70:U70) -> 0 | W70: 0 | X70: 0 | Y70: =SUM(W70:X70) -> 0 | AE70: =ROUND(SUM(H70,L70,Z70,AA70,AC70:AD70,O70,S70,V70,Y70,AB70),0) -> 0 | AH70: =ROUND(SUM(AE70:AG70),0) -> 0
B71: Consumer Financing Payables - Current Portion | D71: 0 | E71: 0 | H71: =SUM(D71:G71) -> 0 | I71: 0 | J71: 0 | L71: =SUM(I71:K71) -> 0 | O71: =SUM(M71:N71) -> 0 | P71: 0 | Q71: 0 | S71: =SUM(P71:R71) -> 0 | T71: 0 | V71: =SUM(T71:U71) -> 0 | W71: 0 | X71: 0 | Y71: =SUM(W71:X71) -> 0 | AE71: =SUM(H71,L71,Z71,AA71,AC71:AD71,O71,S71,V71,Y71,AB71) -> 0 | AH71: =ROUND(SUM(AE71:AG71),0) -> 0
B72: Payable to Subsidiaries | D72: 0 | E72: 0 | H72: =SUM(D72:G72) -> 0 | I72: -6289708320 | J72: 6289708320 | L72: =SUM(I72:K72) -> 0 | M72: 0 | O72: =SUM(M72:N72) -> 0 | P72: 0 | Q72: 0 | S72: =SUM(P72:R72) -> 0 | V72: =SUM(T72:U72) -> 0 | W72: 0 | X72: 0 | Y72: =SUM(W72:X72) -> 0 | AE72: =SUM(H72,L72,Z72,AA72,AC72:AD72,O72,S72,V72,Y72,AB72) -> 0 | AH72: =ROUND(SUM(AE72:AG72),0) -> 0
B73: Payable to Shareholders | D73: 0 | H73: =SUM(D73:G73) -> 0 | I73: 0 | J73: 0 | L73: =SUM(I73:K73) -> 0 | M73: 0 | O73: =SUM(M73:N73) -> 0 | P73: -78750000 | Q73: 78750000 | S73: =SUM(P73:R73) -> 0 | T73: 0 | V73: =SUM(T73:U73) -> 0 | W73: 0 | X73: 0 | Y73: =SUM(W73:X73) -> 0 | AE73: =SUM(H73,L73,Z73,AA73,AC73:AD73,O73,S73,V73,Y73,AB73) -> 0 | AH73: =ROUND(SUM(AE73:AG73),0) -> 0
B74: Unearned Revenue | D74: 0 | E74: 0 | H74: =SUM(D74:G74) -> 0 | I74: -19188165377 | J74: -2508611148 | L74: =SUM(I74:K74) -> -21696776525 | M74: 0 | O74: =SUM(M74:N74) -> 0 | P74: -327908914 | Q74: 0 | S74: =SUM(P74:R74) -> -327908914 | T74: 0 | V74: =SUM(T74:U74) -> 0 | W74: 0 | X74: 0 | Y74: =SUM(W74:X74) -> 0 | AE74: =SUM(H74,L74,Z74,AA74,AC74:AD74,O74,S74,V74,Y74,AB74) -> -22024685439 | AH74: =ROUND(SUM(AE74:AG74),0) -> -22024685439
B75: Current Maturities of Lease Liability | D75: 0 | E75: 0 | H75: =SUM(D75:G75) -> 0 | I75: -57438550501 | J75: 19669278189 | L75: =SUM(I75:K75) -> -37769272312 | M75: -2337553728 | O75: =SUM(M75:N75) -> -2337553728 | P75: 0 | Q75: 0 | S75: =SUM(P75:R75) -> 0 | T75: -4139900766 | V75: =SUM(T75:U75) -> -4139900766 | W75: 0 | X75: 0 | Y75: =SUM(W75:X75) -> 0 | AE75: =SUM(H75,L75,Z75,AA75,AC75:AD75,O75,S75,V75,Y75,AB75) -> -44246726806 | AH75: =ROUND(SUM(AE75:AG75),0) -> -44246726806
B76: Other Current Liabilities | D76: 0 | E76: 0 | H76: =SUM(D76:G76) -> 0 | I76: 0 | J76: 0 | L76: =SUM(I76:K76) -> 0 | M76: 0 | O76: =SUM(M76:N76) -> 0 | P76: 0 | Q76: 0 | S76: =SUM(P76:R76) -> 0 | T76: 0 | V76: =SUM(T76:U76) -> 0 | W76: 0 | X76: 0 | Y76: =SUM(W76:X76) -> 0 | AE76: =SUM(H76,L76,Z76,AA76,AC76:AD76,O76,S76,V76,Y76,AB76) -> 0 | AH76: =ROUND(SUM(AE76:AG76),0) -> 0
B78: TOTAL CURRENT LIABILITIES | D78: =SUM(D57:D76) -> -243693105824 | E78: =SUM(E57:E76) -> 120480252913 | H78: =SUM(H57:H76) -> -1.3967132e+11 | I78: =SUM(I57:I76) -> -1.6175804e+11 | J78: =SUM(J57:J76) -> -933051862412 | L78: =SUM(L57:L76) -> -1.1128776e+12 | M78: =SUM(M57:M76) -> -41797635313 | O78: =SUM(O57:O76) -> -4.2666511e+10 | P78: =SUM(P57:P76) -> -50974479478 | Q78: =SUM(Q57:Q76) -> -149089067953 | S78: =SUM(S57:S76) -> -200063547431 | T78: =SUM(T57:T76) -> -293735296662 | V78: =SUM(V57:V76) -> -3.3837214e+11 | W78: =SUM(W57:W76) -> -1.4255007e+09 | Y78: =SUM(Y57:Y76) -> -1.6649007e+09 | AE78: =SUM(AE57:AE76) -> -1.835316e+12 | AH78: =SUM(AH57:AH76) -> -388047499446
D79: ^ | E79: ^ | I79: ^ | J79: ^ | M79: ^ | P79: ^ | Q79: ^ | T79: ^ | W79: ^ | AE79: ^
B80: NON CURRENT LIABILITIES
B81: Lease liabilities - net of current maturities | D81: 0 | E81: 0 | H81: =SUM(D81:F81) -> 0 | I81: -32226982313 | J81: 8670307543 | L81: =SUM(I81:K81) -> -23556674770 | M81: -11098027500 | O81: =SUM(M81:N81) -> -11098027500 | P81: 0 | Q81: 0 | S81: =SUM(P81:R81) -> 0 | T81: -19730382718 | V81: =SUM(T81:U81) -> -19730382718 | W81: 0 | Y81: =SUM(W81:X81) -> 0 | AE81: =SUM(H81,L81,Z81,AA81,AC81:AD81,O81,S81,V81,Y81,AB81) -> -54385084988 | AH81: =ROUND(SUM(AE81:AG81),0) -> -54385084988
B82: Consumer Financing Payables | D82: 0 | E82: 0 | H82: =SUM(D82:F82) -> 0 | I82: 0 | J82: 0 | L82: =SUM(I82:K82) -> 0 | O82: =SUM(M82:N82) -> 0 | P82: 0 | Q82: 0 | S82: =SUM(P82:R82) -> 0 | T82: 0 | V82: =SUM(T82:U82) -> 0 | W82: 0 | Y82: =SUM(W82:X82) -> 0 | AE82: =SUM(H82,L82,Z82,AA82,AC82:AD82,O82,S82,V82,Y82,AB82) -> 0 | AH82: =ROUND(SUM(AE82:AG82),0) -> 0
B83: Employee Benefit Liabilities | D83: -1.9231329e+09 | E83: 0 | H83: =SUM(D83:F83) -> -1.9231329e+09 | I83: -2930169433 | J83: 0 | L83: =SUM(I83:K83) -> -2930169433 | M83: 0 | O83: =SUM(M83:N83) -> 0 | P83: 0 | Q83: 0 | S83: =SUM(P83:R83) -> 0 | T83: 0 | V83: =SUM(T83:U83) -> 0 | W83: 0 | Y83: =SUM(W83:X83) -> 0 | AE83: =SUM(H83,L83,Z83,AA83,AC83:AD83,O83,S83,V83,Y83,AB83) -> -4.8533023e+09 | AH83: =ROUND(SUM(AE83:AG83),0) -> -4853302291
B84: Deferred Tax Liabilities | D84: 0 | E84: 0 | H84: =SUM(D84:F84) -> 0 | I84: -11841969436 | J84: 0 | L84: =SUM(I84:K84) -> -11841969436 | M84: 0 | O84: =SUM(M84:N84) -> 0 | P84: 0 | Q84: 0 | S84: =SUM(P84:R84) -> 0 | T84: 0 | V84: =SUM(T84:U84) -> 0 | W84: 0 | Y84: =SUM(W84:X84) -> 0 | AE84: =SUM(H84,L84,Z84,AA84,AC84:AD84,O84,S84,V84,Y84,AB84) -> -11841969436 | AH84: =ROUND(SUM(AE84:AG84),0) -> -11841969436
B85: Other non-current liabilities | D85: 0 | E85: 0 | H85: 0 | I85: -4735334275 | J85: 0 | L85: =SUM(I85:K85) -> -4735334275 | M85: 0 | O85: =SUM(M85:N85) -> 0 | P85: 0 | Q85: 0 | S85: =SUM(P85:R85) -> 0 | T85: 0 | V85: =SUM(T85:U85) -> 0 | W85: 0 | Y85: =SUM(W85:X85) -> 0 | AE85: =SUM(H85,L85,Z85,AA85,AC85:AD85,O85,S85,V85,Y85,AB85) -> -4735334275 | AH85: =ROUND(SUM(AE85:AG85),0) -> -4735334275
B87: TOTAL NON CURRENT LIABILITIES | D87: =SUM(D81:D85) -> -1.9231329e+09 | E87: =SUM(E81:E85) -> 0 | H87: =SUM(H81:H85) -> -1.9231329e+09 | I87: =SUM(I81:I85) -> -51734455457 | J87: =SUM(J81:J85) -> 8670307543 | L87: =SUM(L81:L85) -> -43064147914 | M87: =SUM(M81:M85) -> -11098027500 | O87: =SUM(O81:O85) -> -11098027500 | P87: =SUM(P81:P85) -> 0 | Q87: =SUM(Q81:Q85) -> 0 | S87: =SUM(S81:S85) -> 0 | T87: =SUM(T81:T85) -> -19730382718 | V87: =SUM(V81:V85) -> -19730382718 | W87: =SUM(W81:W85) -> 0 | Y87: =SUM(Y81:Y85) -> 0 | AE87: =SUM(AE81:AE85) -> -7.5815691e+10 | AH87: =SUM(AH81:AH85) -> -75815690990
D88: ^ | E88: ^ | H88: ^ | I88: ^ | J88: ^ | L88: ^ | M88: ^ | O88: ^ | P88: ^ | Q88: ^ | S88: ^ | T88: ^ | V88: ^ | W88: ^ | Y88: ^ | AE88: ^ | AH88: ^
B89: TOTAL LIABILITIES | D89: =D78+D87 -> -2.4561624e+11 | E89: =E78+E87 -> 120480252913 | H89: =H78+H87 -> -1.4159445e+11 | I89: =I78+I87 -> -2.1349249e+11 | J89: =J78+J87 -> -924381554869 | L89: =L78+L87 -> -1.1559418e+12 | M89: =M78+M87 -> -52895662813 | O89: =O78+O87 -> -5.3764538e+10 | P89: =P78+P87 -> -50974479478 | Q89: =Q78+Q87 -> -149089067953 | S89: =S78+S87 -> -200063547431 | T89: =T78+T87 -> -313465679380 | V89: =V78+V87 -> -3.5810253e+11 | W89: =W78+W87 -> -1.4255007e+09 | Y89: =Y78+Y87 -> -1.6649007e+09 | AE89: =AE78+AE87 -> -1.9111317e+12 | AH89: =AH78+AH87 -> -463863190436 | AJ89: =AH89-AI89 -> -463863190436
D90: ^ | E90: ^ | I90: ^ | J90: ^ | M90: ^ | P90: ^ | Q90: ^ | T90: ^ | W90: ^ | AE90: ^ | AH90: ^
B91: EQUITY
B92: Equity | AH92: =SUM(AE92:AG92) -> 0
B93: Shareholder Equity | D93: -142427250000 | E93: =-E94 -> -344280825000 | H93: =SUM(D93:G93) -> -486708075000 | I93: -1086047395650 | J93: 434382050025 | L93: =SUM(I93:K93) -> -651665345625 | M93: -23625000 | O93: =SUM(M93:N93) -> -23625000 | P93: -4921875000 | S93: =SUM(P93:R93) -> -4921875000 | T93: -472500000 | V93: =SUM(T93:U93) -> -472500000 | W93: -19687500 | X93: 0 | Y93: =SUM(W93:X93) -> -19687500 | AE93: =SUM(H93,L93,Z93,AA93,AC93:AD93,O93,S93,V93,Y93,AB93) -> -1143811108125 | AF93: =SUM('Elimination 2024'!G6,'Elimination 2024'!G30,'Elimination 2024'!G43,'Elimination 2024'!G56,'Elimination 2024'!G69) -> 657103033125 | AH93: =ROUND(SUM(AE93:AG93),0) -> -486708075000
B94: Advance Capital | D94: -1.952527e+12 | E94: 344280825000 | H94: =SUM(D94:G94) -> -1.6082462e+12 | I94: -4.5621984e+11 | J94: 4.5621984e+11 | L94: =SUM(I94:K94) -> 0 | M94: 0 | O94: =SUM(M94:N94) -> 0 | P94: -114090244632 | Q94: 114090244632 | S94: =SUM(P94:R94) -> 0 | T94: 0 | V94: =SUM(T94:U94) -> 0 | W94: -239400000 | X94: 239400000 | Y94: =SUM(W94:X94) -> 0 | AE94: =SUM(H94,L94,Z94,AA94,AC94:AD94,O94,S94,V94,Y94,AB94) -> -1.6082462e+12 | AH94: =ROUND(SUM(AE94:AG94),0) -> -1608246198282
B95: Additional Paid in Capital | P95: 0 | S95: =SUM(P95:R95) -> 0 | W95: 0 | Y95: =SUM(W95:X95) -> 0 | AE95: =ROUND(SUM(H95,L95,Z95,AA95,AC95:AD95,O95,S95,V95,Y95,AB95),0) -> 0 | AH95: =ROUND(SUM(AE95:AG95),0) -> 0
B96: SNTRESS | L96: =SUM(I96:K96) -> 0 | M96: 0 | O96: =SUM(M96:N96) -> 0 | S96: =SUM(P96:R96) -> 0 | T96: 0 | V96: =SUM(T96:U96) -> 0 | Y96: =SUM(W96:X96) -> 0 | AE96: =ROUND(SUM(H96,L96,Z96,AA96,AC96:AD96,O96,S96,V96,Y96,AB96),0) -> 0 | AG96: ='Elimination 2024'!G27+'Elimination 2024'!G40+'Elimination 2024'!H54+'Elimination 2024'!G66 -> 8.5320142e+10 | AH96: =ROUND(SUM(AE96:AG96),0)-552 -> 85320141313
B97: Share-based compensation reserve
B98: - Beginning Balance ESOP | D98: =SUM('Consol SoFP 23 & 22'!E97:E98) -> -4.238433e+10 | E98: 0 | F98: =-'Equity & Adjustment Consol'!G34 -> 0 | H98: =SUM(D98:G98) -> -4.238433e+10 | I98: =-7334537265*1.575 -> -1.1551896e+10 | L98: =SUM(I98:K98) -> -1.1551896e+10 | M98: 0 | O98: =SUM(M98:N98) -> 0 | P98: 0 | R98: 0 | S98: =SUM(P98:R98) -> 0 | T98: 0 | V98: =SUM(T98:U98) -> 0 | W98: 0 | X98: 0 | Y98: =SUM(W98:X98) -> 0 | Z98: 0 | AE98: =SUM(H98,L98,Z98,AA98,AC98:AD98,O98,S98,V98,Y98,AB98) -> -5.3936227e+10 | AF98: ='Elimination 2024'!G16 -> 1.1551896e+10 | AH98: =ROUND(SUM(AE98:AG98),0) -> -42384330497
B99: - Current year ESOP reserve | D99: 0 | E99: 0 | H99: =SUM(D99:G99) -> 0 | L99: =SUM(I99:K99) -> 0 | M99: 0 | O99: =SUM(M99:N99) -> 0 | P99: 0 | S99: =SUM(P99:R99) -> 0 | T99: 0 | V99: =SUM(T99:U99) -> 0 | W99: 0 | Y99: =SUM(W99:X99) -> 0 | AE99: =ROUND(SUM(H99,L99,Z99,AA99,AC99:AD99,O99,S99,V99,Y99,AB99),0) -> 0 | AH99: =ROUND(SUM(AE99:AG99),0) -> 0
B100: Retained earnings
B101: - Beginning retained earnings | D101: 6.3499233e+11 | E101: -4.1479304e+09 | F101: 0 | G101: ='Equity & Adjustment Consol'!C50 -> 0 | H101: =SUM(D101:G101) -> 6.308444e+11 | I101: 1.130547e+12 | J101: -1.5312641e+10 | L101: =SUM(I101:K101) -> 1.1152343e+12 | M101: -2684595157 | N101: =-Control!F32 -> 2.8944144e+08 | O101: =SUM(M101:N101) -> -2.3951537e+09 | P101: -1.1771504e+10 | Q101: 13466.25 | S101: =SUM(P101:R101) -> -1.1771491e+10 | T101: 98357763125 | V101: =SUM(T101:U101) -> 98357763125 | W101: 0 | X101: 0 | Y101: =SUM(W101:X101) -> 0 | Z101: 0 | AE101: =SUM(H101,L101,Z101,AA101,AC101:AD101,O101,S101,V101,Y101,AB101) -> 1.8302698e+12 | AF101: =SUM('Elimination 2024'!G125+'Elimination 2024'!G34,'Elimination 2024'!G47,'Elimination 2024'!G134) -> 3.3201975e+10 | AG101: ='Elimination 2024'!H13+'Elimination 2024'!H63 -> -1.2135921e+12 | AH101: =ROUND(SUM(AE101:AG101),0) -> 649879728739
B102: - Current profit or loss | D102: ='Consol SoPL-OCI 24'!E87 -> 220917807969 | E102: ='Consol SoPL-OCI 24'!F63 -> 11156573944 | F102: =ROUND(-'Equity & Adjustment Consol'!D34,0) -> 30613662987 | G102: ='Adjustment Consol'!J37 -> -1.1242698e+10 | H102: =SUM(D102:G102) -> 2.5144535e+11 | I102: ='Consol SoPL-OCI 24'!J87 -> 343810988410 | J102: ='Consol SoPL-OCI 24'!K52 -> -100072389485 | K102: =SUM('Adjustment Consol'!I51:I52,'Adjustment Consol'!J56:J57) -> -62074495 | L102: =SUM(I102:K102) -> 2.4367652e+11 | M102: ='Consol SoPL-OCI 24'!N87 -> 10891649906 | O102: =SUM(M102:N102) -> 10891649906 | P102: -2160990000 | Q102: ='Consol SoPL-OCI 24'!R87 -> 38259791827 | S102: =SUM(P102:R102) -> 36098801827 | T102: ='Consol SoPL-OCI 24'!U87 -> -1.958688e+10 | U102: ='BS RP Disclosure 2024'!J102 -> 2.8711286e+10 | V102: =SUM(T102:U102) -> 9.1244059e+09 | W102: ='Consol SoPL-OCI 24'!X87 -> -8.971568e+08 | Y102: =SUM(W102:X102) -> -8.971568e+08 | AE102: =SUM(H102,L102,Z102,AA102,AC102:AD102,O102,S102,V102,Y102,AB102) -> 5.5033957e+11 | AF102: ='Elimination 2024'!H64 -> -9.1244059e+09 | AG102: ='Elimination 2024'!H14+'Elimination 2024'!H38+'Elimination 2024'!G48+'Elimination 2024'!G137 -> -288862775198 | AH102: =ROUND(SUM(AE102:AG102),0) -> 252352390590
B103: OCI - Emben | H103: =SUM(D103:G103) -> 0 | L103: =SUM(I103:K103) -> 0 | S103: =SUM(P103:R103) -> 0 | V103: =SUM(T103:U103) -> 0 | Y103: =SUM(W103:X103) -> 0
B104: - Beginning - OCI Emben | D104: =SUM('Consol SoFP 23 & 22'!E104:E105) -> -1.5052833e+09 | F104: =-'Equity & Adjustment Consol'!E34 -> 0 | H104: =SUM(D104:G104) -> -1.5052833e+09 | I104: =SUM('Consol SoFP 23 & 22'!I104:I105) -> -2.5784654e+09 | J104: 0 | L104: =SUM(I104:K104) -> -2.5784654e+09 | M104: 0 | O104: =SUM(M104:N104) -> 0 | P104: 0 | R104: 0 | S104: =SUM(P104:R104) -> 0 | T104: 0 | V104: =SUM(T104:U104) -> 0 | W104: 0 | X104: 0 | Y104: =SUM(W104:X104) -> 0 | AE104: =SUM(H104,L104,Z104,AA104,AC104:AD104,O104,S104,V104,Y104,AB104) -> -4.0837487e+09 | AF104: ='Elimination 2024'!G21 -> 2.5784654e+09 | AH104: =ROUND(SUM(AE104:AG104),0) -> -1505283289
B105: - Current year - OCI Emben | D105: 0 | H105: =SUM(D105:G105) -> 0 | L105: =SUM(I105:K105) -> 0 | M105: 0 | O105: =SUM(M105:N105) -> 0 | P105: 0 | S105: =SUM(P105:R105) -> 0 | T105: ='Consol SoPL-OCI 24'!AG71 -> 0 | V105: =SUM(T105:U105) -> 0 | W105: 0 | Y105: =SUM(W105:X105) -> 0 | AE105: =SUM(H105,L105,Z105,AA105,AC105:AD105,O105,S105,V105,Y105,AB105) -> 0 | AH105: =ROUND(SUM(AE105:AG105),0) -> 0
B106: Capital Proforma | L106: =SUM(I106:K106) -> 0 | M106: 0 | O106: =SUM(M106:N106) -> 0 | P106: 0 | S106: =SUM(P106:R106) -> 0 | T106: 0 | V106: =SUM(T106:U106) -> 0 | W106: 0 | Y106: =SUM(W106:X106) -> 0 | Z106: =-Z40 -> -2.0937199e+09 | AA106: =-AA40 -> 5.7099484e+10 | AB106: =SUM('Proforma Adjustment'!D111,'Proforma Adjustment'!E116,'Proforma Adjustment'!D119,'Proforma Adjustment'!E124,'Proforma Adjustment'!E128,'Proforma Adjustment'!D131)+'Proforma Adjustment'!D135+'Proforma Adjustment'!E140 -> -5.5005765e+10 | AE106: 0 | AH106: =ROUND(SUM(AE106:AG106),0) -> 0
B109: Total equity attributable to the Owners of the Company | D109: =SUM(D92:D108) -> -1.2829338e+12 | E109: =SUM(E92:E108) -> 7.0086436e+09 | H109: =SUM(H92:H108) -> -1.2565541e+12 | I109: =SUM(I92:I108) -> -8.2039658e+10 | J109: =SUM(J92:J108) -> 7.7521686e+11 | L109: =SUM(L92:L108) -> 6.9311513e+11 | M109: =SUM(M92:M108) -> 8183429749 | N109: =SUM(N92:N108) -> 2.8944144e+08 | O109: =SUM(O92:O108) -> 8.4728712e+09 | P109: =SUM(P92:P108) -> -1.3294461e+11 | Q109: =SUM(Q92:Q108) -> 1.5235005e+11 | R109: =SUM(R92:R108) -> 0 | S109: =SUM(S92:S108) -> 1.9405436e+10 | ... AB109: =SUM(AB92:AB108) -> -5.5005765e+10 | AE109: =SUM(AE92:AE108) -> -4.2946788e+11 | AH109: =SUM(AH92:AH108) -> -1151291626426
B110: Non-controlling interest | H110: =SUM(D110:F110) -> 0 | I110: 0 | L110: =SUM(I110:K110) -> 0 | M110: 0 | O110: =SUM(M110:N110) -> 0 | P110: 0 | S110: =SUM(P110:R110) -> 0 | T110: -30852659 | V110: =SUM(T110:U110) -> -30852659 | W110: 0 | Y110: =SUM(W110:X110) -> 0 | AE110: =ROUND(SUM(H110,L110,Z110,AA110,AC110:AD110,O110,S110,V110,Y110,AB110),0) -> -30852659 | AF110: =SUM('Elimination 2024'!G11:G12,'Elimination 2024'!G35,'Elimination 2024'!H51,'Elimination 2024'!G60) -> 1.3852874e+12 | AG110: ='Elimination 2024'!H8+'Elimination 2024'!H19+'Elimination 2024'!H24+'Elimination 2024'!H32+'Elimination 2024'!H37+'Elimination 2024'!H45+'Elimination 2024'!H50+'Elimination 2024'!H58+'Elimination 2024'!G61 -> -6.4894997e+11 | AH110: =SUM(AE110:AG111) -> 7.3630658e+11
...

Sheet Consol SoPL-OCI 24
C3: PT Dummy - C and its Subsidiaries
C4: Matter:
C5: Statement of Profit or Loss and Other Comprehensive Income
I9: Dummy - C | M9: Dummy - D | P9: Dummy - E | T9: Dummy F | W9: Dummy - A | Z9: Dummy G
B11: Control | E11: =E87-'Consol SoFP 24'!D102 -> 0 | F11: =F87-'Consol SoFP 24'!E102 -> 0 | I11: =I87-'Consol SoFP 24'!H102 -> -0.08404541 | J11: =J87-'Consol SoFP 24'!I102 -> 0 | M11: =M87-'Consol SoFP 24'!L102 -> 0 | N11: =N87-'Consol SoFP 24'!M102 -> 0 | O11: =O87-'Consol SoFP 24'!N102 -> 0 | P11: =P87-'Consol SoFP 24'!O102 -> 0 | Q11: =Q87-'Consol SoFP 24'!P102 -> 0 | S11: =S87-'Consol SoFP 24'!R102 -> 0 | T11: =T87-'Consol SoFP 24'!S102 -> 0 | U11: =U87-'Consol SoFP 24'!T102 -> 0 | V11: =V87-'Consol SoFP 24'!U102 -> -2.8711286e+10 | W11: =W87-'Consol SoFP 24'!V102 -> 0 | X11: =X87-'Consol SoFP 24'!W102 -> 0 | Y11: =Y87-'Consol SoFP 24'!X102 -> 0 | Z11: =Z87-'Consol SoFP 24'!Y102 -> 0 | AD11: =AD87-'Consol SoFP 24'!AE102 -> -0.083984375 | AG11: =AG87-'Consol SoFP 24'!AH102 -> -0.12911987
B12: Description | E12: 45657 | F12: 45657 | G12: Adjustment Equity Method | H12: Adjustment at consol | I12: 45657 | J12: 45657 | K12: 45657 | L12: Adjustment at consol | M12: 45657 | N12: 45657 | O12: Adjustment at consol | P12: 45657 | Q12: 45657 | R12: 45657 | S12: Adjustment at consol | T12: 45657 | U12: 45657 | V12: Adjustment at consol | W12: 45657 | X12: 45657 | Y12: Adjustment at consol | Z12: 45657 | AA12: Proforma Adjustment | AB12: Adjustment/ Reclassification | AD12: Combined | AE12: Elimination Entries | AG12: Consolidated
E13: Statutory | F13: CLA | I13: Group - to Dummy - C | J13: Per Book | K13: CLA | M13: Group - to Dummy - C | N13: Statutory | P13: Group - to Dummy - C | Q13: Per Book | R13: CLA | T13: Group - to Dummy - C | U13: Statutory | W13: Group - to Dummy - C | X13: Statutory | Z13: Group - to Dummy - C | AA13: 45657 | AB13: Dr. | AC13: Cr. | AD13: 45657 | AE13: Dr. | AF13: Cr. | AG13: 45657
A16: 1 | B16: Revenue | E16: -21213830389 | F16: 3647176270 | I16: =SUM(E16:H16) -> -17566654119 | J16: -233826140611 | K16: 40085445837 | L16: =SUM('Adjustment Consol'!J56:J57) -> -2.204243e+09 | M16: =SUM(J16:L16) -> -1.9594494e+11 | N16: -20729834856 | P16: =SUM(N16:O16) -> -20729834856 | Q16: -65349876086 | R16: 41920113409 | T16: =SUM(Q16:S16) -> -23429762677 | U16: -529332761675 | W16: =SUM(U16:V16) -> -529332761675 | X16: -1.6412162e+09 | Z16: =SUM(X16:Y16) -> -1.6412162e+09 | AD16: =SUM(I16,M16,P16,T16,W16,Z16,AA16:AC16) -> -7.8864517e+11 | AG16: =SUM(AD16:AF16) -> -7.8864517e+11
A17: 2 | B17: Cost of Revenue | E17: 19476856647 | F17: -7607998269 | H17: ='Adjustment Consol'!J37 -> -1.1242698e+10 | I17: =SUM(E17:H17) -> 6.2615991e+08 | J17: 232231810474 | K17: -61079638391 | L17: =SUM('Adjustment Consol'!I51:I52) -> 2.1421685e+09 | M17: =SUM(J17:L17) -> 1.7329434e+11 | N17: 19901974828 | P17: =SUM(N17:O17) -> 19901974828 | Q17: 20024656898 | R17: -19145856191 | T17: =SUM(Q17:S17) -> 878800707 | U17: 502117212458 | W17: =SUM(U17:V17) -> 502117212458 | X17: 5.4164871e+08 | Z17: =SUM(X17:Y17) -> 5.4164871e+08 | AD17: =SUM(I17,M17,P17,T17,W17,Z17,AA17:AC17) -> 6.9736014e+11 | AG17: =SUM(AD17:AF17) -> 6.9736014e+11
B19: GROSS PROFIT | E19: =SUM(E15:E18) -> -1736973742 | F19: =SUM(F15:F18) -> -3960821999 | I19: =SUM(I15:I18) -> -1.6940494e+10 | J19: =SUM(J15:J18) -> -1594330137 | K19: =SUM(K15:K18) -> -20994192554 | M19: =SUM(M15:M18) -> -2.2650597e+10 | N19: =SUM(N15:N18) -> -827860028 | P19: =SUM(P15:P18) -> -827860028 | Q19: =SUM(Q15:Q18) -> -45325219188 | R19: =SUM(R15:R18) -> 22774257218 | T19: =SUM(T15:T18) -> -22550961970 | U19: =SUM(U15:U18) -> -27215549217 | W19: =SUM(W15:W18) -> -27215549217 | X19: =SUM(X15:X18) -> -1.0995675e+09 | Z19: =SUM(Z15:Z18) -> -1.0995675e+09 | AD19: =SUM(AD15:AD18) -> -9.128503e+10 | AG19: =SUM(AG15:AG18) -> -9.128503e+10
B21: OPERATING EXPENSES
A22: 3 | B22: Commission and Incentives | E22: 0 | F22: 0 | I22: =SUM(E22:H22) -> 0 | J22: 0 | K22: 0 | M22: =SUM(J22:L22) -> 0 | N22: 0 | P22: =SUM(N22:O22) -> 0 | Q22: 0 | R22: 0 | T22: =SUM(Q22:S22) -> 0 | U22: 0 | W22: =SUM(U22:V22) -> 0 | X22: 0 | Z22: =SUM(X22:Y22) -> 0 | AD22: =SUM(I22,M22,P22,T22,W22,Z22,AA22:AC22) -> 0 | AG22: =SUM(AD22:AF22) -> 0
B23: Sales and Marketing Expenses | E23: 7504545005 | F23: -667188005 | I23: =SUM(E23:H23) -> 6837357000 | J23: 217966206 | K23: 0 | M23: =SUM(J23:L23) -> 217966206 | N23: 56260948 | P23: =SUM(N23:O23) -> 56260948 | Q23: 0 | R23: 0 | T23: =SUM(Q23:S23) -> 0 | U23: 0 | W23: =SUM(U23:V23) -> 0 | X23: 1.5104635e+08 | Z23: =SUM(X23:Y23) -> 1.5104635e+08 | AD23: =SUM(I23,M23,P23,T23,W23,Z23,AA23:AC23) -> 7.2626305e+09 | AG23: =SUM(AD23:AF23) -> 7.2626305e+09
A24: 4 | B24: General and Administrasi Expenses | E24: 191625306573 | F24: -7844815470 | I24: =SUM(E24:H24) -> 183780491103 | J24: 300131791767 | K24: -47484836738 | M24: =SUM(J24:L24) -> 252646955029 | N24: 11959012417 | O24: 0 | P24: =SUM(N24:O24) -> 11959012417 | Q24: 41276450194 | R24: 33375954404 | T24: =SUM(Q24:S24) -> 74652404598 | U24: 8328766765 | V24: ='Consol SoFP 24'!U102 -> 2.8711286e+10 | W24: =SUM(U24:V24) -> 3.7040052e+10 | X24: 47010491 | Z24: =SUM(X24:Y24) -> 47010491 | AD24: =SUM(I24,M24,P24,T24,W24,Z24,AA24:AC24) -> 5.6012593e+11 | AG24: =SUM(AD24:AF24) -> 5.6012593e+11
B25: Depreciation and Amortization | E25: 6612687009 | F25: 4384597463 | I25: =SUM(E25:H25) -> 10997284472 | J25: 21874009299 | K25: -8793416902 | M25: =SUM(J25:L25) -> 13080592397 | N25: 64132685 | P25: =SUM(N25:O25) -> 64132685 | Q25: 6835992 | R25: 0 | T25: =SUM(Q25:S25) -> 6835992 | U25: 0 | W25: =SUM(U25:V25) -> 0 | X25: 6352499.5 | Z25: =SUM(X25:Y25) -> 6352499.5 | AD25: =SUM(I25,M25,P25,T25,W25,Z25,AA25:AC25) -> 2.4155198e+10 | AG25: =SUM(AD25:AF25) -> 2.4155198e+10
B26: Loss (Gain) on revaluation and impairment financial assets | E26: 3805101352 | F26: 4348455686 | I26: =SUM(E26:H26) -> 8153557038 | J26: 3335347373 | K26: -222699102 | M26: =SUM(J26:L26) -> 3112648271 | N26: 0 | P26: =SUM(N26:O26) -> 0 | Q26: 0 | R26: 0 | T26: =SUM(Q26:S26) -> 0 | U26: 0 | V26: 0 | W26: =SUM(U26:V26) -> 0 | X26: 0 | Z26: =SUM(X26:Y26) -> 0 | AD26: =SUM(I26,M26,P26,T26,W26,Z26,AA26:AC26) -> 11266205309 | AG26: =SUM(AD26:AF26) -> 11266205309
B27: Impairment loss on property and equipment | E27: 0 | F27: 0 | I27: =SUM(E27:H27) -> 0 | J27: 0 | K27: 0 | M27: =SUM(J27:L27) -> 0 | N27: 0 | P27: =SUM(N27:O27) -> 0 | Q27: 0 | R27: 0 | T27: =SUM(Q27:S27) -> 0 | U27: 0 | W27: =SUM(U27:V27) -> 0 | X27: 0 | Z27: =SUM(X27:Y27) -> 0 | AD27: =SUM(I27,M27,P27,T27,W27,Z27,AA27:AC27) -> 0 | AG27: =SUM(AD27:AF27) -> 0
B28: Others, net | E28: 8401068927 | F28: 16123353665 | I28: =SUM(E28:H28) -> 24524422592 | J28: 12816435653 | K28: -30392363503 | M28: =SUM(J28:L28) -> -17575927850 | N28: 0 | P28: =SUM(N28:O28) -> 0 | Q28: -20963326 | R28: -17909439780 | T28: =SUM(Q28:S28) -> -17930403106 | U28: -8.3039769e+08 | W28: =SUM(U28:V28) -> -8.3039769e+08 | X28: -2371316.9 | Z28: =SUM(X28:Y28) -> -2371316.9 | AD28: =SUM(I28,M28,P28,T28,W28,Z28,AA28:AC28) -> -1.1814677e+10 | AG28: =SUM(AD28:AF28) -> -1.1814677e+10
B30: TOTAL OPERATING EXPENSES | E30: =SUM(E21:E29) -> 217948708866 | F30: =SUM(F21:F29) -> 16344403339 | I30: =SUM(I21:I29) -> 234293112205 | J30: =SUM(J21:J29) -> 338375550298 | K30: =SUM(K21:K29) -> -86893316245 | M30: =SUM(M21:M29) -> 251482234053 | N30: =SUM(N21:N29) -> 12079406050 | P30: =SUM(P21:P29) -> 12079406050 | Q30: =SUM(Q21:Q29) -> 41262322860 | R30: =SUM(R21:R29) -> 15466514624 | T30: =SUM(T21:T29) -> 56728837484 | U30: =SUM(U21:U29) -> 7.4983691e+09 | W30: =SUM(W21:W29) -> 3.6209655e+10 | X30: =SUM(X21:X29) -> 2.0203803e+08 | Z30: =SUM(Z21:Z29) -> 2.0203803e+08 | AD30: =SUM(AD21:AD29) -> 5.9099528e+11 | AG30: =SUM(AG21:AG29) -> 5.9099528e+11
E31: ^ | F31: ^ | I31: ^ | J31: ^ | K31: ^ | M31: ^ | N31: ^ | P31: ^ | Q31: ^ | R31: ^ | T31: ^ | U31: ^ | W31: ^ | X31: ^ | Z31: ^ | AD31: ^ | AG31: ^
B32: OPERATING INCOME | E32: =E19+E30 -> 216211735124 | F32: =F19+F30 -> 12383581340 | I32: =I19+I30 -> 2.1735262e+11 | J32: =J19+J30 -> 336781220161 | K32: =K19+K30 -> -107887508799 | M32: =M19+M30 -> 2.2883164e+11 | N32: =N19+N30 -> 11251546022 | P32: =P19+P30 -> 11251546022 | Q32: =Q19+Q30 -> -4062896328 | R32: =R19+R30 -> 38240771842 | T32: =T19+T30 -> 34177875514 | U32: =U19+U30 -> -1.971718e+10 | W32: =W19+W30 -> 8.9941055e+09 | X32: =X19+X30 -> -8.9752945e+08 | Z32: =Z19+Z30 -> -8.9752945e+08 | AD32: =AD19+AD30 -> 4.9971025e+11 | AG32: =AG19+AG30 -> 4.9971025e+11
E33: ^ | F33: ^ | I33: ^ | J33: ^ | K33: ^ | M33: ^ | N33: ^ | P33: ^ | Q33: ^ | R33: ^ | T33: ^ | U33: ^ | W33: ^ | X33: ^ | Z33: ^ | AD33: ^ | AG33: ^
B34: OTHER EXPENSE (INCOME)
A35: 8 | B35: Finance Income | E35: -242497274 | F35: 0 | I35: =SUM(E35:H35) -> -242497274 | J35: -7224479274 | K35: -844706627 | M35: =SUM(J35:L35) -> -8069185901 | N35: -545359940 | P35: =SUM(N35:O35) -> -545359940 | Q35: 0 | R35: 0 | T35: =SUM(Q35:S35) -> 0 | U35: -9.7270427e+08 | W35: =SUM(U35:V35) -> -9.7270427e+08 | X35: -7120.575 | Z35: =SUM(X35:Y35) -> -7120.575 | AD35: =SUM(I35,M35,P35,T35,W35,Z35,AA35:AC35) -> -9.8297545e+09 | AE35: ='Elimination 2024'!G137 -> 1.804201e+09 | AG35: =SUM(AD35:AF35) -> -8.0255535e+09
A36: 9 | B36: Finance Expense | E36: 313556544 | F36: 0 | I36: =SUM(E36:H36) -> 313556544 | J36: 2626687977 | K36: 8969049644 | M36: =SUM(J36:L36) -> 11595737621 | N36: 92697083 | P36: =SUM(N36:O36) -> 92697083 | Q36: 0 | R36: 0 | T36: =SUM(Q36:S36) -> 0 | U36: 8.0116343e+08 | W36: =SUM(U36:V36) -> 8.0116343e+08 | X36: 0 | Z36: =SUM(X36:Y36) -> 0 | AD36: =SUM(I36,M36,P36,T36,W36,Z36,AA36:AC36) -> 1.2803155e+10 | AG36: =SUM(AD36:AF36) -> 1.2803155e+10
A37: 10 | B37: Gain (Loss) Forex | E37: 391539132 | F37: 888379418 | I37: =SUM(E37:H37) -> 1279918550 | J37: -306219514 | K37: -34633911 | M37: =SUM(J37:L37) -> -340853425 | N37: 0 | P37: =SUM(N37:O37) -> 0 | Q37: 0 | R37: 0 | T37: =SUM(Q37:S37) -> 0 | U37: 0 | W37: =SUM(U37:V37) -> 0 | X37: 0 | Z37: =SUM(X37:Y37) -> 0 | AD37: =SUM(I37,M37,P37,T37,W37,Z37,AA37:AC37) -> 939065125 | AG37: =SUM(AD37:AF37) -> 939065125
A38: 11 | B38: Tax Expenses | E38: 4243474443 | F38: -2115386814 | I38: =SUM(E38:H38) -> 2128087629 | J38: 11933779060 | K38: -274589792 | M38: =SUM(J38:L38) -> 11659189268 | N38: 92766741 | P38: =SUM(N38:O38) -> 92766741 | Q38: 1901906328 | R38: 19019985 | T38: =SUM(Q38:S38) -> 1920926313 | U38: 268343807 | W38: =SUM(U38:V38) -> 268343807 | X38: 379765.58 | Z38: =SUM(X38:Y38) -> 379765.58 | AD38: =SUM(I38,M38,P38,T38,W38,Z38,AA38:AC38) -> 1.6069694e+10 | AG38: =SUM(AD38:AF38) -> 1.6069694e+10
A39: 12 | B39: Unrecognised Bank - Payable | E39: 0 | F39: 0 | I39: =SUM(E39:H39) -> 0 | J39: 0 | K39: 0 | M39: =SUM(J39:L39) -> 0 | N39: 0 | P39: =SUM(N39:O39) -> 0 | Q39: 0 | R39: 0 | T39: =SUM(Q39:S39) -> 0 | U39: 0 | W39: =SUM(U39:V39) -> 0 | X39: 0 | Z39: =SUM(X39:Y39) -> 0 | AD39: =SUM(I39,M39,P39,T39,W39,Z39,AA39:AC39) -> 0 | AG39: =SUM(AD39:AF39) -> 0
E41: =SUM(E34:E40) -> 4706072845 | F41: =SUM(F34:F40) -> -1227007396 | I41: =SUM(I34:I40) -> 3479065449 | J41: =SUM(J34:J40) -> 7029768249 | K41: =SUM(K34:K40) -> 7815119314 | M41: =SUM(M34:M40) -> 14844887563 | N41: =SUM(N34:N40) -> -359896116 | P41: =SUM(P34:P40) -> -359896116 | Q41: =SUM(Q34:Q40) -> 1901906328 | R41: =SUM(R34:R40) -> 19019985 | T41: =SUM(T34:T40) -> 1920926313 | U41: =SUM(U34:U40) -> 96802975 | W41: =SUM(W34:W40) -> 96802975 | X41: =SUM(X34:X40) -> 372645 | Z41: =SUM(Z34:Z40) -> 372645 | AD41: =SUM(AD34:AD40) -> 1.9982159e+10 | AG41: =SUM(AG34:AG40) -> 2.178636e+10
E42: ^ | F42: ^ | I42: ^ | J42: ^ | K42: ^ | M42: ^ | N42: ^ | P42: ^ | Q42: ^ | R42: ^ | T42: ^ | U42: ^ | W42: ^ | X42: ^ | Z42: ^ | AD42: ^ | AG42: ^
B43: (INCOME) LOSS FROM SUBSIDIARIES
B44: Dividend income | E44: 0 | F44: 0 | I44: =SUM(E44:H44) -> 0 | J44: 0 | AD44: =SUM(I44,M44,P44,T44,W44,Z44,AA44:AC44) -> 0 | AG44: =SUM(AD44:AF44) -> 0
B45: Equity loss (income) in Dummy - D | E45: 0 | F45: 0 | G45: =-'Equity & Adjustment Consol'!D29 -> 5.1306523e+09 | I45: =SUM(E45:H45) -> 5.1306523e+09 | J45: 0 | AA45: ='Proforma Adjustment'!D111 -> 2.910673e+09 | AD45: =SUM(I45,M45,P45,T45,W45,Z45,AA45:AC45) -> 8.0413253e+09 | AF45: =-AD45 -> -8.0413253e+09 | AG45: =SUM(AD45:AF45) -> 0
B46: Equity loss (income) in Dummy - E | E46: 0 | F46: 0 | G46: =-'Equity & Adjustment Consol'!D30 -> 3.9719066e+09 | I46: =SUM(E46:H46) -> 3.9719066e+09 | J46: 0 | AA46: ='Proforma Adjustment'!D119 -> 1.5828349e+09 | AD46: =SUM(I46,M46,P46,T46,W46,Z46,AA46:AC46) -> 5.5547415e+09 | AF46: =-AD46 -> -5.5547415e+09 | AG46: =SUM(AD46:AF46) -> 0
B47: Equity loss (income) in Dummy F | E47: 0 | F47: 0 | G47: =-'Equity & Adjustment Consol'!D31 -> 9.0770283e+09 | I47: =SUM(E47:H47) -> 9.0770283e+09 | J47: 0 | AA47: ='Proforma Adjustment'!E128 -> 9.3333607e+09 | AD47: =SUM(I47,M47,P47,T47,W47,Z47,AA47:AC47) -> 1.8410389e+10 | AF47: =-AD47 -> -1.8410389e+10 | AG47: =SUM(AD47:AF47) -> 0
B48: Equity loss (income) in Dummy - A Consol | E48: 0 | F48: 0 | G48: =-'Equity & Adjustment Consol'!D32 -> 1.2434076e+10 | I48: =SUM(E48:H48) -> 1.2434076e+10 | J48: 0 | AA48: ='Proforma Adjustment'!D135 -> -7.7806288e+09 | AD48: =SUM(I48,M48,P48,T48,W48,Z48,AA48:AC48) -> 4.653447e+09 | AF48: =-AD48 -> -4.653447e+09 | AG48: =SUM(AD48:AF48) -> 0
B49: Equity loss (income) in Dummy G | E49: 0 | F49: 0 | I49: =SUM(E49:H49) -> 0 | J49: 0 | AG49: =SUM(AD49:AF49) -> 0
B50: TOTAL (INCOME) LOSS FROM SUBSIDIARIES | E50: =SUM(E43:E49) -> 0 | F50: =SUM(F43:F49) -> 0 | G50: =G30+G39+G48 -> 1.2434076e+10 | I50: =SUM(I43:I49) -> 3.0613663e+10 | J50: =SUM(J43:J49) -> 0 | K50: =SUM(K43:K49) -> 0 | M50: =SUM(M43:M49) -> 0 | N50: =SUM(N43:N49) -> 0 | P50: =SUM(P43:P49) -> 0 | Q50: =SUM(Q43:Q49) -> 0 | R50: =SUM(R43:R49) -> 0 | T50: =SUM(T43:T49) -> 0 | U50: =SUM(U43:U49) -> 0 | W50: =SUM(W43:W49) -> 0 | X50: =SUM(X43:X49) -> 0 | Z50: =SUM(Z43:Z49) -> 0 | AA50: =SUM(AA43:AA49) -> 6.0462397e+09 | AD50: =SUM(AD43:AD49) -> 3.6659903e+10 | AG50: =SUM(AG43:AG49) -> 0
E51: ^ | F51: ^ | I51: ^ | J51: ^ | K51: ^ | M51: ^ | N51: ^ | P51: ^ | Q51: ^ | R51: ^ | T51: ^ | U51: ^ | W51: ^ | X51: ^ | Z51: ^ | AD51: ^ | AG51: ^
B52: (INCOME) LOSS BEFORE INCOME TAX | E52: =E32+E41+E50 -> 220917807969 | F52: =F32+F41+F50 -> 11156573944 | I52: =I32+I41+I50 -> 2.5144535e+11 | J52: =J32+J41+J50 -> 343810988410 | K52: =K32+K41+K50 -> -100072389485 | M52: =M32+M41+M50 -> 2.4367652e+11 | N52: =N32+N41+N50 -> 10891649906 | P52: =P32+P41+P50 -> 10891649906 | Q52: =Q32+Q41+Q50 -> -2160990000 | R52: =R32+R41+R50 -> 38259791827 | T52: =T32+T41+T50 -> 36098801827 | U52: =U32+U41+U50 -> -1.9620377e+10 | W52: =W32+W41+W50 -> 9.0909085e+09 | X52: =X32+X41+X50 -> -8.971568e+08 | Z52: =Z32+Z41+Z50 -> -8.971568e+08 | AA52: =AA32+AA41+AA50 -> 6.0462397e+09 | AD52: =AD32+AD41+AD50 -> 5.5635231e+11 | AG52: =AG32+AG41+AG50 -> 5.2149661e+11
E53: ^ | F53: ^ | I53: ^ | J53: ^ | K53: ^ | M53: ^ | N53: ^ | P53: ^ | Q53: ^ | R53: ^ | T53: ^ | U53: ^ | W53: ^ | X53: ^ | Z53: ^ | AD53: ^ | AG53: ^
B54: INCOME TAX EXPENSE
A55: 14 | B55: Current Tax | I55: =SUM(E55:G55) -> 0 | J55: 0 | M55: =SUM(J55:L55) -> 0 | N55: 0 | P55: =SUM(N55:O55) -> 0 | Q55: 0 | T55: =SUM(Q55:S55) -> 0 | W55: =SUM(U55:V55) -> 0 | Z55: =SUM(X55:Y55) -> 0 | AD55: =SUM(I55,M55,P55,T55,W55,Z55,AA55:AC55) -> 0 | AG55: =SUM(AD55:AF55) -> 0
A56: 15 | B56: Deferred Tax | I56: 0 | J56: 0 | L56: 0 | M56: =SUM(J56:L56) -> 0 | N56: 0 | O56: 0 | P56: =SUM(N56:O56) -> 0 | S56: 0 | T56: =SUM(Q56:S56) -> 0 | V56: 0 | W56: =SUM(U56:V56) -> 0 | Y56: 0 | Z56: =SUM(X56:Y56) -> 0 | AB56: 0 | AD56: =SUM(I56,M56,P56,T56,W56,Z56,AA56:AC56) -> 0 | AG56: =SUM(AD56:AF56) -> 0
B57: Income tax expense - net | E57: =SUM(E55:E56) -> 0 | I57: =SUM(I55:I56) -> 0 | J57: =SUM(J55:J56) -> 0 | M57: =SUM(M55:M56) -> 0 | N57: =SUM(N55:N56) -> 0 | P57: =SUM(P55:P56) -> 0 | Q57: =SUM(Q55:Q56) -> 0 | T57: =SUM(T55:T56) -> 0 | U57: =SUM(U55:U56) -> 0 | W57: =SUM(W55:W56) -> 0 | X57: =SUM(X55:X56) -> 0 | Z57: =SUM(Z55:Z56) -> 0 | AD57: =SUM(AD55:AD56) -> 0 | AG57: =SUM(AG55:AG56) -> 0
B59: NET (INCOME) LOSS FOR THE YEAR BEFORE EFFECT OF PROFORMA ADJUSTMENT | E59: =E52+E57 -> 220917807969 | F59: =F52+F57 -> 11156573944 | I59: =I52+I57 -> 2.5144535e+11 | J59: =J52+J57 -> 343810988410 | K59: =K52+K57 -> -100072389485 | M59: =M52+M57 -> 2.4367652e+11 | N59: =N52+N57 -> 10891649906 | P59: =P52+P57 -> 10891649906 | Q59: =Q52+Q57 -> -2160990000 | R59: =R52+R57 -> 38259791827 | T59: =T52+T57 -> 36098801827 | U59: =U52+U57 -> -1.9620377e+10 | W59: =W52+W57 -> 9.0909085e+09 | X59: =X52+X57 -> -8.971568e+08 | Z59: =Z52+Z57 -> -8.971568e+08 | AA59: =AA52+AA57 -> 6.0462397e+09 | AD59: =AD52+AD57 -> 5.5635231e+11 | AG59: =AG52+AG57 -> 5.2149661e+11
B61: Effect of proforma adjustment on net income for the year | J61: 0 | M61: =SUM(J61:L61) -> 0 | N61: 0 | P61: =SUM(N61:O61) -> 0 | Q61: 0 | T61: =SUM(Q61:S61) -> 0 | U61: 0 | W61: =SUM(U61:V61) -> 0 | X61: 0 | Z61: =SUM(X61:Y61) -> 0 | AA61: =-AA50 -> -6.0462397e+09 | AD61: =SUM(I61,M61,P61,T61,W61,Z61,AA61:AC61) -> -6.0462397e+09 | AG61: =SUM(AD61:AF61) -> -6.0462397e+09
B63: NET (INCOME) LOSS FOR THE YEAR | E63: =SUM(E59:E62) -> 220917807969 | F63: =SUM(F59:F62) -> 11156573944 | I63: =SUM(I59:I62) -> 2.5144535e+11 | J63: =SUM(J59:J62) -> 343810988410 | K63: =SUM(K59:K62) -> -100072389485 | M63: =SUM(M59:M62) -> 2.4367652e+11 | N63: =SUM(N59:N62) -> 10891649906 | P63: =SUM(P59:P62) -> 10891649906 | Q63: =SUM(Q59:Q62) -> -2160990000 | R63: =SUM(R59:R62) -> 38259791827 | T63: =SUM(T59:T62) -> 36098801827 | U63: =SUM(U59:U62) -> -1.9620377e+10 | W63: =SUM(W59:W62) -> 9.0909085e+09 | X63: =SUM(X59:X62) -> -8.971568e+08 | Z63: =SUM(Z59:Z62) -> -8.971568e+08 | AA63: =SUM(AA59:AA62) -> 0 | AD63: =SUM(AD59:AD62) -> 5.5030607e+11 | AG63: =SUM(AG59:AG62) -> 5.1545037e+11
B65: OTHER COMPREHENSIVE INCOME (LOSS)
B66: Item that will not be reclassified to profit or loss in subsequent period
A67: 16 | B67: Remeasurement of employee benefits liabiltiies | E67: 0 | I67: =SUM(E67:G67) -> 0 | M67: =SUM(J67:L67) -> 0 | P67: =SUM(N67:O67) -> 0 | Q67: 0 | U67: 0 | X67: 0 | Z67: 0 | AD67: =SUM(I67,M67,P67,T67,W67,Z67,AA67:AC67) -> 0 | AE67: =-M67 -> 0 | AG67: =SUM(AD67:AF67) -> 0
A68: 17 | B68: Related income tax | E68: 0 | I68: =SUM(E68:G68) -> 0 | M68: =SUM(J68:L68) -> 0 | P68: =SUM(N68:O68) -> 0 | Q68: 0 | U68: 0 | X68: 0 | Z68: 0 | AD68: =SUM(I68,M68,P68,T68,W68,Z68,AA68:AC68) -> 0 | AE68: =-M68 -> 0 | AG68: =SUM(AD68:AF68) -> 0
B70: Item that will be reclassified to profit or loss in subsequent period
B71: Differences in translation of financial statements in foregin currencies | I71: =SUM(E71:G71) -> 0 | L71: 0 | M71: =SUM(J71:L71) -> 0 | O71: 0 | P71: =SUM(N71:O71) -> 0 | T71: =SUM(Q71:S71) -> 0 | W71: =SUM(U71:V71) -> 0 | Z71: =SUM(X71:Y71) -> 0 | AD71: =SUM(I71,M71,P71,T71,W71,Z71,AA71:AC71) -> 0 | AG71: =SUM(AD71:AF71) -> 0
B73: Other Comperhensive Income - Emben | AD73: =SUM(I73,M73,P73,T73,W73,Z73,AA73:AC73) -> 0 | AG73: =SUM(AD73:AF73) -> 0
B74: - OCI Dummy - D | AD74: =SUM(I74,M74,P74,T74,W74,Z74,AA74:AC74) -> 0 | AG74: =SUM(AD74:AF74) -> 0
B75: - OCI Dummy F | AD75: =SUM(I75,M75,P75,T75,W75,Z75,AA75:AC75) -> 0 | AG75: =SUM(AD75:AF75) -> 0
B77: Other comprehensive loss - Net of tax | E77: =SUM(E67:E76) -> 0 | I77: =SUM(I67:I76) -> 0 | J77: =SUM(J67:J76) -> 0 | M77: =SUM(M67:M76) -> 0 | N77: =SUM(N67:N76) -> 0 | P77: =SUM(P67:P76) -> 0 | Q77: =SUM(Q67:Q76) -> 0 | T77: =SUM(T67:T76) -> 0 | U77: =SUM(U67:U76) -> 0 | W77: =SUM(W67:W76) -> 0 | X77: =SUM(X67:X76) -> 0 | Z77: =SUM(Z67:Z76) -> 0 | AA77: =SUM(AA67:AA76) -> 0 | AD77: =SUM(AD67:AD76) -> 0 | AG77: =SUM(AG67:AG76) -> 0
B79: TOTAL COMPREHENSIVE INCOME FOR THE YEAR BEFORE EFFECT OF PROFORMA ADJUSTMENT | E79: =E63+E77 -> 220917807969 | F79: =F63+F77 -> 11156573944 | I79: =I63+I77 -> 2.5144535e+11 | J79: =J63+J77 -> 343810988410 | K79: =K63+K77 -> -100072389485 | M79: =M63+M77 -> 2.4367652e+11 | N79: =N63+N77 -> 10891649906 | P79: =P63+P77 -> 10891649906 | Q79: =Q63+Q77 -> -2160990000 | R79: =R63+R77 -> 38259791827 | T79: =T63+T77 -> 36098801827 | U79: =U63+U77 -> -1.9620377e+10 | W79: =W63+W77 -> 9.0909085e+09 | X79: =X63+X77 -> -8.971568e+08 | Z79: =Z63+Z77 -> -8.971568e+08 | AA79: =AA63+AA77 -> 0 | AB79: =SUM(AB15:AB78) -> 0 | AC79: =SUM(AC15:AC78) -> 0 | AD79: =AD63+AD77 -> 5.5030607e+11 | AG79: =AG63+AG77 -> 5.1545037e+11
B81: Effect of proforma adjustment on Comperhensive Income for the year | J81: 0 | M81: 0 | N81: 0 | P81: 0 | Q81: 0 | T81: 0 | U81: 0 | W81: 0 | X81: 0 | Z81: 0 | AA81: =-AA74 -> 0 | AD81: =SUM(I81,M81,P81,T81,W81,Z81,AA81:AC81) -> 0 | AG81: =SUM(AD81:AF81) -> 0
B83: TOTAL COMPREHENSIVE INCOME FOR THE YEAR | E83: =SUM(E78:E82) -> 220917807969 | F83: =SUM(F78:F82) -> 11156573944 | I83: =SUM(I78:I82) -> 2.5144535e+11 | J83: =SUM(J78:J82) -> 343810988410 | K83: =SUM(K78:K82) -> -100072389485 | M83: =SUM(M78:M82) -> 2.4367652e+11 | N83: =SUM(N78:N82) -> 10891649906 | P83: =SUM(P78:P82) -> 10891649906 | Q83: =SUM(Q78:Q82) -> -2160990000 | R83: =SUM(R78:R82) -> 38259791827 | T83: =SUM(T78:T82) -> 36098801827 | U83: =SUM(U78:U82) -> -1.9620377e+10 | W83: =SUM(W78:W82) -> 9.0909085e+09 | X83: =SUM(X78:X82) -> -8.971568e+08 | Z83: =SUM(Z78:Z82) -> -8.971568e+08 | AA83: =SUM(AA78:AA82) -> 0 | AD83: =SUM(AD78:AD82) -> 5.5030607e+11 | AG83: =SUM(AG78:AG82) -> 5.1545037e+11
E84: ^ | F84: ^ | J84: ^ | K84: ^ | N84: ^ | Q84: ^ | R84: ^ | U84: ^ | X84: ^
B86: Net income for the year attributable to:
B87: Owners of the Company | E87: =E63-E88 -> 220917807969 | F87: =F63-F88 -> 11156573944 | I87: =I63-I88 -> 2.5144535e+11 | J87: =J63-J88 -> 343810988410 | K87: =K63-K88 -> -100072389485 | M87: =M90-M88 -> 2.4367652e+11 | N87: =N63-N88 -> 10891649906 | P87: =P63-P88 -> 10891649906 | Q87: =Q63-Q88 -> -2160990000 | R87: =R63-R88 -> 38259791827 | T87: =SUM(Q87:S87) -> 36098801827 | U87: =U63-U88 -> -1.958688e+10 | W87: =W90-W88 -> 9.1244059e+09 | X87: =X63-X88 -> -8.971568e+08 | Z87: =SUM(X87:Y87) -> -8.971568e+08 | AD87: =SUM(I87,M87,P87,T87,W87,Z87,AA87:AC87) -> 5.5033957e+11 | AG87: =AG63-AG88 -> 2.5235239e+11
B88: Non-controlling interest | I88: =SUM(E88:G88) -> 0 | J88: 0 | M88: =SUM(J88:L88) -> 0 | N88: 0 | P88: 0 | Q88: 0 | T88: =SUM(Q88:S88) -> 0 | U88: -33497476 | W88: =SUM(U88:V88) -> -33497476 | X88: 0 | Z88: =SUM(X88:Y88) -> 0 | AD88: =SUM(I88,M88,P88,T88,W88,Z88,AA88:AC88) -> -33497476 | AE88: ='Elimination 2024'!G12+'Elimination 2024'!G35+'Elimination 2024'!H51 -> 2.5866052e+11 | AF88: ='Elimination 2024'!G61 -> 4.4709589e+09 | AG88: =SUM(AD88,AE88,AF88) -> 2.6309798e+11
B90: NET INCOME FOR THE YEAR | E90: =SUM(E86:E88) -> 220917807969 | F90: =SUM(F86:F88) -> 11156573944 | I90: =SUM(I86:I88) -> 2.5144535e+11 | J90: =SUM(J86:J88) -> 343810988410 | K90: =SUM(K86:K88) -> -100072389485 | M90: =M83 -> 2.4367652e+11 | N90: =SUM(N86:N88) -> 10891649906 | P90: =SUM(P86:P88) -> 10891649906 | Q90: =SUM(Q86:Q88) -> -2160990000 | R90: =SUM(R86:R88) -> 38259791827 | T90: =SUM(T86:T88) -> 36098801827 | U90: =SUM(U86:U88) -> -1.9620377e+10 | W90: =W83 -> 9.0909085e+09 | X90: =SUM(X86:X88) -> -8.971568e+08 | Z90: =SUM(Z86:Z88) -> -8.971568e+08 | AD90: =AD63 -> 5.5030607e+11 | AG90: =AG63 -> 5.1545037e+11
AG91: =AG90-AG63 -> 0
B93: Total comprehensive income for the year attributable to:
B94: Owners of the Company | E94: =E79-E97 -> 220917807969 | F94: =F79-F97 -> 11156573944 | I94: =I79-I97 -> 2.5144535e+11 | J94: =J98-J95 -> 343810988410 | K94: =K98-K95 -> -100072389485 | M94: =M79-M97-M95-M96 -> 2.4367652e+11 | N94: =N98-N95 -> 10891649906 | P94: =P79-P97-P95-P96 -> 10891649906 | Q94: =Q98-Q95 -> -2160990000 | R94: =R98-R95 -> 38259791827 | T94: =T98-T95 -> 36098801827 | U94: =U98-U95 -> -1.958688e+10 | W94: =W98-W95 -> 9.1244059e+09 | X94: =X98-X95 -> -8.971568e+08 | Z94: =Z98-Z95 -> -8.971568e+08 | AD94: =SUM(I94,M94,P94,T94,W94,Z94,AA94:AC94) -> 5.5033957e+11 | AG94: =AG98-AG95 -> 2.5682335e+11
B95: Non-controlling interest - PL | J95: 0 | M95: =SUM(J95:L95) -> 0 | N95: 0 | P95: =SUM(N95:O95) -> 0 | Q95: =Q88 -> 0 | T95: =T88 -> 0 | U95: =U88 -> -33497476 | W95: =W88 -> -33497476 | X95: =X88 -> 0 | Z95: =Z88 -> 0 | AD95: =AD88 -> -33497476 | AE95: =AE88 -> 2.5866052e+11 | AG95: =SUM(AD95,AE95,AF95) -> 2.5862702e+11
B96: Non-controlling interest - OCI Emp Ben | AD96: =SUM(I96,M96,P96,T96,W96,Z96,AA96:AC96) -> 0 | AG96: =SUM(AD96,AE96,AF96) -> 0
B97: Non-controlling interest - OCI Translation | I97: =SUM(E97:G97) -> 0 | M97: =SUM(J97:L97) -> 0 | P97: =SUM(N97:O97) -> 0 | T97: =SUM(Q97:S97) -> 0 | W97: =SUM(U97:V97) -> 0 | Z97: =SUM(X97:Y97) -> 0 | AD97: =SUM(I97,M97,P97,T97,W97,Z97,AA97:AC97) -> 0 | AG97: =SUM(AD97:AF97) -> 0
B98: TOTAL COMPREHENSIVE INCOME FOR THE YEAR | E98: =SUM(E93:E97) -> 220917807969 | F98: =SUM(F93:F97) -> 11156573944 | I98: =SUM(I93:I97) -> 2.5144535e+11 | J98: =J83 -> 343810988410 | K98: =K83 -> -100072389485 | M98: =M83 -> 2.4367652e+11 | N98: =N83 -> 10891649906 | P98: =P83 -> 10891649906 | Q98: =Q90 -> -2160990000 | R98: =R90 -> 38259791827 | T98: =T90 -> 36098801827 | U98: =U90 -> -1.9620377e+10 | W98: =W90 -> 9.0909085e+09 | X98: =X90 -> -8.971568e+08 | Z98: =Z90 -> -8.971568e+08 | AD98: =AD83 -> 5.5030607e+11 | AG98: =AG79 -> 5.1545037e+11
E99: =E98-E79 -> 0 | Q99: =Q98-Q79 -> 0 | U99: =U98-U79 -> 0 | X99: =X98-X79 -> 0 | AG99: =AG98-AG79 -> 0

Sheet Consol SoFP 23 & 22
C3: PT Dummy C and its Subsidiaries
C4: Matter:
C5: Consolidated Statement of Financial Position | AE5: in Indonesian Rupiah
K7: oke | N7: oke | AM7: Agreed to Report Released
H8: Dummy - C | K8: Dummy - D | N8: Dummy - E | Q8: Dummy F | T8: Dummy - A | W8: Dummy G | AJ8: Dummy C | AM8: Dummy D | AP8: Dummy E | AS8: Dummy F | AV8: Dummy A Consol | AY8: Dummy G
B9: Control to A=LE+E | E9: =E114+E54 -> -0.17480469 | H9: =H114+H54 -> -0.17480469 | I9: =I114+I54 -> -0.0077514648 | K9: =K114+K54 -> -0.0077514648 | L9: =L114+L54 -> -0.57500076 | M9: =M114+M54 -> 0 | N9: =N114+N54 -> -0.57500076 | O9: =O114+O54 -> 1.2750015 | P9: =P114+P54 -> 0 | Q9: =Q114+Q54 -> 1.2750015 | R9: =R114+R54 -> 1.3288574 | ... W9: =W114+W54 -> 0 | Z9: =SUM(Z12:Z114) -> 0 | AA9: =SUM(AA12:AA114) -> 0 | AB9: =AB114+AB54 -> 1.8464355 | AC9: =SUM(AC12:AC114) -> 2.8216446e+12 | AD9: =SUM(AD12:AD114) -> -2.8216446e+12 | AE9: =AE114+AE54 -> -0.31237793 | AG9: =AG114+AG54 -> -0.27490234 | AJ9: =AJ114+AJ54 -> -0.27490234 | AK9: =AK114+AK54 -> -0.10974121 | AM9: =AM114+AM54 -> -0.10974121 | AN9: =AN114+AN54 -> 0 | AP9: =AP114+AP54 -> 0 | AQ9: =AQ114+AQ54 -> -0.47500038 | AS9: =AS114+AS54 -> -0.47500038 | AT9: =AT114+AT54 -> 0 | AV9: =AV114+AV54 -> 0 | AW9: =AW114+AW54 -> 0 | AY9: =AY114+AY54 -> 0 | BA9: =SUM(BA12:BA114) -> 0 | BB9: =SUM(BB12:BB114) -> 0 | BC9: =BC114+BC54 -> 0 | BD9: =SUM(BD12:BD114) -> 1.3853971e+12 | BE9: =SUM(BE12:BE114) -> -1.3853971e+12 | BF9: =BF114+BF54 -> 0
B10: Description | E10: Dummy - C | F10: Adjustment Equity Method | G10: Adjustment at consol | H10: Dummy - C | I10: Dummy - D | J10: Adjustment at consol | K10: Dummy - D | L10: Dummy - E | M10: Adjustment at consol | N10: Dummy - E | O10: Dummy F | P10: Adjustment at consol | Q10: Dummy F | R10: Dummy - A | S10: Adjustment at consol | T10: Dummy - A | U10: Dummy G | V10: Adjustment at consol | W10: Dummy G | X10: Proforma Adjustment | Z10: Adjustment/ Reclassification | AB10: Combined | AC10: Elimination Entries | AE10: Consolidated | AG10: Dummy C | AH10: Adjustment Equity Method | AI10: Adjustment at consol | AJ10: Dummy C | AK10: Dummy D | AL10: Adjustment at consol | AM10: Dummy D | AN10: Dummy E | AO10: Adjustment at consol | AP10: Dummy E | AQ10: Dummy F | AR10: Adjustment at consol | AS10: Dummy F | AT10: Dummy A Consol | AU10: Adjustment at consol | AV10: Dummy A Consol | AW10: Dummy G | AX10: Adjustment at consol | AY10: Dummy G | AZ10: Proforma Adjustment | BA10: Adjustment/ Reclassification | BC10: Combined | BD10: Elimination Entries | BF10: Consolidated
E11: 45291 | H11: 45291 | I11: 45291 | K11: 45291 | L11: 45291 | N11: 45291 | O11: 45291 | Q11: 45291 | R11: 45291 | T11: 45291 | U11: 45291 | W11: 45291 | X11: 44926 | Y11: 45291 | Z11: Dr. | AA11: Cr. | AB11: 45291 | AC11: Dr. | AD11: Cr. | AE11: 45291 | AG11: 44926 | AJ11: 44926 | AK11: 44926 | AM11: 44926 | AN11: 44926 | AP11: 44926 | AQ11: 44926 | AS11: 44926 | AT11: 44926 | AV11: 44926 | AW11: 44926 | AY11: 44926 | AZ11: 44926 | BA11: Dr. | BB11: Cr. | BC11: 44926 | BD11: Dr. | BE11: Cr. | BF11: 44926
B13: ASSET
B14: CURRENT ASSET
B15: Cash and cash equivalents | E15: 41026163646 | H15: 41026163646 | I15: 14609918281 | K15: 14609918281 | L15: 8815278530 | N15: 8815278530 | O15: 745329690 | Q15: 745329690 | R15: 9912795948 | T15: 9912795948 | U15: 0 | W15: 0 | AB15: =SUM(H15,K15,X15,Y15,Z15:AA15,N15,Q15,T15,W15) -> 75109486095 | AE15: =ROUND(SUM(AB15:AD15),0) -> 75109486095 | AG15: 25526565333 | AJ15: 25526565333 | AK15: 9450630157 | AM15: 9450630157 | AN15: 2.3245849e+08 | AP15: 2.3245849e+08 | AQ15: 36209184 | AS15: 36209184 | AT15: 5.4153952e+09 | AV15: 5.4153952e+09 | AW15: 0 | AY15: 0 | BC15: =ROUND(SUM(AJ15,AM15,AP15,AS15,AV15,AY15,AZ15),0) -> 40661258337 | BF15: =ROUND(SUM(BC15:BE15),0) -> 40661258337 | BH15: ok
B16: Trade receivables | AT16: 0
B17: Trade Receivables - Third Parties | E17: 22570871222 | H17: 22570871222 | I17: 81172049227 | K17: 81172049227 | L17: 4378731777 | N17: 4378731777 | O17: 52187509409 | Q17: 52187509409 | R17: 112397037300 | T17: 112397037300 | U17: 0 | W17: 0 | AB17: =SUM(H17,K17,X17,Y17,Z17:AA17,N17,Q17,T17,W17) -> 272706198935 | AE17: =ROUND(SUM(AB17:AD17),0) -> 272706198935 | AG17: 67255836494 | AJ17: 67255836494 | AK17: 66788139360 | AM17: 66788139360 | AN17: 1.1208523e+09 | AP17: 1.1208523e+09 | AQ17: 13466 | AS17: 13466 | AT17: 43413315906 | AV17: 43413315906 | AW17: 0 | AY17: 0 | BC17: =ROUND(SUM(AJ17,AM17,AP17,AS17,AV17,AY17,AZ17),0) -> 178578157565 | BF17: =ROUND(SUM(BC17:BE17),0) -> 178578157565 | BH17: ok
B18: Trade Receivables - Related Parties | E18: 30542833417 | H18: 30542833417 | I18: 3513008908 | K18: 3513008908 | L18: 0 | N18: 0 | O18: 0 | Q18: 0 | R18: 18820641340 | T18: 18820641340 | U18: 0 | W18: 0 | AB18: =SUM(H18,K18,X18,Y18,Z18:AA18,N18,Q18,T18,W18) -> 52876483665 | AD18: ='Elimination 23'!H72+'Elimination 23'!H64 -> -3.5141395e+09 | AE18: =ROUND(SUM(AB18:AD18),0) -> 49362344144 | AG18: 30542833417 | AJ18: 30542833417 | AK18: 0 | AM18: 0 | AN18: 0 | AP18: 0 | AQ18: 0 | AS18: 0 | AT18: 18819510726 | AV18: 18819510726 | AW18: 0 | AY18: 0 | BC18: =ROUND(SUM(AJ18,AM18,AP18,AS18,AV18,AY18,AZ18),0) -> 49362344143 | BF18: =ROUND(SUM(BC18:BE18),0) -> 49362344143 | BH18: ok
B19: Unbilled Receivable
B20: Unbilled - Third Parties | E20: 0 | H20: 0 | I20: 0 | K20: 0 | L20: 0 | N20: 0 | O20: 1191821441 | Q20: 1191821441 | R20: 0 | T20: 0 | U20: 0 | W20: 0 | AB20: =SUM(H20,K20,X20,Y20,Z20:AA20,N20,Q20,T20,W20) -> 1191821441 | AE20: =ROUND(SUM(AB20:AD20),0) -> 1191821441 | AG20: 0 | AJ20: 0 | AK20: 0 | AM20: 0 | AN20: 0 | AP20: 0 | AQ20: 0 | AS20: 0 | AT20: 0 | AV20: 0 | AW20: 0 | AY20: 0 | BC20: =ROUND(SUM(AJ20,AM20,AP20,AS20,AV20,AY20,AZ20),0) -> 0 | BF20: =ROUND(SUM(BC20:BE20),0) -> 0
B21: Unbilled - Related Parties | E21: 0 | H21: 0 | I21: 0 | K21: 0 | L21: 0 | N21: 0 | O21: 0 | Q21: 0 | R21: 0 | T21: 0 | U21: 0 | W21: 0 | AB21: =SUM(H21,K21,X21,Y21,Z21:AA21,N21,Q21,T21,W21) -> 0 | AE21: =ROUND(SUM(AB21:AD21),0) -> 0 | AG21: 0 | AJ21: 0 | AK21: 0 | AM21: 0 | AN21: 0 | AP21: 0 | AQ21: 0 | AS21: 0 | AT21: 0 | AV21: 0 | AW21: 0 | AY21: 0 | BC21: =ROUND(SUM(AJ21,AM21,AP21,AS21,AV21,AY21,AZ21),0) -> 0 | BF21: =ROUND(SUM(BC21:BE21),0) -> 0
B22: Current portion of Lease receivables | E22: 0 | H22: 0 | I22: 15830303102 | K22: 15830303102 | L22: 0 | N22: 0 | O22: 0 | Q22: 0 | R22: 0 | T22: 0 | U22: 0 | W22: 0 | AB22: =SUM(H22,K22,X22,Y22,Z22:AA22,N22,Q22,T22,W22) -> 15830303102 | AE22: =ROUND(SUM(AB22:AD22),0) -> 15830303102 | AG22: 0 | AJ22: 0 | AK22: 14442442151 | AM22: 14442442151 | AN22: 0 | AP22: 0 | AQ22: 0 | AS22: 0 | AT22: 0 | AV22: 0 | AW22: 0 | AY22: 0 | BC22: =ROUND(SUM(AJ22,AM22,AP22,AS22,AV22,AY22,AZ22),0) -> 14442442151 | BF22: =ROUND(SUM(BC22:BE22),0) -> 14442442151 | BH22: ok
B23: Employee Receivables | E23: 0 | H23: 0 | I23: 0 | K23: 0 | L23: 0 | N23: 0 | O23: 0 | Q23: 0 | R23: 0 | T23: 0 | U23: 0 | W23: 0 | AB23: =SUM(H23,K23,X23,Y23,Z23:AA23,N23,Q23,T23,W23) -> 0 | AE23: =ROUND(SUM(AB23:AD23),0) -> 0 | AG23: 0 | AJ23: 0 | AK23: 0 | AM23: 0 | AN23: 0 | AP23: 0 | AQ23: 0 | AS23: 0 | AT23: 0 | AV23: 0 | AW23: 0 | AY23: 0 | BC23: =ROUND(SUM(AJ23,AM23,AP23,AS23,AV23,AY23,AZ23),0) -> 0 | BF23: =ROUND(SUM(BC23:BE23),0) -> 0 | BH23: ok
B24: Loan Receivable
B25: Loan Receivable - Third Parties | E25: 0 | H25: 0 | I25: 0 | K25: 0 | L25: 0 | N25: 0 | O25: 0 | Q25: 0 | R25: 0 | T25: 0 | U25: 0 | W25: 0 | Z25: 0 | AB25: =SUM(H25,K25,X25,Y25,Z25:AA25,N25,Q25,T25,W25) -> 0 | AE25: =ROUND(SUM(AB25:AD25),0) -> 0 | AG25: 0 | AJ25: 0 | AK25: 0 | AM25: 0 | AN25: 0 | AP25: 0 | AQ25: 0 | AS25: 0 | AT25: 0 | AV25: 0 | AW25: 0 | AY25: 0 | BA25: 0 | BC25: =ROUND(SUM(AJ25,AM25,AP25,AS25,AV25,AY25,AZ25),0) -> 0 | BF25: =ROUND(SUM(BC25:BE25),0) -> 0
B26: Loan Receivable - Related Parties | E26: 803982133222 | G26: 0 | H26: 803982133222 | I26: 47074007016 | K26: 47074007016 | L26: 0 | N26: 0 | O26: 0 | Q26: 0 | R26: 0 | T26: 0 | U26: 0 | W26: 0 | AB26: =SUM(H26,K26,X26,Y26,Z26:AA26,N26,Q26,T26,W26) -> 851056140238 | AC26: ='Elimination 23'!G109 -> 0 | AD26: =SUM('Elimination 23'!H62:H63)+'Elimination 23'!H73+'Elimination 23'!H75+'Elimination 23'!H84+'Elimination 23'!H85 -> -8.3072973e+11 | AE26: =ROUND(SUM(AB26:AD26),0) -> 20326406410 | AG26: 5.182371e+09 | AJ26: 5.182371e+09 | AK26: 4553935708 | AM26: 4553935708 | AN26: 0 | AP26: 0 | AQ26: 14058094952 | AS26: 14058094952 | AT26: 0 | AV26: 0 | AW26: 0 | AY26: 0 | BC26: =ROUND(SUM(AJ26,AM26,AP26,AS26,AV26,AY26,AZ26),0) -> 23794401695 | BD26: ='Elimination 22'!G83 -> 8.7289589e+09 | BE26: =SUM('Elimination 22'!H65,'Elimination 22'!H67)+SUM('Elimination 22'!H73,'Elimination 22'!H76)+SUM('Elimination 22'!H80:H81) -> -2.7342565e+10 | BF26: =ROUND(SUM(BC26:BE26),0) -> 5180796035 | BH26: ok
B27: Other Receivables | L27: 0 | R27: 0
B28: Other Receivables - Third Parties | E28: 3195366722 | H28: 3195366722 | I28: 1683922612 | K28: 1683922612 | L28: 0 | N28: 0 | O28: 0 | Q28: 0 | R28: 0 | T28: 0 | U28: 0 | W28: 0 | AB28: =SUM(H28,K28,X28,Y28,Z28:AA28,N28,Q28,T28,W28) -> 4879289334 | AE28: =ROUND(SUM(AB28:AD28),0) -> 4879289334 | AG28: 529736825 | AJ28: 529736825 | AK28: 494847861 | AM28: 494847861 | AN28: 0 | AP28: 0 | AQ28: 0 | AS28: 0 | AT28: 4410000000 | AV28: 4410000000 | AW28: 0 | AY28: 0 | BC28: =ROUND(SUM(AJ28,AM28,AP28,AS28,AV28,AY28,AZ28),0) -> 5434584686 | BF28: =ROUND(SUM(BC28:BE28),0) -> 5434584686 | BH28: ok
B29: Other Receivable - Related Parties | E29: 58448443601 | H29: 58448443601 | I29: 63036055189 | J29: 0 | K29: 63036055189 | L29: 0 | N29: 0 | O29: 0 | Q29: 0 | R29: 0 | T29: 0 | U29: 0 | W29: 0 | AB29: =SUM(H29,K29,X29,Y29,Z29:AA29,N29,Q29,T29,W29) -> 121484498790 | AD29: =SUM('Elimination 23'!H65:H66)+'Elimination 23'!H74+'Elimination 23'!H83+'Elimination 23'!H89+SUM('Elimination 23'!H99:H101)+'Elimination 23'!H98+'Elimination 23'!H82+'Elimination 23'!H104 -> -8.8007186e+10 | AE29: =ROUND(SUM(AB29:AD29),0) -> 33477312809 | AG29: 18267984779 | AJ29: 18267984779 | AK29: 0 | AM29: 0 | AN29: 0 | AP29: 0 | AQ29: 0 | AS29: 0 | AT29: 0 | AV29: 0 | AW29: 0 | AY29: 0 | BC29: =ROUND(SUM(AJ29,AM29,AP29,AS29,AV29,AY29,AZ29),0) -> 18267984779 | BE29: ='Elimination 22'!H66+'Elimination 22'!H75 -> -1.8267985e+10 | BF29: =ROUND(SUM(BC29:BE29),0) -> 0
B30: Inventories | E30: 0 | H30: 0 | I30: 0 | K30: 0 | L30: 0 | N30: 0 | O30: 0 | Q30: 0 | R30: 0 | T30: 0 | U30: 0 | W30: 0 | AB30: =SUM(H30,K30,X30,Y30,Z30:AA30,N30,Q30,T30,W30) -> 0 | AE30: =ROUND(SUM(AB30:AD30),0) -> 0 | AG30: 0 | AJ30: 0 | AK30: 0 | AM30: 0 | AN30: 0 | AP30: 0 | AQ30: 0 | AS30: 0 | AT30: 0 | AV30: 0 | AW30: 0 | AY30: 0 | BC30: =ROUND(SUM(AJ30,AM30,AP30,AS30,AV30,AY30,AZ30),0) -> 0 | BF30: =ROUND(SUM(BC30:BE30),0) -> 0
B31: Prepaid Tax | E31: 0 | H31: 0 | I31: 2424148440 | K31: 2424148440 | L31: 2598751 | N31: 2598751 | O31: 0 | Q31: 0 | R31: 197229685 | T31: 197229685 | U31: 0 | W31: 0 | AB31: =SUM(H31,K31,X31,Y31,Z31:AA31,N31,Q31,T31,W31) -> 2623976876 | AE31: =ROUND(SUM(AB31:AD31),0) -> 2623976876 | AG31: 0 | AJ31: 0 | AK31: 0 | AM31: 0 | AN31: 0 | AP31: 0 | AQ31: 0 | AS31: 0 | AT31: 90969692 | AV31: 90969692 | AW31: 0 | AY31: 0 | BC31: =ROUND(SUM(AJ31,AM31,AP31,AS31,AV31,AY31,AZ31),0) -> 90969692 | BF31: =ROUND(SUM(BC31:BE31),0) -> 90969692 | BH31: ok
B32: Prepayment and Advances | E32: 0 | H32: 0 | I32: 11323351672 | K32: 11323351672 | L32: 10598227 | N32: 10598227 | O32: 199170563 | Q32: 199170563 | R32: 278608508 | T32: 278608508 | U32: 0 | W32: 0 | AB32: =SUM(H32,K32,X32,Y32,Z32:AA32,N32,Q32,T32,W32) -> 11811728970 | AE32: =ROUND(SUM(AB32:AD32),0) -> 11811728970 | AG32: 0 | AJ32: 0 | AK32: 25727138954 | AM32: 25727138954 | AN32: 0 | AP32: 0 | AQ32: 3189375 | AS32: 3189375 | AT32: 20701691630 | AV32: 20701691630 | AW32: 0 | AY32: 0 | BC32: =ROUND(SUM(AJ32,AM32,AP32,AS32,AV32,AY32,AZ32),0) -> 46432019959 | BF32: =ROUND(SUM(BC32:BE32),0) -> 46432019959 | BH32: ok
B33: Deposits | E33: 0 | H33: 0 | I33: 0 | K33: 0 | L33: 0 | N33: 0 | O33: 0 | Q33: 0 | R33: 0 | T33: 0 | U33: 0 | W33: 0 | AB33: =SUM(H33,K33,X33,Y33,Z33:AA33,N33,Q33,T33,W33) -> 0 | AE33: =ROUND(SUM(AB33:AD33),0) -> 0 | AG33: 0 | AJ33: 0 | AK33: 0 | AM33: 0 | AN33: 0 | AP33: 0 | AQ33: 0 | AS33: 0 | AT33: 0 | AV33: 0 | AW33: 0 | AY33: 0 | BC33: =ROUND(SUM(AJ33,AM33,AP33,AS33,AV33,AY33,AZ33),0) -> 0 | BF33: =ROUND(SUM(BC33:BE33),0) -> 0
B34: Restricted Cash and Time Deposits | E34: 23625000000 | H34: 23625000000 | I34: 111931554091 | K34: 111931554091 | L34: 0 | N34: 0 | O34: 0 | Q34: 0 | R34: 24032039498 | T34: 24032039498 | U34: 0 | W34: 0 | AB34: =SUM(H34,K34,X34,Y34,Z34:AA34,N34,Q34,T34,W34) -> 159588593589 | AE34: =ROUND(SUM(AB34:AD34),0) -> 159588593589 | AG34: 0 | AJ34: 0 | AK34: 31729071673 | AM34: 31729071673 | AN34: 0 | AP34: 0 | AQ34: 0 | AS34: 0 | AT34: 23625000000 | AV34: 23625000000 | AW34: 0 | AY34: 0 | BC34: =ROUND(SUM(AJ34,AM34,AP34,AS34,AV34,AY34,AZ34),0) -> 55354071673 | BF34: =ROUND(SUM(BC34:BE34),0) -> 55354071673 | BH34: ok
B35: Other Current Assets | E35: 3.4613286e+09 | H35: 3.4613286e+09 | I35: 20551888106 | K35: 20551888106 | L35: 0 | N35: 0 | O35: 0 | Q35: 0 | R35: 0 | T35: 0 | U35: 0 | W35: 0 | AB35: =SUM(H35,K35,X35,Y35,Z35:AA35,N35,Q35,T35,W35) -> 2.4013217e+10 | AE35: =ROUND(SUM(AB35:AD35),0) -> 24013216750 | AG35: 2.7641384e+09 | AJ35: 2.7641384e+09 | AK35: 9673383745 | AM35: 9673383745 | AN35: 0 | AP35: 0 | AQ35: 0 | AS35: 0 | AT35: 196875000 | AV35: 196875000 | AW35: 0 | AY35: 0 | BC35: =ROUND(SUM(AJ35,AM35,AP35,AS35,AV35,AY35,AZ35),0) -> 12634397153 | BF35: =ROUND(SUM(BC35:BE35),0) -> 12634397153 | BH35: ok
B37: TOTAL CURRENT ASSETS | E37: =SUM(E14:E36) -> 9.8685214e+11 | H37: =SUM(H14:H36) -> 9.8685214e+11 | I37: =SUM(I14:I36) -> 373150206644 | K37: =SUM(K14:K36) -> 373150206644 | L37: =SUM(L14:L36) -> 13207207285 | N37: =SUM(N14:N36) -> 13207207285 | O37: =SUM(O14:O36) -> 54323831103 | Q37: =SUM(Q14:Q36) -> 54323831103 | R37: =SUM(R14:R36) -> 165638352279 | T37: =SUM(T14:T36) -> 165638352279 | U37: =SUM(U14:U36) -> 0 | W37: =SUM(W14:W36) -> 0 | AB37: =SUM(AB14:AB36) -> 1.5931717e+12 | AE37: =SUM(AE14:AE36) -> 670920678455 | AG37: =SUM(AG14:AG36) -> 1.5006947e+11 | AJ37: =SUM(AJ14:AJ36) -> 1.5006947e+11 | AK37: =SUM(AK14:AK36) -> 162859589609 | AM37: =SUM(AM14:AM36) -> 162859589609 | AN37: =SUM(AN14:AN36) -> 1.3533108e+09 | AP37: =SUM(AP14:AP36) -> 1.3533108e+09 | AQ37: =SUM(AQ14:AQ36) -> 14097506977 | AS37: =SUM(AS14:AS36) -> 14097506977 | AT37: =SUM(AT14:AT36) -> 1.1667276e+11 | AV37: =SUM(AV14:AV36) -> 1.1667276e+11 | AW37: =SUM(AW14:AW36) -> 0 | AY37: =SUM(AY14:AY36) -> 0 | BC37: =SUM(BC14:BC36) -> 445052631833 | BF37: =SUM(BF14:BF36) -> 408171041394
E38: ^ | I38: ^ | L38: ^ | O38: ^ | R38: ^ | U38: ^ | AB38: ^ | AG38: ^ | AK38: ^ | AN38: ^ | AQ38: ^ | AT38: ^ | AW38: ^ | BC38: ^
B39: Investments | AE39: =SUM(AB39:AD39) -> 0
B40: Investment in Subsidiaries | E40: 0 | H40: 0 | I40: 0 | K40: 0 | L40: 0 | N40: 0 | O40: 0 | Q40: 0 | R40: 0 | T40: 0 | U40: 0 | W40: 0 | X40: 2.0937199e+09 | Y40: -5.7099484e+10 | AB40: =SUM(H40,K40,X40,Y40,Z40:AA40,N40,Q40,T40,W40) -> -5.5005765e+10 | AC40: ='Elimination 23'!G11+'Elimination 23'!G54 -> 8.6965191e+10 | AD40: ='Elimination 23'!H7+'Elimination 23'!H19+'Elimination 23'!H24+'Elimination 23'!H29+'Elimination 23'!H34+'Elimination 23'!H39+'Elimination 23'!H44+'Elimination 23'!H49 -> -3.1959427e+10 | AE40: =ROUND(SUM(AB40:AD40),0)+1 -> 0 | AG40: 0 | AI40: 0 | AJ40: 0 | AK40: 0 | AM40: 0 | AN40: 0 | AP40: 0 | AQ40: 0 | AS40: 0 | AT40: 0 | AV40: 0 | AW40: 0 | AY40: 0 | AZ40: ='Proforma Adjustment'!O15 -> 2.0937199e+09 | BC40: =ROUND(SUM(AJ40,AM40,AP40,AS40,AV40,AY40,AZ40),0) -> 2093719896 | BD40: ='Elimination 22'!G15+'Elimination 22'!G34 -> 1.7041328e+10 | BE40: ='Elimination 22'!H8+'Elimination 22'!H23+'Elimination 22'!H31+'Elimination 22'!H39+'Elimination 22'!H43+'Elimination 22'!H48+'Elimination 22'!H27+'Elimination 22'!H53+'Elimination 22'!H58 -> -1.9135048e+10 | BF40: =ROUND(SUM(BC40:BE40),0)-1 -> 0
B41: Deemed Investment | E41: 0 | H41: 0 | I41: 0 | K41: 0 | L41: 0 | N41: 0 | O41: 0 | Q41: 0 | R41: 0 | T41: 0 | U41: 0 | W41: 0 | AB41: =SUM(H41,K41,X41,Y41,Z41:AA41,N41,Q41,T41,W41) -> 0 | AE41: =SUM(AB41:AD41) -> 0 | AG41: 0 | AJ41: 0 | AK41: 0 | AM41: 0 | AN41: 0 | AP41: 0 | AQ41: 0 | AS41: 0 | AT41: 0 | AV41: 0 | AW41: 0 | AY41: 0 | BC41: =ROUND(SUM(AJ41,AM41,AP41,AS41,AV41,AY41,AZ41),0) -> 0 | BF41: =ROUND(SUM(BC41:BE41),0) -> 0
B42: Lease Receivables - Non Current | E42: 0 | H42: 0 | I42: 2156177190 | K42: 2156177190 | L42: 0 | N42: 0 | O42: 0 | Q42: 0 | R42: 0 | T42: 0 | U42: 0 | W42: 0 | AB42: =SUM(H42,K42,X42,Y42,Z42:AA42,N42,Q42,T42,W42) -> 2156177190 | AE42: =ROUND(SUM(AB42:AD42),0) -> 2156177190 | AG42: 0 | AJ42: 0 | AK42: 14398163289 | AM42: 14398163289 | AN42: 0 | AP42: 0 | AQ42: 0 | AS42: 0 | AT42: 0 | AV42: 0 | AW42: 0 | AY42: 0 | BC42: =ROUND(SUM(AJ42,AM42,AP42,AS42,AV42,AY42,AZ42),0) -> 14398163289 | BF42: =ROUND(SUM(BC42:BE42),0) -> 14398163289
B43: Loan Receivable - Related Parties - non-current | E43: 0 | H43: 0 | I43: 0 | K43: 0 | L43: 0 | N43: 0 | O43: 0 | Q43: 0 | R43: 0 | T43: 0 | U43: 0 | W43: 0 | AB43: =SUM(H43,K43,X43,Y43,Z43:AA43,N43,Q43,T43,W43) -> 0 | AE43: =ROUND(SUM(AB43:AD43),0) -> 0 | AG43: 1.3039411e+11 | AJ43: 1.3039411e+11 | AK43: 0 | AM43: 0 | AN43: 0 | AP43: 0 | AQ43: 0 | AS43: 0 | AT43: 0 | AV43: 0 | AW43: 0 | AY43: 0 | BC43: =ROUND(SUM(AJ43,AM43,AP43,AS43,AV43,AY43,AZ43),0) -> 130394112646 | BE43: ='Elimination 22'!H74 -> -1.3039411e+11 | BF43: =ROUND(SUM(BC43:BE43),0)+1 -> 0
B44: Fixed Assets | E44: 278653421 | H44: 278653421 | I44: 21360897428 | K44: 21360897428 | L44: 181298250 | N44: 181298250 | O44: 0 | Q44: 0 | R44: 11861883 | T44: 11861883 | U44: 0 | W44: 0 | AB44: =SUM(H44,K44,X44,Y44,Z44:AA44,N44,Q44,T44,W44) -> 21832710982 | AE44: =ROUND(SUM(AB44:AD44),0) -> 21832710982 | AG44: 277523469 | AJ44: 277523469 | AK44: 35363492591 | AM44: 35363492591 | AN44: 0 | AP44: 0 | AQ44: 0 | AS44: 0 | AT44: 23017214 | AV44: 23017214 | AW44: 0 | AY44: 0 | BC44: =ROUND(SUM(AJ44,AM44,AP44,AS44,AV44,AY44,AZ44),0) -> 35664033274 | BF44: =ROUND(SUM(BC44:BE44),0) -> 35664033274
B45: Intangible Assets | E45: 13132539190 | H45: 13132539190 | I45: 11753548874 | K45: 11753548874 | L45: 0 | N45: 0 | O45: 0 | Q45: 0 | R45: 0 | T45: 0 | U45: 0 | W45: 0 | AB45: =SUM(H45,K45,X45,Y45,Z45:AA45,N45,Q45,T45,W45) -> 24886088064 | AE45: =ROUND(SUM(AB45:AD45),0) -> 24886088064 | AG45: 27816908987 | AJ45: 27816908987 | AK45: 15671398500 | AM45: 15671398500 | AN45: 0 | AP45: 0 | AQ45: 0 | AS45: 0 | AT45: 0 | AV45: 0 | AW45: 0 | AY45: 0 | BC45: =ROUND(SUM(AJ45,AM45,AP45,AS45,AV45,AY45,AZ45),0) -> 43488307487 | BF45: =ROUND(SUM(BC45:BE45),0) -> 43488307487
B46: Right of Used of Asset | E46: 0 | H46: 0 | I46: 11843914378 | K46: 11843914378 | L46: 0 | N46: 0 | O46: 0 | Q46: 0 | R46: 0 | T46: 0 | U46: 0 | W46: 0 | AB46: =SUM(H46,K46,X46,Y46,Z46:AA46,N46,Q46,T46,W46) -> 11843914378 | AE46: =ROUND(SUM(AB46:AD46),0) -> 11843914378 | AG46: 0 | AJ46: 0 | AK46: 140145541230 | AM46: 140145541230 | AN46: 0 | AP46: 0 | AQ46: 0 | AS46: 0 | AT46: 0 | AV46: 0 | AW46: 0 | AY46: 0 | BC46: =ROUND(SUM(AJ46,AM46,AP46,AS46,AV46,AY46,AZ46),0) -> 140145541230 | BF46: =ROUND(SUM(BC46:BE46),0) -> 140145541230
B47: Shareholder Receivable | E47: 0 | H47: 0 | I47: 0 | K47: 0 | L47: 23625000 | N47: 23625000 | O47: 1789200000 | Q47: 1789200000 | R47: 669375000 | T47: 669375000 | U47: 0 | W47: 0 | AA47: 0 | AB47: =SUM(H47,K47,X47,Y47,Z47:AA47,N47,Q47,T47,W47) -> 2482200000 | AE47: =ROUND(SUM(AB47:AD47),0) -> 2482200000 | AG47: 0 | AJ47: 0 | AK47: 0 | AM47: 0 | AN47: 23625000 | AP47: 23625000 | AQ47: 0 | AS47: 0 | AT47: 850500000 | AV47: 850500000 | AW47: 0 | AY47: 0 | BB47: 0 | BC47: =ROUND(SUM(AJ47,AM47,AP47,AS47,AV47,AY47,AZ47),0) -> 874125000 | BF47: =ROUND(SUM(BC47:BE47),0) -> 874125000
B48: Prepayments - non-current | E48: 0 | H48: 0 | I48: 0 | K48: 0 | L48: 0 | N48: 0 | O48: 0 | Q48: 0 | R48: 0 | T48: 0 | U48: 0 | W48: 0 | AA48: 0 | AB48: =SUM(H48,K48,X48,Y48,Z48:AA48,N48,Q48,T48,W48) -> 0 | AE48: =ROUND(SUM(AB48:AD48),0) -> 0 | AG48: 0 | AJ48: 0 | AK48: 2173500000 | AM48: 2173500000 | AN48: 0 | AP48: 0 | AQ48: 0 | AS48: 0 | AT48: 0 | AV48: 0 | AW48: 0 | AY48: 0 | BB48: 0 | BC48: =ROUND(SUM(AJ48,AM48,AP48,AS48,AV48,AY48,AZ48),0) -> 2173500000 | BF48: =ROUND(SUM(BC48:BE48),0) -> 2173500000
B49: Deferred Tax Asset | E49: 0 | H49: 0 | I49: 0 | K49: 0 | L49: 0 | N49: 0 | O49: 0 | Q49: 0 | R49: 0 | T49: 0 | U49: 0 | W49: 0 | AB49: =SUM(H49,K49,X49,Y49,Z49:AA49,N49,Q49,T49,W49) -> 0 | AE49: =ROUND(SUM(AB49:AD49),0) -> 0 | AG49: 0 | AJ49: 0 | AK49: 0 | AM49: 0 | AN49: 0 | AP49: 0 | AQ49: 0 | AS49: 0 | AT49: 0 | AV49: 0 | AW49: 0 | AY49: 0 | BC49: =ROUND(SUM(AJ49,AM49,AP49,AS49,AV49,AY49,AZ49),0) -> 0 | BF49: =ROUND(SUM(BC49:BE49),0) -> 0
B50: Other non-current assets | E50: 1255362372 | H50: 1255362372 | I50: 11705633633 | K50: 11705633633 | L50: 0 | N50: 0 | O50: 0 | Q50: 0 | R50: 0 | T50: 0 | U50: 0 | W50: 0 | AB50: =SUM(H50,K50,X50,Y50,Z50:AA50,N50,Q50,T50,W50) -> 12960996005 | AE50: =ROUND(SUM(AB50:AD50),0)-800 -> 12960995205 | AG50: 1047306519 | AJ50: 1047306519 | AK50: 7726897981 | AM50: 7726897981 | AN50: 0 | AP50: 0 | AQ50: 0 | AS50: 0 | AT50: 0 | AV50: 0 | AW50: 0 | AY50: 0 | BC50: =ROUND(SUM(AJ50,AM50,AP50,AS50,AV50,AY50,AZ50),0) -> 8774204500 | BF50: =ROUND(SUM(BC50:BE50),0) -> 8774204500
B52: TOTAL NON CURRENT ASSETS | E52: =SUM(E39:E51) -> 14666554983 | H52: =SUM(H39:H51) -> 14666554983 | I52: =SUM(I39:I51) -> 58820171503 | K52: =SUM(K39:K51) -> 58820171503 | L52: =SUM(L39:L51) -> 204923250 | N52: =SUM(N39:N51) -> 204923250 | O52: =SUM(O39:O51) -> 1789200000 | Q52: =SUM(Q39:Q51) -> 1789200000 | R52: =SUM(R39:R51) -> 681236883 | T52: =SUM(T39:T51) -> 681236883 | U52: =SUM(U39:U51) -> 0 | W52: =SUM(W39:W51) -> 0 | AB52: =SUM(AB39:AB51) -> 2.1156322e+10 | AE52: =SUM(AE39:AE51) -> 76162085819 | AG52: =SUM(AG39:AG51) -> 1.5953585e+11 | AJ52: =SUM(AJ39:AJ51) -> 1.5953585e+11 | AK52: =SUM(AK39:AK51) -> 215478993591 | AM52: =SUM(AM39:AM51) -> 215478993591 | AN52: =SUM(AN39:AN51) -> 23625000 | AP52: =SUM(AP39:AP51) -> 23625000 | AQ52: =SUM(AQ39:AQ51) -> 0 | AS52: =SUM(AS39:AS51) -> 0 | AT52: =SUM(AT39:AT51) -> 873517214 | AV52: =SUM(AV39:AV51) -> 873517214 | AW52: =SUM(AW39:AW51) -> 0 | AY52: =SUM(AY39:AY51) -> 0 | BC52: =SUM(BC39:BC51) -> 378005707322 | BF52: =SUM(BF39:BF51) -> 245517874780
E53: ^ | I53: ^ | L53: ^ | O53: ^ | R53: ^ | U53: ^ | AB53: ^ | AE53: ^ | AG53: ^ | AK53: ^ | AN53: ^ | AQ53: ^ | AT53: ^ | AW53: ^ | BC53: ^ | BF53: ^
B54: TOTAL ASSETS | E54: =E37+E52 -> 1.0015187e+12 | H54: =H37+H52 -> 1.0015187e+12 | I54: =I37+I52 -> 431970378147 | K54: =K37+K52 -> 431970378147 | L54: =L37+L52 -> 13412130535 | N54: =N37+N52 -> 13412130535 | O54: =O37+O52 -> 56113031103 | Q54: =Q37+Q52 -> 56113031103 | R54: =R37+R52 -> 166319589162 | T54: =T37+T52 -> 166319589162 | U54: =U37+U52 -> 0 | W54: =W37+W52 -> 0 | AB54: =AB37+AB52 -> 1.6143281e+12 | AE54: =AE37+AE52 -> 747082764274 | AG54: =AG37+AG52 -> 3.0960532e+11 | AJ54: =AJ37+AJ52 -> 3.0960532e+11 | AK54: =AK37+AK52 -> 378338583200 | AM54: =AM37+AM52 -> 378338583200 | AN54: =AN37+AN52 -> 1.3769358e+09 | AP54: =AP37+AP52 -> 1.3769358e+09 | AQ54: =AQ37+AQ52 -> 14097506977 | AS54: =AS37+AS52 -> 14097506977 | AT54: =AT37+AT52 -> 1.1754628e+11 | AV54: =AV37+AV52 -> 1.1754628e+11 | AW54: =AW37+AW52 -> 0 | AY54: =AY37+AY52 -> 0 | BC54: =BC37+BC52 -> 823058339155 | BF54: =BF37+BF52 -> 653688916174
E55: ^ | I55: ^ | L55: ^ | O55: ^ | R55: ^ | U55: ^ | AB55: ^ | AG55: ^ | AK55: ^ | AN55: ^ | AQ55: ^ | AT55: ^ | AW55: ^ | BC55: ^
B56: LIABILITIES
B57: CURRENT LIABILITIES
B58: Short-tern Bank Loans | E58: -23477724917 | H58: -23477724917 | I58: =-15716362212-78750000000 -> -94466362212 | K58: =SUM(I58:J58) -> -94466362212 | L58: 0 | N58: 0 | O58: 0 | Q58: 0 | R58: -23497929999 | T58: -23497929999 | U58: 0 | W58: 0 | AB58: =SUM(H58,K58,X58,Y58,Z58:AA58,N58,Q58,T58,W58) -> -141442017128 | AE58: =ROUND(SUM(AB58:AD58),0) -> -141442017128 | AG58: -11025000000 | AJ58: -11025000000 | AK58: =-15523844204-16647530688 -> -32171374892 | AM58: -32171374892 | AN58: 0 | AP58: 0 | AQ58: 0 | AS58: 0 | AT58: 0 | AV58: 0 | AW58: 0 | AY58: 0 | BC58: =ROUND(SUM(AJ58,AM58,AP58,AS58,AV58,AY58,AZ58),0) -> -43196374892 | BF58: =ROUND(SUM(BC58:BE58),0) -> -43196374892 | BH58: ok
B59: Account Payable
B60: Account Payable - Third Parties | E60: -8540007944 | H60: -8540007944 | I60: -23842772056 | K60: -23842772056 | L60: -1306072821 | N60: -1306072821 | O60: -10488095 | Q60: -10488095 | R60: -14056983157 | T60: -14056983157 | U60: 0 | W60: 0 | AB60: =SUM(H60,K60,X60,Y60,Z60:AA60,N60,Q60,T60,W60) -> -47756324073 | AE60: =ROUND(SUM(AB60:AD60),0) -> -47756324073 | AG60: -20939555138 | AJ60: -20939555138 | AK60: -14460551044 | AM60: -14460551044 | AN60: 0 | AP60: 0 | AQ60: 0 | AS60: 0 | AT60: -2.3389356e+08 | AV60: -2.3389356e+08 | AW60: 0 | AY60: 0 | BC60: =ROUND(SUM(AJ60,AM60,AP60,AS60,AV60,AY60,AZ60),0) -> -35633999745 | BF60: =ROUND(SUM(BC60:BE60),0) -> -35633999745 | BH60: ok
B61: Account Payable - Related Parties | E61: -16677146926 | H61: -16677146926 | I61: 0 | K61: 0 | L61: 0 | N61: 0 | O61: -64992375 | Q61: -64992375 | R61: -757589512 | T61: -757589512 | U61: 0 | W61: 0 | AB61: =SUM(H61,K61,X61,Y61,Z61:AA61,N61,Q61,T61,W61) -> -17499728813 | AC61: =SUM('Elimination 23'!G58)+SUM('Elimination 23'!G68:G69)+'Elimination 23'!G78 -> 1.6724757e+10 | AE61: =ROUND(SUM(AB61:AD61),0) -> -774971649 | AG61: -1417500000 | AJ61: -1417500000 | AK61: 0 | AM61: 0 | AN61: -1575000 | AP61: -1575000 | AQ61: 0 | AS61: 0 | AT61: 0 | AV61: 0 | AW61: 0 | AY61: 0 | BC61: =ROUND(SUM(AJ61,AM61,AP61,AS61,AV61,AY61,AZ61),0) -> -1419075000 | BD61: =SUM('Elimination 22'!G62,'Elimination 22'!G64) -> 1419075000 | BF61: =ROUND(SUM(BC61:BE61),0) -> 0
B62: Accrued Expenses
B63: Accrued Expenses - Third Parties | E63: -25805117827 | H63: -25805117827 | I63: -31584211682 | J63: 0 | K63: -31584211682 | L63: 0 | M63: 0 | N63: 0 | O63: -343035000 | Q63: -343035000 | R63: -1.6911653e+09 | S63: 0 | T63: -1.6911653e+09 | U63: 0 | W63: 0 | AB63: =SUM(H63,K63,X63,Y63,Z63:AA63,N63,Q63,T63,W63) -> -5.942353e+10 | AE63: =ROUND(SUM(AB63:AD63),0) -> -59423529841 | AG63: -44636984121 | AJ63: -44636984121 | AK63: -37320309073 | AM63: -37320309073 | AN63: -1.6341628e+09 | AP63: -1.6341628e+09 | AQ63: -44887500 | AS63: -44887500 | AT63: -21262500 | AV63: -21262500 | AW63: 0 | AY63: 0 | BC63: =ROUND(SUM(AJ63,AM63,AP63,AS63,AV63,AY63,AZ63),0) -> -83657606012 | BD63: 0 | BF63: =ROUND(SUM(BC63:BE63),0) -> -83657606012 | BH63: ok
B64: Accrued Expenses - Related Parties | E64: 0 | H64: 0 | I64: 0 | K64: 0 | L64: 0 | N64: 0 | O64: 0 | Q64: 0 | R64: -8.4171491e+09 | T64: -8.4171491e+09 | U64: 0 | W64: 0 | AB64: =SUM(H64,K64,X64,Y64,Z64:AA64,N64,Q64,T64,W64) -> -8.4171491e+09 | AC64: ='Elimination 23'!G88 -> 8.4171491e+09 | AE64: =ROUND(SUM(AB64:AD64),0) -> 0 | AG64: 0 | AJ64: 0 | AK64: 0 | AM64: 0 | AN64: 0 | AP64: 0 | AQ64: 0 | AS64: 0 | AT64: -1798008334 | AV64: -1798008334 | AW64: 0 | AY64: 0 | BC64: =ROUND(SUM(AJ64,AM64,AP64,AS64,AV64,AY64,AZ64),0) -> -1798008334 | BD64: ='Elimination 22'!G71 -> 1798008334 | BF64: =ROUND(SUM(BC64:BE64),0) -> 0
B65: Deposit Payable | E65: -3998598175 | H65: -3998598175 | I65: 0 | K65: 0 | L65: 0 | N65: 0 | O65: 0 | Q65: 0 | R65: 0 | T65: 0 | U65: 0 | W65: 0 | AB65: =SUM(H65,K65,X65,Y65,Z65:AA65,N65,Q65,T65,W65) -> -3998598175 | AE65: =ROUND(SUM(AB65:AD65),0) -> -3998598175 | AG65: -6108774604 | AJ65: -6108774604 | AK65: 0 | AM65: 0 | AN65: 0 | AP65: 0 | AQ65: 0 | AS65: 0 | AT65: 0 | AV65: 0 | AW65: 0 | AY65: 0 | BC65: =ROUND(SUM(AJ65,AM65,AP65,AS65,AV65,AY65,AZ65),0) -> -6108774604 | BF65: =ROUND(SUM(BC65:BE65),0) -> -6108774604 | BH65: ok
B66: Tax Payables | E66: -2190985816 | H66: -2190985816 | I66: -2647943596 | K66: -2647943596 | L66: -210271714 | N66: -210271714 | O66: -25876398 | Q66: -25876398 | R66: -409166550 | T66: -409166550 | U66: 0 | W66: 0 | AB66: =SUM(H66,K66,X66,Y66,Z66:AA66,N66,Q66,T66,W66) -> -5484244074 | AE66: =ROUND(SUM(AB66:AD66),0) -> -5484244074 | AG66: -3966836088 | AJ66: -3966836088 | AK66: -4240362064 | AM66: -4240362064 | AN66: -191827.12 | AP66: -191827.12 | AQ66: -18811869 | AS66: -18811869 | AT66: -548830624 | AV66: -548830624 | AW66: 0 | AY66: 0 | BC66: =ROUND(SUM(AJ66,AM66,AP66,AS66,AV66,AY66,AZ66),0) -> -8775032472 | BF66: =ROUND(SUM(BC66:BE66),0) -> -8775032472 | BH66: ok
B67: Loan Payable Related Party | E67: -15877040272 | H67: -15877040272 | I67: -602607420011 | K67: -602607420011 | L67: -9187565842 | N67: -9187565842 | O67: -38975273693 | P67: 5.120913e+09 | Q67: -3.3854361e+10 | R67: -40883219693 | T67: -40883219693 | U67: 0 | W67: 0 | AB67: =SUM(H67,K67,X67,Y67,Z67:AA67,N67,Q67,T67,W67) -> -7.0240961e+11 | AC67: =SUM('Elimination 23'!G60:G61)+'Elimination 23'!G70+'Elimination 23'!G79+'Elimination 23'!G81 -> 6.8649226e+11 | AE67: =ROUND(SUM(AB67:AD67),0) -> -15917342497 | AG67: -14058094952 | AJ67: -14058094952 | AK67: 0 | AM67: 0 | AN67: 0 | AP67: 0 | AQ67: -125782200 | AS67: -125782200 | AT67: -3050955732 | AV67: -3050955732 | AW67: 0 | AY67: 0 | BC67: =ROUND(SUM(AJ67,AM67,AP67,AS67,AV67,AY67,AZ67),0) -> -17234832884 | BD67: ='Elimination 22'!G69+SUM('Elimination 22'!G78:G79)+'Elimination 22'!G72 -> 2.592349e+10 | BE67: ='Elimination 22'!H87 -> -8.7289589e+09 | BF67: =ROUND(SUM(BC67:BE67),0) -> -40302224 | BH67: ok
B68: Other Payables
B69: Other Payable - Third Parties | E69: 0 | H69: 0 | I69: 0 | K69: 0 | L69: 0 | N69: 0 | O69: 0 | Q69: 0 | R69: 0 | T69: 0 | U69: 0 | W69: 0 | AB69: =SUM(H69,K69,X69,Y69,Z69:AA69,N69,Q69,T69,W69) -> 0 | AE69: =ROUND(SUM(AB69:AD69),0) -> 0 | AG69: 0 | AJ69: 0 | AK69: 0 | AM69: 0 | AN69: 0 | AP69: 0 | AQ69: 0 | AS69: 0 | AT69: 0 | AV69: 0 | AW69: 0 | AY69: 0 | BC69: =ROUND(SUM(AJ69,AM69,AP69,AS69,AV69,AY69,AZ69),0) -> 0 | BF69: =ROUND(SUM(BC69:BE69),0) -> 0
B70: Other Payable - Related Parties | E70: 0 | H70: 0 | I70: -17087265241 | K70: -17087265241 | L70: -289441437 | N70: -289441437 | O70: 0 | P70: -5.120913e+09 | Q70: -5.120913e+09 | R70: -30256823164 | T70: -30256823164 | U70: 0 | W70: 0 | AB70: =SUM(H70,K70,X70,Y70,Z70:AA70,N70,Q70,T70,W70) -> -5.2754443e+10 | AC70: ='Elimination 23'!G80+'Elimination 23'!G59 -> 4.7344088e+10 | AE70: =ROUND(SUM(AB70:AD70),0) -> -5410354427 | AG70: 0 | AJ70: 0 | AK70: -16469976445 | AM70: -16469976445 | AN70: 0 | AP70: 0 | AQ70: 0 | AS70: 0 | AT70: 0 | AV70: 0 | AW70: 0 | AY70: 0 | BC70: =ROUND(SUM(AJ70,AM70,AP70,AS70,AV70,AY70,AZ70),0) -> -16469976445 | BD70: ='Elimination 22'!G63 -> 16469976445 | BF70: =ROUND(SUM(BC70:BE70),0) -> 0 | BH70: ok
B71: Borrowings | E71: 0 | H71: 0 | I71: 0 | K71: 0 | L71: 0 | N71: 0 | O71: 0 | Q71: 0 | R71: 0 | T71: 0 | U71: 0 | W71: 0 | AB71: =SUM(H71,K71,X71,Y71,Z71:AA71,N71,Q71,T71,W71) -> 0 | AE71: =ROUND(SUM(AB71:AD71),0) -> 0 | AG71: 0 | AJ71: 0 | AM71: 0 | AN71: 0 | AP71: 0 | AQ71: 0 | AS71: 0 | AT71: 0 | AV71: 0 | AW71: 0 | AY71: 0 | BC71: =ROUND(SUM(AJ71,AM71,AP71,AS71,AV71,AY71,AZ71),0) -> 0 | BF71: =ROUND(SUM(BC71:BE71),0) -> 0
B72: Payable to Subsidiaries | E72: 0 | H72: 0 | I72: 0 | K72: 0 | L72: 0 | N72: 0 | O72: 0 | Q72: 0 | R72: 0 | T72: 0 | U72: 0 | W72: 0 | AB72: =SUM(H72,K72,X72,Y72,Z72:AA72,N72,Q72,T72,W72) -> 0 | AE72: =ROUND(SUM(AB72:AD72),0) -> 0 | AG72: 0 | AJ72: 0 | AK72: 0 | AM72: 0 | AN72: 0 | AP72: 0 | AQ72: 0 | AS72: 0 | AT72: 0 | AV72: 0 | AW72: 0 | AY72: 0 | BC72: =ROUND(SUM(AJ72,AM72,AP72,AS72,AV72,AY72,AZ72),0) -> 0 | BF72: =ROUND(SUM(BC72:BE72),0) -> 0
B73: Payable to Shareholders | E73: 0 | H73: 0 | I73: 0 | K73: 0 | L73: 0 | N73: 0 | O73: 0 | Q73: 0 | R73: 0 | T73: 0 | U73: 0 | W73: 0 | AB73: =SUM(H73,K73,X73,Y73,Z73:AA73,N73,Q73,T73,W73) -> 0 | AE73: =ROUND(SUM(AB73:AD73),0) -> 0 | AG73: 0 | AJ73: 0 | AK73: 0 | AM73: 0 | AN73: 0 | AP73: 0 | AQ73: 0 | AS73: 0 | AT73: 0 | AV73: 0 | AW73: 0 | AY73: 0 | BC73: =ROUND(SUM(AJ73,AM73,AP73,AS73,AV73,AY73,AZ73),0) -> 0 | BF73: =ROUND(SUM(BC73:BE73),0) -> 0
B74: Unernead Revenue | E74: 0 | H74: 0 | I74: 0 | K74: 0 | L74: 0 | N74: 0 | O74: 0 | Q74: 0 | R74: 0 | T74: 0 | U74: 0 | W74: 0 | AB74: =SUM(H74,K74,X74,Y74,Z74:AA74,N74,Q74,T74,W74) -> 0 | AE74: =ROUND(SUM(AB74:AD74),0) -> 0 | AG74: 0 | AJ74: 0 | AK74: 0 | AM74: 0 | AN74: 0 | AP74: 0 | AQ74: 0 | AS74: 0 | AT74: 0 | AV74: 0 | AW74: 0 | AY74: 0 | BC74: =ROUND(SUM(AJ74,AM74,AP74,AS74,AV74,AY74,AZ74),0) -> 0 | BF74: =ROUND(SUM(BC74:BE74),0) -> 0
B75: Current Maturities of Lease Liability | E75: 0 | H75: 0 | I75: -57438550502 | K75: -57438550502 | L75: 0 | N75: 0 | O75: 0 | Q75: 0 | R75: 0 | T75: 0 | U75: 0 | W75: 0 | AB75: =SUM(H75,K75,X75,Y75,Z75:AA75,N75,Q75,T75,W75) -> -57438550502 | AE75: =ROUND(SUM(AB75:AD75),0) -> -57438550502 | AG75: 0 | AJ75: 0 | AK75: -52729712992 | AM75: -52729712992 | AN75: 0 | AP75: 0 | AQ75: 0 | AS75: 0 | AT75: 0 | AV75: 0 | AW75: 0 | AY75: 0 | BC75: =ROUND(SUM(AJ75,AM75,AP75,AS75,AV75,AY75,AZ75),0) -> -52729712992 | BF75: =ROUND(SUM(BC75:BE75),0) -> -52729712992 | BH75: ok
B76: Other Current Liabilities | E76: 0 | H76: 0 | I76: 0 | K76: 0 | L76: 0 | N76: 0 | O76: 0 | Q76: 0 | R76: 0 | T76: 0 | U76: 0 | W76: 0 | AB76: =SUM(H76,K76,X76,Y76,Z76:AA76,N76,Q76,T76,W76) -> 0 | AE76: =ROUND(SUM(AB76:AD76),0) -> 0 | AG76: 0 | AJ76: 0 | AK76: 0 | AM76: 0 | AN76: 0 | AP76: 0 | AQ76: 0 | AS76: 0 | AT76: 0 | AV76: 0 | AW76: 0 | AY76: 0 | BC76: =ROUND(SUM(AJ76,AM76,AP76,AS76,AV76,AY76,AZ76),0) -> 0 | BF76: =ROUND(SUM(BC76:BE76),0) -> 0
AN77: 0
B78: TOTAL CURRENT LIABILITIES | E78: =SUM(E58:E76) -> -96566621877 | H78: =SUM(H58:H76) -> -96566621877 | I78: =SUM(I58:I76) -> -829674525300 | K78: =SUM(K58:K76) -> -829674525300 | L78: =SUM(L58:L76) -> -10993351814 | N78: =SUM(N58:N76) -> -10993351814 | O78: =SUM(O58:O76) -> -39419665561 | Q78: =SUM(Q58:Q76) -> -39419665561 | R78: =SUM(R58:R76) -> -119970026506 | T78: =SUM(T58:T76) -> -119970026506 | U78: =SUM(U58:U76) -> 0 | W78: =SUM(W58:W76) -> 0 | AB78: =SUM(AB58:AB76) -> -1096624191058 | AE78: =SUM(AE58:AE76) -> -337645932366 | AG78: =SUM(AG58:AG76) -> -102152744903 | AJ78: =SUM(AJ58:AJ76) -> -102152744903 | AK78: =SUM(AK58:AK76) -> -157392286510 | AM78: =SUM(AM58:AM76) -> -157392286510 | AN78: =SUM(AN58:AN76) -> -1.6359296e+09 | AP78: =SUM(AP58:AP76) -> -1.6359296e+09 | AQ78: =SUM(AQ58:AQ76) -> -189481569 | AS78: =SUM(AS58:AS76) -> -189481569 | AT78: =SUM(AT58:AT76) -> -5.6529508e+09 | AV78: =SUM(AV58:AV76) -> -5.6529508e+09 | AW78: =SUM(AW58:AW76) -> 0 | AY78: =SUM(AY58:AY76) -> 0 | BC78: =SUM(BC58:BC76) -> -267023393380 | BF78: =SUM(BF58:BF76) -> -230141802941
E79: ^ | I79: ^ | L79: ^ | O79: ^ | R79: ^ | U79: ^ | AB79: ^ | AG79: ^ | AK79: ^ | AN79: ^ | AQ79: ^ | AT79: ^ | AW79: ^ | BC79: ^
B80: NON CURRENT LIABILITIES
B81: Lease liabilities - net of current maturities | E81: 0 | H81: 0 | I81: -32226982313 | K81: -32226982313 | L81: 0 | N81: 0 | O81: 0 | Q81: 0 | R81: 0 | T81: 0 | U81: 0 | W81: 0 | AB81: =SUM(H81,K81,X81,Y81,Z81:AA81,N81,Q81,T81,W81) -> -32226982313 | AE81: =ROUND(SUM(AB81:AD81),0) -> -32226982313 | AG81: 0 | AJ81: =SUM(AG81:AH81) -> 0 | AK81: -72365951557 | AM81: =SUM(AK81:AL81) -> -72365951557 | AP81: =SUM(AN81:AO81) -> 0 | AQ81: =SUM(AO81:AP81) -> 0 | AS81: =SUM(AQ81:AR81) -> 0 | AT81: 0 | AV81: =SUM(AT81:AU81) -> 0 | AY81: =SUM(AW81:AX81) -> 0 | BC81: =ROUND(SUM(AJ81,AM81,AP81,AS81,AV81,AY81,AZ81),0) -> -72365951557 | BF81: =ROUND(SUM(BC81:BE81),0)-2 -> -72365951559 | BH81: ok
B82: Employee Benefit Liabilities | E82: -1.9231329e+09 | H82: -1.9231329e+09 | I82: -2.9301694e+09 | K82: -2.9301694e+09 | L82: 0 | N82: 0 | O82: 0 | Q82: 0 | R82: 0 | T82: 0 | U82: 0 | W82: 0 | AB82: =SUM(H82,K82,X82,Y82,Z82:AA82,N82,Q82,T82,W82) -> -4.8533023e+09 | AE82: =ROUND(SUM(AB82:AD82),0) -> -4853302291 | AG82: -1.4211746e+09 | AJ82: =SUM(AG82:AH82) -> -1.4211746e+09 | AK82: -3.4970723e+09 | AM82: =SUM(AK82:AL82) -> -3.4970723e+09 | AN82: 0 | AP82: =SUM(AN82:AO82) -> 0 | AQ82: =SUM(AO82:AP82) -> 0 | AS82: =SUM(AQ82:AR82) -> 0 | AT82: 0 | AV82: =SUM(AT82:AU82) -> 0 | AW82: 0 | AY82: =SUM(AW82:AX82) -> 0 | BC82: =ROUND(SUM(AJ82,AM82,AP82,AS82,AV82,AY82,AZ82),0) -> -4918246882 | BF82: =ROUND(SUM(BC82:BE82),0) -> -4918246882
B83: Loan Payable Related Party - non current | E83: 0 | H83: 0 | I83: 0 | K83: 0 | L83: 0 | N83: 0 | O83: 0 | Q83: 0 | R83: -144237470598 | T83: -144237470598 | U83: 0 | W83: 0 | AB83: =SUM(H83,K83,X83,Y83,Z83:AA83,N83,Q83,T83,W83) -> -144237470598 | AC83: ='Elimination 23'!G71-1 -> 1.4423747e+11 | AE83: =ROUND(SUM(AB83:AD83),0) -> 0 | AG83: 0 | AJ83: 0 | AK83: 0 | AM83: =SUM(AK83:AL83) -> 0 | AN83: 0 | AP83: =SUM(AN83:AO83) -> 0 | AQ83: =SUM(AO83:AP83) -> 0 | AS83: =SUM(AQ83:AR83) -> 0 | AT83: -130394112648 | AV83: =SUM(AT83:AU83) -> -130394112648 | AW83: 0 | AY83: =SUM(AW83:AX83) -> 0 | BC83: =ROUND(SUM(AJ83,AM83,AP83,AS83,AV83,AY83,AZ83),0) -> -130394112648 | BD83: ='Elimination 22'!G70 -> 1.3039411e+11 | BF83: =ROUND(SUM(BC83:BE83),0) -> 0
B84: Deferred Tax Liabilities | E84: 0 | H84: 0 | I84: -11841969435 | K84: -11841969435 | L84: 0 | N84: 0 | O84: 0 | Q84: 0 | R84: 0 | T84: 0 | U84: 0 | W84: 0 | AB84: =SUM(H84,K84,X84,Y84,Z84:AA84,N84,Q84,T84,W84) -> -11841969435 | AE84: =ROUND(SUM(AB84:AD84),0) -> -11841969435 | AG84: 0 | AJ84: =SUM(AG84:AH84) -> 0 | AK84: -3469782201 | AM84: =SUM(AK84:AL84) -> -3469782201 | AN84: 0 | AP84: =SUM(AN84:AO84) -> 0 | AQ84: =SUM(AO84:AP84) -> 0 | AS84: =SUM(AQ84:AR84) -> 0 | AT84: 0 | AV84: =SUM(AT84:AU84) -> 0 | AW84: 0 | AY84: =SUM(AW84:AX84) -> 0 | BC84: =ROUND(SUM(AJ84,AM84,AP84,AS84,AV84,AY84,AZ84),0) -> -3469782201 | BF84: =ROUND(SUM(BC84:BE84),0) -> -3469782201 | BH84: ok
B85: Other non-current liabilities | E85: 0 | H85: 0 | I85: -4735334275 | K85: -4735334275 | L85: 0 | N85: 0 | O85: 0 | Q85: 0 | R85: 0 | T85: 0 | U85: 0 | W85: 0 | AB85: =SUM(H85,K85,X85,Y85,Z85:AA85,N85,Q85,T85,W85) -> -4735334275 | AE85: =ROUND(SUM(AB85:AD85),0) -> -4735334275 | AG85: 0 | AJ85: =SUM(AG85:AH85) -> 0 | AK85: 0 | AM85: =SUM(AK85:AL85) -> 0 | AN85: 0 | AP85: =SUM(AN85:AO85) -> 0 | AQ85: =SUM(AO85:AP85) -> 0 | AS85: =SUM(AQ85:AR85) -> 0 | AT85: 0 | AV85: =SUM(AT85:AU85) -> 0 | AW85: 0 | AY85: =SUM(AW85:AX85) -> 0 | BC85: =ROUND(SUM(AJ85,AM85,AP85,AS85,AV85,AY85,AZ85),0) -> 0 | BF85: =ROUND(SUM(BC85:BE85),0) -> 0
B87: TOTAL NON CURRENT LIABILITIES | E87: =SUM(E81:E85) -> -1.9231329e+09 | H87: =SUM(H81:H85) -> -1.9231329e+09 | I87: =SUM(I81:I85) -> -5.1734455e+10 | K87: =SUM(K81:K85) -> -5.1734455e+10 | L87: =SUM(L81:L85) -> 0 | N87: =SUM(N81:N85) -> 0 | O87: =SUM(O81:O85) -> 0 | Q87: =SUM(Q81:Q85) -> 0 | R87: =SUM(R81:R85) -> -144237470598 | T87: =SUM(T81:T85) -> -144237470598 | U87: =SUM(U81:U85) -> 0 | W87: =SUM(W81:W85) -> 0 | AB87: =SUM(AB81:AB85) -> -1.9789506e+11 | AE87: =SUM(AE81:AE85) -> -53657588314 | AG87: =SUM(AG81:AG85) -> -1.4211746e+09 | AJ87: =SUM(AJ81:AJ85) -> -1.4211746e+09 | AK87: =SUM(AK81:AK85) -> -7.9332806e+10 | AM87: =SUM(AM81:AM85) -> -7.9332806e+10 | AN87: =SUM(AN81:AN85) -> 0 | AP87: =SUM(AP81:AP85) -> 0 | AQ87: =SUM(AQ81:AQ85) -> 0 | AS87: =SUM(AS81:AS85) -> 0 | AT87: =SUM(AT81:AT85) -> -130394112648 | AV87: =SUM(AV81:AV85) -> -130394112648 | AW87: =SUM(AW81:AW85) -> 0 | AY87: =SUM(AY81:AY85) -> 0 | BC87: =SUM(BC81:BC85) -> -211148093288 | BF87: =SUM(BF81:BF85) -> -80753980642
E88: ^ | H88: ^ | I88: ^ | K88: ^ | L88: ^ | N88: ^ | O88: ^ | Q88: ^ | R88: ^ | T88: ^ | U88: ^ | W88: ^ | AB88: ^ | AE88: ^ | AG88: ^ | AJ88: ^ | AK88: ^ | AM88: ^ | AN88: ^ | AP88: ^ | AQ88: ^ | AS88: ^ | AT88: ^ | AV88: ^ | AW88: ^ | AY88: ^ | BC88: ^ | BF88: ^
B89: TOTAL LIABILITIES | E89: =E78+E87 -> -9.8489755e+10 | H89: =H78+H87 -> -9.8489755e+10 | I89: =I78+I87 -> -8.8140898e+11 | K89: =K78+K87 -> -8.8140898e+11 | L89: =L78+L87 -> -10993351814 | N89: =N78+N87 -> -10993351814 | O89: =O78+O87 -> -39419665561 | Q89: =Q78+Q87 -> -39419665561 | R89: =R78+R87 -> -264207497104 | T89: =T78+T87 -> -264207497104 | U89: =U78+U87 -> 0 | W89: =W78+W87 -> 0 | AB89: =AB78+AB87 -> -1.2945192e+12 | AE89: =AE78+AE87 -> -391303520680 | AG89: =AG78+AG87 -> -1.0357392e+11 | AJ89: =AJ78+AJ87 -> -1.0357392e+11 | AK89: =AK78+AK87 -> -2.3672509e+11 | AM89: =AM78+AM87 -> -2.3672509e+11 | AN89: =AN78+AN87 -> -1.6359296e+09 | AP89: =AP78+AP87 -> -1.6359296e+09 | AQ89: =AQ78+AQ87 -> -189481569 | AS89: =AS78+AS87 -> -189481569 | AT89: =AT78+AT87 -> -1.3604706e+11 | AV89: =AV78+AV87 -> -1.3604706e+11 | AW89: =AW78+AW87 -> 0 | AY89: =AY78+AY87 -> 0 | BC89: =BC78+BC87 -> -478171486668 | BF89: =BF78+BF87 -> -310895783583
E90: ^ | I90: ^ | L90: ^ | O90: ^ | R90: ^ | U90: ^ | AB90: ^ | AE90: ^ | AG90: ^ | AK90: ^ | AN90: ^ | AQ90: ^ | AT90: ^ | AW90: ^ | BC90: ^ | BF90: ^
B91: EQUITY
B92: Equity | L92: 0 | R92: 0 | AB92: =SUM(H92,K92,X92,Y92,Z92:AA92,N92,Q92,T92,W92) -> 0 | AE92: =SUM(AB92:AD92) -> 0
B93: Shareholder Equity | E93: -486708075000 | H93: -486708075000 | I93: -651665345625 | K93: -651665345625 | L93: -23625000 | N93: -23625000 | O93: -4921875000 | Q93: -4921875000 | R93: -472500000 | T93: -472500000 | U93: 0 | W93: 0 | AB93: =SUM(H93,K93,X93,Y93,Z93:AA93,N93,Q93,T93,W93) -> -1143791420625 | AC93: ='Elimination 23'!G6+'Elimination 23'!G28+'Elimination 23'!G38+'Elimination 23'!G48 -> 657083345625 | AE93: =ROUND(SUM(AB93:AD93),0) -> -486708075000 | AG93: -142427250000 | AJ93: -142427250000 | AK93: -217283295600 | AM93: -217283295600 | AN93: -23625000 | AP93: -23625000 | AQ93: -984375000 | AS93: -984375000 | AT93: -472500000 | AV93: -472500000 | AW93: 0 | AY93: 0 | BC93: =ROUND(SUM(AJ93,AM93,AP93,AS93,AV93,AY93,AZ93),0) -> -361191045600 | BD93: ='Elimination 22'!G6+'Elimination 22'!G30+'Elimination 22'!G38+'Elimination 22'!G52 -> 218763795600 | BF93: =ROUND(SUM(BC93:BE93),0) -> -142427250000
B94: Advance Capital | E94: -1.0032756e+12 | H94: -1.0032756e+12 | I94: 0 | K94: 0 | L94: 0 | N94: 0 | O94: 0 | Q94: 0 | R94: 0 | T94: 0 | U94: 0 | W94: 0 | AB94: =SUM(H94,K94,X94,Y94,Z94:AA94,N94,Q94,T94,W94) -> -1.0032756e+12 | AE94: =ROUND(SUM(AB94:AD94),0) -> -1003275649843 | AG94: -3.5785358e+11 | AJ94: -3.5785358e+11 | AK94: -4.3008243e+11 | AM94: -4.3008243e+11 | AN94: 0 | BC94: =ROUND(SUM(AJ94,AM94,AP94,AS94,AV94,AY94,AZ94),0) -> -787936009183 | BD94: ='Elimination 22'!G7 -> 4.3008243e+11 | BF94: =ROUND(SUM(BC94:BE94),0) -> -357853579198
B95: Additional Paid in Capital | O95: 0 | Q95: 0 | U95: 0 | W95: 0 | AB95: =SUM(H95,K95,X95,Y95,Z95:AA95,N95,Q95,T95,W95) -> 0 | AE95: =SUM(AB95:AD95) -> 0 | AK95: 0 | AM95: 0 | AN95: 0 | AP95: 0 | AQ95: -2165625000 | AS95: -2165625000 | AT95: 0 | AV95: 0 | AW95: 0 | AY95: 0 | BC95: =ROUND(SUM(AJ95,AM95,AP95,AS95,AV95,AY95,AZ95),0) -> -2165625000 | BD95: ='Elimination 22'!G42 -> 2165625000 | BF95: =ROUND(SUM(BC95:BE95),0) -> 0
B96: Share-based compensation reserve | AE96: =SUM(AB96:AD96) -> 0
B97: - Beginning Balance ESOP | E97: -2.8533902e+10 | H97: -2.8533902e+10 | I97: -4.5465255e+09 | K97: -4.5465255e+09 | L97: 0 | N97: 0 | O97: 0 | P97: 0 | Q97: 0 | R97: 0 | T97: 0 | U97: 0 | V97: 0 | W97: 0 | X97: 0 | AB97: =SUM(H97,K97,X97,Y97,Z97:AA97,N97,Q97,T97,W97) -> -3.3080427e+10 | AC97: ='Elimination 23'!G17 -> 4.5465255e+09 | AE97: =ROUND(SUM(AB97:AD97),0) -> -28533901860 | AG97: -9.1049162e+09 | AJ97: -9.1049162e+09 | AK97: -1287204345 | AM97: -1287204345 | AN97: 0 | AP97: 0 | AQ97: 0 | AS97: 0 | AT97: 0 | AV97: 0 | AW97: 0 | AY97: 0 | AZ97: 0 | BC97: =ROUND(SUM(AJ97,AM97,AP97,AS97,AV97,AY97,AZ97),0) -> -10392120542 | BD97: ='Elimination 22'!G21 -> 1287204345 | BF97: =ROUND(SUM(BC97:BE97),0) -> -9104916197
B98: - Current year ESOP reserve | E98: -1.3850429e+10 | H98: -1.3850429e+10 | I98: -7.0053707e+09 | K98: -7.0053707e+09 | L98: 0 | N98: 0 | O98: 0 | Q98: 0 | R98: 0 | T98: 0 | U98: 0 | W98: 0 | AB98: =SUM(H98,K98,X98,Y98,Z98:AA98,N98,Q98,T98,W98) -> -2.0855799e+10 | AC98: ='Elimination 23'!G18 -> 7.0053707e+09 | AE98: =ROUND(SUM(AB98:AD98),0) -> -13850428637 | AG98: -1.9428986e+10 | AJ98: -1.9428986e+10 | AK98: -3.2593211e+09 | AM98: -3.2593211e+09 | AN98: 0 | AP98: 0 | AQ98: 0 | AS98: 0 | AT98: 0 | AV98: 0 | AW98: 0 | AY98: 0 | BC98: =ROUND(SUM(AJ98,AM98,AP98,AS98,AV98,AY98,AZ98),0) -> -22688306810 | BD98: ='Elimination 22'!G22 -> 3.2593211e+09 | BF98: =ROUND(SUM(BC98:BE98),0) -> -19428985663
B99: Difference in value from transaction with non-controlling interest | I99: 0 | K99: 0 | L99: 0 | N99: 0 | Q99: 0 | R99: 0 | T99: 0 | W99: 0 | AB99: =SUM(H99,K99,X99,Y99,Z99:AA99,N99,Q99,T99,W99) -> 0 | AE99: =ROUND(SUM(AB99:AD99),0) -> 0 | AK99: 0 | AM99: 0 | AN99: 0 | AP99: 0 | AQ99: 0 | AS99: 0 | AT99: 0 | AV99: 0 | AW99: 0 | AY99: 0 | BC99: =ROUND(SUM(AJ99,AM99,AP99,AS99,AV99,AY99,AZ99),0) -> 0 | BF99: =SUM(BC99:BE99) -> 0
B100: Retained earnings
B101: - Beginning retained earnings | E101: =SUM(AJ101:AJ102) -> 3.2367391e+11 | H101: =SUM(E101:G101) -> 3.2367391e+11 | I101: =325102299933*1.575 -> 5.1203612e+11 | K101: =SUM(I101:J101) -> 5.1203612e+11 | L101: =179440519*1.575 -> 2.8261882e+08 | N101: =SUM(L101:M101) -> 2.8261882e+08 | O101: =-6830492323*1.575 -> -1.0758025e+10 | P101: 0 | Q101: =SUM(O101:P101) -> -1.0758025e+10 | R101: 19179424326 | T101: =SUM(R101:S101) -> 19179424326 | U101: 0 | V101: 0 | W101: =SUM(U101:V101) -> 0 | X101: 0 | AB101: =SUM(H101,K101,X101,Y101,Z101:AA101,N101,Q101,T101,W101) -> 8.4441405e+11 | AC101: ='Elimination 23'!G42 -> 1.0758025e+10 | AD101: ='Elimination 23'!H14+'Elimination 23'!H36+'Elimination 23'!H55 -> -5.3149817e+11 | AE101: =ROUND(SUM(AB101:AD101),0) -> 323673912325 | AG101: 145740154214 | AJ101: =SUM(AG101:AI101) -> 145740154214 | AK101: 1.2996164e+11 | AM101: =SUM(AK101:AL101) -> 1.2996164e+11 | AN101: 0 | AP101: =SUM(AN101:AO101) -> 0 | AQ101: =-7195288493*1.575 -> -1.1332579e+10 | AS101: =SUM(AQ101:AR101) -> -1.1332579e+10 | AT101: -20240927228 | AV101: =SUM(AT101:AU101) -> -20240927228 | AW101: 0 | AY101: =SUM(AW101:AX101) -> 0 | AZ101: 0 | BC101: =ROUND(SUM(AJ101,AM101,AP101,AS101,AV101,AY101,AZ101),0) -> 244128288268 | BD101: ='Elimination 22'!G46+'Elimination 22'!G56 -> 3.1573507e+10 | BE101: ='Elimination 22'!H18 -> -1.2996164e+11 | BF101: =ROUND(SUM(BC101:BE101),0) -> 145740154214
B102: - Current profit or loss | E102: ='Consol SoPL-OCI 23 & 22'!D86 -> 3.0717049e+11 | G102: =-G26-G29 -> 0 | H102: =SUM(E102:G102) -> 3.0717049e+11 | I102: ='Consol SoPL-OCI 23 & 22'!H86 -> 6.0319819e+11 | J102: ='Adjustment Consolaa'!G14 -> 0 | K102: =SUM(I102:J102) -> 6.0319819e+11 | L102: ='Consol SoPL-OCI 23 & 22'!K86 -> -2677772539 | N102: =SUM(L102:M102) -> -2677772539 | O102: ='Consol SoPL-OCI 23 & 22'!N86 -> -1013465132 | Q102: =SUM(O102:P102) -> -1013465132 | R102: ='Consol SoPL-OCI 23 & 22'!Q86 -> 7.9178339e+10 | T102: =SUM(R102:S102) -> 7.9178339e+10 | U102: 0 | W102: =SUM(U102:V102) -> 0 | AB102: =SUM(H102,K102,X102,Y102,Z102:AA102,N102,Q102,T102,W102) -> 9.8585577e+11 | AC102: ='Elimination 23'!G32+'Elimination 23'!G43+SUM('Elimination 23'!G95:G97)+'Elimination 23'!G94+'Elimination 23'!G103 -> 2.2726569e+10 | AD102: ='Elimination 23'!H15+'Elimination 23'!H56+'Elimination 23'!H110 -> -6.8237653e+11 | AE102: =ROUND(SUM(AB102:AD102),0) -> 326205816418 | AG102: ='Consol SoPL-OCI 23 & 22'!AE86 -> 1.7793376e+11 | AJ102: =SUM(AG102:AI102) -> 1.7793376e+11 | AK102: ='Consol SoPL-OCI 23 & 22'!AI86 -> 3.8207448e+11 | AM102: =SUM(AK102:AL102) -> 3.8207448e+11 | AN102: ='Consol SoPL-OCI 23 & 22'!AL86 -> 2.8261882e+08 | AP102: =SUM(AN102:AO102) -> 2.8261882e+08 | AQ102: ='Consol SoPL-OCI 23 & 22'!AO86 -> 574553968 | AS102: =SUM(AQ102:AR102) -> 574553968 | AT102: ='Consol SoPL-OCI 23 & 22'!AR86 -> 3.9420352e+10 | AV102: =SUM(AT102:AU102) -> 3.9420352e+10 | AW102: 0 | AY102: =SUM(AW102:AX102) -> 0 | BC102: =ROUND(SUM(AJ102,AM102,AP102,AS102,AV102,AY102,AZ102),0) -> 600285764188 | BD102: ='Elimination 22'!G47 -> -574553968 | BE102: ='Elimination 22'!H19+'Elimination 22'!H36+'Elimination 22'!G57 -> -4.2177745e+11 | BF102: =ROUND(SUM(BC102:BE102),0) -> 177933758111
B103: OCI - Emben | H103: =SUM(E103:G103) -> 0 | K103: =SUM(I103:J103) -> 0 | Q103: =SUM(O103:P103) -> 0 | T103: =SUM(R103:S103) -> 0 | W103: =SUM(U103:V103) -> 0 | AB103: =SUM(H103,K103,X103,Y103,Z103:AA103,N103,Q103,T103,W103) -> 0 | AJ103: =SUM(AG103:AI103) -> 0 | AM103: =SUM(AK103:AL103) -> 0 | AP103: =SUM(AN103:AO103) -> 0 | AS103: =SUM(AQ103:AR103) -> 0 | AV103: =SUM(AT103:AU103) -> 0 | AY103: =SUM(AW103:AX103) -> 0 | BC103: =ROUND(SUM(AJ103,AM103,AP103,AS103,AV103,AY103,AZ103),0) -> 0
B104: - Beginning - OCI Emben | E104: =SUM(AG104:AG105) -> -8.9057972e+08 | H104: =SUM(E104:G104) -> -8.9057972e+08 | I104: =-1103086940*1.575 -> -1.7373619e+09 | K104: =SUM(I104:J104) -> -1.7373619e+09 | L104: 0 | N104: =SUM(L104:M104) -> 0 | O104: 0 | P104: 0 | Q104: =SUM(O104:P104) -> 0 | R104: 0 | T104: =SUM(R104:S104) -> 0 | U104: 0 | V104: 0 | W104: =SUM(U104:V104) -> 0 | AB104: =SUM(H104,K104,X104,Y104,Z104:AA104,N104,Q104,T104,W104) -> -2.6279416e+09 | AC104: ='Elimination 23'!G22 -> 1.7373619e+09 | AE104: =ROUND(SUM(AB104:AD104),0) -> -890579715 | AG104: =-163949065*1.575 -> -2.5821978e+08 | AJ104: =SUM(AG104:AI104) -> -2.5821978e+08 | AK104: 0 | AM104: =SUM(AK104:AL104) -> 0 | AN104: 0 | AP104: =SUM(AN104:AO104) -> 0 | AQ104: 0 | AS104: =SUM(AQ104:AR104) -> 0 | AT104: 0 | AV104: =SUM(AT104:AU104) -> 0 | AW104: 0 | AY104: =SUM(AW104:AX104) -> 0 | BC104: =ROUND(SUM(AJ104,AM104,AP104,AS104,AV104,AY104,AZ104),0) -> -258219777 | BF104: =ROUND(SUM(BC104:BE104),0) -> -258219777
B105: - Current year - OCI Emben | E105: =SUM('Consol SoPL-OCI 23 & 22'!D66:D67) -> -6.1470357e+08 | H105: =SUM(E105:G105) -> -6.1470357e+08 | I105: =-534033979*1.575 -> -8.4110352e+08 | K105: =SUM(I105:J105) -> -8.4110352e+08 | L105: 0 | M105: =SUM(L105:L105) -> 0 | N105: =SUM(L105:M105) -> 0 | O105: 0 | Q105: =SUM(O105:P105) -> 0 | R105: ='Consol SoPL-OCI 23 & 22'!AC70 -> 0 | T105: =SUM(R105:S105) -> 0 | U105: 0 | W105: =SUM(U105:V105) -> 0 | AB105: =SUM(H105,K105,X105,Y105,Z105:AA105,N105,Q105,T105,W105) -> -1.4558071e+09 | AC105: ='Elimination 23'!G23 -> 8.4110352e+08 | AE105: =ROUND(SUM(AB105:AD105),0) -> -614703573 | AG105: =ROUND(SUM('Consol SoPL-OCI 23 & 22'!AE66:AE67),0) -> -632359938 | AJ105: =SUM(AG105:AI105) -> -632359938 | AK105: =SUM('Consol SoPL-OCI 23 & 22'!AI66:AI67) -> -1.7373619e+09 | AM105: =SUM(AK105:AL105) -> -1.7373619e+09 | AN105: ='Consol SoPL-OCI 23 & 22'!BU70 -> 0 | AP105: =SUM(AN105:AO105) -> 0 | AQ105: ='Consol SoPL-OCI 23 & 22'!BX70 -> 0 | AS105: =SUM(AQ105:AR105) -> 0 | AT105: 0 | AV105: =SUM(AT105:AU105) -> 0 | AW105: ='Consol SoPL-OCI 23 & 22'!CD70 -> 0 | AY105: =SUM(AW105:AX105) -> 0 | BC105: =ROUND(SUM(AJ105,AM105,AP105,AS105,AV105,AY105,AZ105),0) -> -2369721868 | BD105: ='Elimination 22'!G26 -> 1.7373619e+09 | BF105: =ROUND(SUM(BC105:BE105),0) -> -632359938
B106: Capital Proforma | I106: 0 | K106: =SUM(I106:J106) -> 0 | L106: 0 | N106: =SUM(L106:M106) -> 0 | O106: 0 | Q106: =SUM(O106:P106) -> 0 | R106: 0 | T106: =SUM(R106:S106) -> 0 | U106: 0 | W106: =SUM(U106:V106) -> 0 | X106: -2.0937199e+09 | Y106: 5.7099484e+10 | AB106: =SUM(H106,K106,X106,Y106,Z106:AA106,N106,Q106,T106,W106) -> 5.5005765e+10 | AE106: =ROUND(SUM(AB106:AD106),0) -> 55005764507 | AK106: 0 | AM106: =SUM(AK106:AL106) -> 0 | AN106: 0 | AP106: =SUM(AN106:AO106) -> 0 | AQ106: 0 | AS106: =SUM(AQ106:AR106) -> 0 | AT106: 0 | AV106: =SUM(AT106:AU106) -> 0 | AW106: 0 | AY106: =SUM(AW106:AX106) -> 0 | AZ106: ='Proforma Adjustment'!P15 -> -2.0937199e+09 | BC106: =ROUND(SUM(AJ106,AM106,AP106,AS106,AV106,AY106,AZ106),0) -> -2093719896 | BF106: =ROUND(SUM(BC106:BE106),0) -> -2093719896
B109: Total equity attributable to the Owners of the Company | E109: =SUM(E92:E108) -> -9.0302894e+11 | H109: =SUM(H92:H108) -> -9.0302894e+11 | I109: =SUM(I92:I108) -> 4.494386e+11 | J109: =SUM(J92:J108) -> 0 | K109: =SUM(K92:K108) -> 4.494386e+11 | L109: =SUM(L92:L108) -> -2.4187787e+09 | M109: =SUM(M92:M108) -> 0 | N109: =SUM(N92:N108) -> -2.4187787e+09 | O109: =SUM(O92:O108) -> -1.6693366e+10 | ... Y109: =SUM(Y92:Y108) -> 5.7099484e+10 | AB109: =SUM(H109,K109,X109,Y109,Z109:AA109,N109,Q109,T109,W109) -> -3.1981145e+11 | AE109: =SUM(AE92:AE108) -> -828987845378 | AG109: =SUM(AG92:AG108) -> -2.060314e+11 | AH109: =SUM(AH92:AH108) -> 0 | AJ109: =SUM(AJ92:AJ108) -> -2.060314e+11 | AK109: =SUM(AK92:AK108) -> -1.4161349e+11 | AL109: =SUM(AL92:AL108) -> 0 | AM109: =SUM(AM92:AM108) -> -1.4161349e+11 | AN109: =SUM(AN92:AN108) -> 2.5899382e+08 | AO109: =SUM(AO92:AO108) -> 0 | AP109: =SUM(AP92:AP108) -> 2.5899382e+08 | AQ109: =SUM(AQ92:AQ108) -> -1.3908025e+10 | ... AZ109: =SUM(AZ92:AZ108) -> -2.0937199e+09 | BC109: =SUM(BC92:BC108) -> -344680716220 | BF109: =SUM(BF92:BF108) -> -208125118344
...

Sheet Consol SoPL-OCI 23 & 22
C3: PT Dummy - C and Subsidiaries
C4: Matter:
C5: Consolidated Statement of Profit or Loss and Other Comprehensive Income
G9: Dummy - C | J9: Dummy - D | M9: Dummy - E | P9: Dummy F | S9: Dummy - A | V9: Dummy G | AH9: Dummy C | AK9: Dummy D | AN9: Dummy E | AQ9: Dummy F | AT9: Dummy A Consol | AW9: Dummy G
B11: Control | D11: =D86-'Consol SoFP 23 & 22'!E102 -> 0 | G11: =G86-'Consol SoFP 23 & 22'!H102 -> 0 | H11: =H86-'Consol SoFP 23 & 22'!I102 -> 0 | I11: =I86-'Consol SoFP 23 & 22'!J102 -> 0 | J11: =J86-'Consol SoFP 23 & 22'!K102 -> 0 | K11: =K86-'Consol SoFP 23 & 22'!L102 -> 0 | L11: =L86-'Consol SoFP 23 & 22'!M102 -> 0 | M11: =M86-'Consol SoFP 23 & 22'!N102 -> 0 | N11: =N86-'Consol SoFP 23 & 22'!O102 -> 0 | ... V11: =V86-'Consol SoFP 23 & 22'!W102 -> 0 | Z11: =Z86-'Consol SoFP 23 & 22'!AB102 -> -0.015380859 | AC11: =AC86-'Consol SoFP 23 & 22'!AE102 -> -0.50476074 | AE11: =AE86-'Consol SoFP 23 & 22'!AG102 -> 0 | AF11: =AF86-'Consol SoFP 23 & 22'!AH102 -> 0 | AG11: =AG86-'Consol SoFP 23 & 22'!AI102 -> 0 | AH11: =AH86-'Consol SoFP 23 & 22'!AJ102 -> 0 | AI11: =AI86-'Consol SoFP 23 & 22'!AK102 -> 0 | AJ11: =AJ86-'Consol SoFP 23 & 22'!AL102 -> 0 | AK11: =AK86-'Consol SoFP 23 & 22'!AM102 -> 0 | AL11: =AL86-'Consol SoFP 23 & 22'!AN102 -> 0 | ... AW11: =AW86-'Consol SoFP 23 & 22'!AY102 -> 0 | BA11: =BA86-'Consol SoFP 23 & 22'!BC102 -> -0.4732666 | BD11: =BD86-'Consol SoFP 23 & 22'!BF102 -> -0.32501221
B12: Description | D12: 45291 | E12: Adjustment Equity Method | F12: Adjustment at consol | G12: 45291 | H12: 45291 | I12: Adjustment at consol | J12: 45291 | K12: 45291 | L12: Adjustment at consol | M12: 45291 | N12: 45291 | O12: Adjustment at consol | P12: 45291 | Q12: 45291 | R12: Adjustment at consol | S12: 45291 | T12: 45291 | U12: Adjustment at consol | V12: 45291 | W12: Proforma Adjustment | X12: Adjustment/ Reclassification | Z12: Combined | AA12: Elimination Entries | AC12: Consolidated | AE12: 44926 | AF12: Adjustment Equity Method | AG12: Adjustment at consol | AH12: 44926 | AI12: 44926 | AJ12: Adjustment at consol | AK12: 44926 | AL12: 44926 | AM12: Adjustment at consol | AN12: 44926 | AO12: 44926 | AP12: Adjustment at consol | AQ12: 44926 | AR12: 44926 | AS12: Adjustment at consol | AT12: 44926 | AU12: 44926 | AV12: Adjustment at consol | AW12: 44926 | AX12: Proforma Adjustment | AY12: Adjustment/ Reclassification | BA12: Combined | BB12: Elimination Entries | BD12: Consolidated
D13: Statutory | G13: Group - to Dummy - C | H13: Statutory | J13: Group - to Dummy - C | K13: Statutory | M13: Group - to Dummy - C | N13: Statutory | P13: Group - to Dummy - C | Q13: Statutory | S13: Group - to Dummy - C | T13: Statutory | V13: Group - to Dummy - C | W13: 45291 | X13: Dr. | Y13: Cr. | Z13: 45291 | AA13: Dr. | AB13: Cr. | AC13: 45291 | AE13: Statutory | AH13: Group - to Dummy C | AI13: Statutory | AK13: Group - to Dummy C | AL13: Statutory | AN13: Group - to Dummy C | AO13: Statutory | AQ13: Group - to Dummy C | AR13: Statutory | AT13: Group - to Dummy C | AU13: Statutory | AW13: Group - to Dummy C | AX13: 44926 | AY13: Dr. | AZ13: Cr. | BA13: 44926 | BB13: Dr. | BC13: Cr. | BD13: 44926
A16: 1 | B16: Revenue | D16: -47509988566 | G16: -47509988566 | H16: -257476547236 | J16: -257476547236 | K16: -15350656851 | M16: -15350656851 | N16: -8440039495 | P16: -8440039495 | Q16: -584705071240 | S16: -584705071240 | T16: 0 | V16: 0 | Z16: =ROUND(SUM(G16,J16,M16,P16,S16,V16,W16:Y16),0) -> -913482303388 | AC16: =SUM(Z16:AB16) -> -913482303388 | AE16: -74458078918 | AH16: -74458078918 | AI16: -2.0606117e+11 | AK16: -2.0606117e+11 | AL16: -1.3651164e+09 | AN16: -1.3651164e+09 | AO16: 0 | AQ16: 0 | AR16: -93058934331 | AT16: -93058934331 | AU16: 0 | AW16: 0 | BA16: =SUM(AH16,AK16,AN16,AQ16,AT16,AW16,AX16) -> -3.749433e+11 | BD16: =SUM(BA16:BC16) -> -3.749433e+11
A17: 2 | B17: Cost of Revenue | D17: 46445564176 | G17: 46445564176 | H17: 344915837698 | J17: 344915837698 | K17: 9679181517 | M17: 9679181517 | N17: 223360712 | P17: 223360712 | Q17: 565546756058 | S17: 565546756058 | T17: 0 | V17: 0 | Z17: =ROUND(SUM(G17,J17,M17,P17,S17,V17,W17:Y17),0) -> 966810700161 | AC17: =SUM(Z17:AB17) -> 966810700161 | AE17: 42627538009 | AH17: 42627538009 | AI17: 1.889777e+11 | AK17: 1.889777e+11 | AL17: 1.3449995e+09 | AN17: 1.3449995e+09 | AO17: 0 | AQ17: 0 | AR17: 91192305041 | AT17: 91192305041 | AU17: 0 | AW17: 0 | BA17: =SUM(AH17,AK17,AN17,AQ17,AT17,AW17,AX17) -> 3.2414255e+11 | BD17: =SUM(BA17:BC17) -> 3.2414255e+11
B19: GROSS PROFIT | D19: -1064424390 | G19: -1064424390 | H19: 87439290462 | J19: 87439290462 | K19: -5671475334 | M19: -5671475334 | N19: -8216678783 | P19: -8216678783 | Q19: -19158315182 | S19: -19158315182 | T19: 0 | V19: 0 | Z19: =SUM(Z15:Z18) -> 53328396773 | AC19: =SUM(AC15:AC18) -> 53328396773 | AE19: =SUM(AE15:AE18) -> -31830540909 | AH19: =SUM(AH15:AH18) -> -31830540909 | AI19: =SUM(AI15:AI18) -> -1.7083468e+10 | AK19: =SUM(AK15:AK18) -> -1.7083468e+10 | AL19: =SUM(AL15:AL18) -> -20116958 | AN19: =SUM(AN15:AN18) -> -20116958 | AO19: =SUM(AO15:AO18) -> 0 | AQ19: =SUM(AQ15:AQ18) -> 0 | AR19: =SUM(AR15:AR18) -> -1866629290 | AT19: =SUM(AT15:AT18) -> -1866629290 | AU19: =SUM(AU15:AU18) -> 0 | AW19: =SUM(AW15:AW18) -> 0 | BA19: =SUM(BA15:BA18) -> -5.0800755e+10 | BD19: =SUM(BD15:BD18) -> -5.0800755e+10
Q20: 0.032765776 | Z20: =S16/Z16 -> 0.64008363
B21: OPERATING EXPENSES
A22: 3 | B22: Commission and Incentives | D22: 0 | G22: 0 | H22: 0 | J22: 0 | K22: 0 | M22: 0 | N22: 0 | P22: 0 | Q22: 0 | S22: 0 | T22: 0 | V22: 0 | Z22: =ROUND(SUM(G22,J22,M22,P22,S22,V22,W22:Y22),0) -> 0 | AC22: =SUM(Z22:AB22) -> 0 | AE22: 0 | AH22: 0 | AI22: 0 | AK22: 0 | AL22: 0 | AN22: 0 | AO22: 0 | AQ22: 0 | AR22: 0 | AT22: 0 | AU22: 0 | AW22: 0 | BA22: =SUM(AH22,AK22,AN22,AQ22,AT22,AW22,AX22) -> 0 | BD22: =SUM(BA22:BC22) -> 0
B23: Sales and Marketing Expenses | D23: 31311860360 | G23: 31311860360 | H23: 800369664 | J23: 800369664 | K23: 0 | M23: 0 | N23: 0 | P23: 0 | Q23: 0 | S23: 0 | T23: 0 | V23: 0 | Z23: =ROUND(SUM(G23,J23,M23,P23,S23,V23,W23:Y23),0) -> 32112230024 | AC23: =SUM(Z23:AB23) -> 32112230024 | AE23: 23065709441 | AH23: 23065709441 | AI23: 3.2949847e+08 | AK23: 3.2949847e+08 | AL23: 0 | AN23: 0 | AO23: 0 | AQ23: 0 | AR23: 0 | AT23: 0 | AU23: 0 | AW23: 0 | BA23: =SUM(AH23,AK23,AN23,AQ23,AT23,AW23,AX23) -> 2.3395208e+10 | BD23: =SUM(BA23:BC23) -> 2.3395208e+10
A24: 4 | B24: General and Administrasi Expenses | D24: 270320702589 | G24: 270320702589 | H24: 446947159360 | I24: 0 | J24: 446947159360 | K24: 2627783321 | L24: 0 | M24: 2627783321 | N24: 7277775032 | P24: 7277775032 | Q24: 7.2580062e+10 | S24: 7.2580062e+10 | T24: 0 | V24: 0 | Z24: =ROUND(SUM(G24,J24,M24,P24,S24,V24,W24:Y24),0) -> 799753482326 | AC24: =SUM(Z24:AB24) -> 799753482326 | AE24: 180158681166 | AH24: 180158681166 | AI24: 3.7802954e+11 | AK24: 3.7802954e+11 | AL24: 7673077.1 | AN24: 7673077.1 | AO24: 574254170 | AQ24: 574254170 | AR24: 8.5334442e+09 | AT24: 8.5334442e+09 | AU24: 0 | AW24: 0 | BA24: =SUM(AH24,AK24,AN24,AQ24,AT24,AW24,AX24) -> 5.673036e+11 | BD24: =SUM(BA24:BC24) -> 5.673036e+11
B25: Depreciation and Amortization | D25: 17514686287 | G25: 17514686287 | H25: 13100761494 | J25: 13100761494 | K25: 7442480 | M25: 7442480 | N25: 0 | P25: 0 | Q25: 0 | S25: 0 | T25: 0 | V25: 0 | Z25: =ROUND(SUM(G25,J25,M25,P25,S25,V25,W25:Y25),0) -> 30622890261 | AC25: =SUM(Z25:AB25) -> 30622890261 | AE25: 174853015 | AH25: 174853015 | AI25: 9.0402171e+09 | AK25: 9.0402171e+09 | AL25: 0 | AN25: 0 | AO25: 0 | AQ25: 0 | AR25: 0 | AT25: 0 | AU25: 0 | AW25: 0 | BA25: =SUM(AH25,AK25,AN25,AQ25,AT25,AW25,AX25) -> 9.2150701e+09 | BD25: =SUM(BA25:BC25) -> 9.2150701e+09
B26: Loss (Gain) on revaluation and impairment financial assets | D26: -3.7967102e+09 | F26: 0 | G26: -3.7967102e+09 | H26: 2883155094 | J26: 2883155094 | K26: 0 | M26: 0 | N26: 0 | P26: 0 | Q26: 2813013954 | S26: 2813013954 | T26: 0 | V26: 0 | Z26: =ROUND(SUM(G26,J26,M26,P26,S26,V26,W26:Y26),0) -> 1899458800 | AB26: ='Elimination 23'!H110 -> 0 | AC26: =SUM(Z26:AB26) -> 1899458800 | AE26: 8.7289589e+09 | AH26: 8.7289589e+09 | AI26: 0 | AK26: 0 | AL26: 0 | AN26: 0 | AO26: 0 | AQ26: 0 | AR26: 32139141056 | AT26: 32139141056 | AU26: 0 | AW26: 0 | BA26: =SUM(AH26,AK26,AN26,AQ26,AT26,AW26,AX26) -> 4.08681e+10 | BB26: ='Elimination 22'!H84 -> -8.7289589e+09 | BC26: ='Elimination 22'!G86 -> 8.7289589e+09 | BD26: =SUM(BA26:BC26) -> 4.08681e+10
B27: Impairment loss on property and equipment | D27: 0 | G27: 0 | H27: 32453747018 | J27: 32453747018 | K27: 0 | M27: 0 | N27: 0 | P27: 0 | Q27: 0 | S27: 0 | T27: 0 | V27: 0 | Z27: =ROUND(SUM(G27,J27,M27,P27,S27,V27,W27:Y27),0) -> 32453747018 | AC27: =SUM(Z27:AB27) -> 32453747018 | AE27: 0 | AH27: 0 | AI27: 0 | AK27: 0 | AL27: 0 | AN27: 0 | AO27: 0 | AQ27: 0 | AR27: -1.3268913e+09 | AT27: -1.3268913e+09 | AU27: 0 | AW27: 0 | BA27: =SUM(AH27,AK27,AN27,AQ27,AT27,AW27,AX27) -> -1.3268913e+09 | BD27: =SUM(BA27:BC27) -> -1.3268913e+09
B28: Others, net | D28: 5.0219646e+09 | G28: 5.0219646e+09 | H28: -6127204538 | J28: -6127204538 | K28: 0 | M28: 0 | N28: -60575066 | P28: -60575066 | Q28: 1.5152247e+10 | S28: 1.5152247e+10 | T28: 0 | V28: 0 | Z28: =ROUND(SUM(G28,J28,M28,P28,S28,V28,W28:Y28),0) -> 13986431727 | AC28: =SUM(Z28:AB28) -> 13986431727 | AE28: -5.3015383e+09 | AH28: -5.3015383e+09 | AI28: 75330718 | AK28: 75330718 | AL28: 0 | AN28: 0 | AO28: 244988 | AQ28: 244988 | AR28: 0 | AT28: 0 | AU28: 0 | AW28: 0 | BA28: =SUM(AH28,AK28,AN28,AQ28,AT28,AW28,AX28) -> -5.2259626e+09 | BD28: =SUM(BA28:BC28) -> -5.2259626e+09
B30: TOTAL OPERATING EXPENSES | D30: 3.203725e+11 | G30: 3.203725e+11 | H30: 490057988092 | J30: 490057988092 | K30: 2635225801 | M30: 2635225801 | N30: 7217199966 | P30: 7217199966 | Q30: 9.0545323e+10 | S30: 9.0545323e+10 | T30: 0 | V30: 0 | Z30: =SUM(Z21:Z29) -> 910828240156 | AC30: =SUM(AC21:AC29) -> 910828240156 | AE30: =SUM(AE21:AE29) -> 2.0682666e+11 | AH30: =SUM(AH21:AH29) -> 2.0682666e+11 | AI30: =SUM(AI21:AI29) -> 3.8747459e+11 | AK30: =SUM(AK21:AK29) -> 3.8747459e+11 | AL30: =SUM(AL21:AL29) -> 7673077.1 | AN30: =SUM(AN21:AN29) -> 7673077.1 | AO30: =SUM(AO21:AO29) -> 574499158 | AQ30: =SUM(AQ21:AQ29) -> 574499158 | AR30: =SUM(AR21:AR29) -> 3.9345694e+10 | AT30: =SUM(AT21:AT29) -> 3.9345694e+10 | AU30: =SUM(AU21:AU29) -> 0 | AW30: =SUM(AW21:AW29) -> 0 | BA30: =SUM(BA21:BA29) -> 6.3422912e+11 | BD30: =SUM(BD21:BD29) -> 6.3422912e+11
D31: ^ | G31: ^ | H31: ^ | J31: ^ | K31: ^ | M31: ^ | N31: ^ | P31: ^ | Q31: ^ | S31: ^ | T31: ^ | V31: ^ | Z31: ^ | AC31: ^ | AE31: ^ | AH31: ^ | AI31: ^ | AK31: ^ | AL31: ^ | AN31: ^ | AO31: ^ | AQ31: ^ | AR31: ^ | AT31: ^ | AU31: ^ | AW31: ^ | BA31: ^ | BD31: ^
